Workbook

Sheet Dashboard
B1: LIVE PORTFOLIO DASHBOARD · ₹1 Crore, 3-Year Plan
B2: Pick an investor, then type any override in the yellow column. Every number, table and chart on this page recalculates instantly.
B4: SELECT INVESTOR ▸ | C4: Vikram | D4: =INDEX('Investor Personas'!$B$3:$B$6,Dash_Calc!$B$1)&" · "&INDEX('Investor Personas'!$E$3:$E$6,Dash_Calc!$B$1)&" risk" -> The Momentum Maverick · Very High risk | H4: PROJECTED VALUE | J4: EXPECTED CAGR | L4: REQUIRED CAGR | N4: PROBABILITY OF TARGET | P4: PORTFOLIO BETA | R4: VOLATILITY (5Y)
H5: =Dash_Calc!B30 -> 14451037 | J5: =Dash_Calc!B31 -> 0.13057575 | L5: =Dash_Calc!B32 -> 0.29066288 | N5: =Dash_Calc!B37 -> 0.078015433 | P5: =Dash_Calc!B34 -> 0.9695613 | R5: =Dash_Calc!B35 -> 0.16169608
B6: INVESTOR POLICY | C6: Preset | D6: Your override | E6: In use
B7: Corpus (₹) | C7: ='Investor Personas'!$C$1 -> 10000000 | E7: =IF(D7="",C7,D7) -> 10000000 | H7: ="vs target "&TEXT($E$8,"₹#,##0") -> vs target ₹21,500,000 | J7: ="model central estimate" -> model central estimate | L7: ="to hit the target" -> to hit the target | N7: ="lognormal, 5Y volatility" -> lognormal, 5Y volatility | P7: ="1.00 = moves with NIFTY" -> 1.00 = moves with NIFTY | R7: ="annualised, monthly data" -> annualised, monthly data
B8: Target corpus (₹) | C8: =INDEX('Investor Personas'!$C$3:$C$6,Dash_Calc!$B$1) -> 21500000 | E8: =IF(D8="",C8,D8) -> 21500000
B9: Horizon (years) | C9: ='Investor Personas'!$F$1 -> 3 | E9: =IF(D9="",C9,D9) -> 3 | H9: SURPLUS / (SHORTFALL) | J9: EXPECTED SHARPE | L9: STOCKS HELD | N9: LARGEST POSITION | P9: BACKTEST CAGR (5Y) | R9: MAX DRAWDOWN (5Y)
B10: Equity allocation | C10: =INDEX('Investor Personas'!$F$3:$F$6,Dash_Calc!$B$1) -> 0.95 | E10: =IF(D10="",C10,D10) -> 0.95 | H10: =Dash_Calc!B33 -> -7048963.3 | J10: =Dash_Calc!B36 -> 0.35298169 | L10: =Dash_Calc!B38 -> 12 | N10: =Dash_Calc!E28 -> 0.14383291 | P10: =Dash_Calc!E30 -> 0.10828102 | R10: =Dash_Calc!E31 -> -0.21017469
B11: Large-cap share of equity | C11: =INDEX(Dash_Calc!$B$41:$E$41,Dash_Calc!$B$1) -> 0.4 | E11: =IF(D11="",C11,D11) -> 0.4
B12: Mid-cap share of equity | C12: =INDEX(Dash_Calc!$B$42:$E$42,Dash_Calc!$B$1) -> 0.35 | E12: =IF(D12="",C12,D12) -> 0.35 | H12: =IF(Dash_Calc!B33>=0,"on track","gap to close") -> gap to close | J12: ="(Exp. CAGR − Rƒ) ÷ vol" -> (Exp. CAGR − Rƒ) ÷ vol | L12: ="of 14 in the universe" -> of 14 in the universe | N12: =Dash_Calc!E29 -> KEI | P12: ="NIFTY: "&TEXT(Dash_Calc!E32,"0.0%") -> NIFTY: 5.1% | R12: ="today's weights, hypothetical" -> today's weights, hypothetical
B13: Small-cap share of equity | C13: =INDEX(Dash_Calc!$B$43:$E$43,Dash_Calc!$B$1) -> 0.25 | E13: =IF(D13="",C13,D13) -> 0.25
B14: Max beta allowed per stock | C14: =INDEX('Investor Personas'!$I$3:$I$6,Dash_Calc!$B$1) -> 2.5 | E14: =IF(D14="",C14,D14) -> 2.5 | H14: =IF(Dash_Calc!B33>=0,"✔ ON TRACK — the model's expected path reaches the target.",IF(Dash_Calc!B37>=0.3,"◐ STRETCH — target is reachable only with above-model returns ("&TEXT(Dash_Calc!B37,"0%")&" probability).","✖ SHORTFALL — expected "&TEXT(Dash_Calc!B30,"₹#,##0")&" vs target "&TEXT($E$8,"₹#,##0")&". Raise equity / risk, lower the target, or extend the horizon.")) -> ✖ SHORTFALL — expected ₹14,451,037 vs target ₹21,500,000. Raise equity / risk, lower the target, or extend the horizon.
B15: Min score to qualify (0-100) | C15: =INDEX('Investor Personas'!$J$3:$J$6,Dash_Calc!$B$1) -> 40 | E15: =IF(D15="",C15,D15) -> 40
B16: Debt mix: 3Y G-Sec | C16: =INDEX(Dash_Calc!$B$44:$E$44,Dash_Calc!$B$1) -> 0 | E16: =IF(D16="",C16,D16) -> 0
B17: Debt mix: Reliance AAA NCD | C17: =INDEX(Dash_Calc!$B$45:$E$45,Dash_Calc!$B$1) -> 0 | E17: =IF(D17="",C17,D17) -> 0
B18: Debt mix: SMC A NCD | C18: =INDEX(Dash_Calc!$B$46:$E$46,Dash_Calc!$B$1) -> 1 | E18: =IF(D18="",C18,D18) -> 1
B19: Risk-free rate (10Y G-Sec) | C19: ='Investor Personas'!$C$13 -> 0.0735 | E19: =IF(D19="",C19,D19) -> 0.0735
B20: Equity risk premium | C20: ='Investor Personas'!$C$10 -> 0.07 | E20: =IF(D20="",C20,D20) -> 0.07
B21: Max score tilt (±) | C21: ='Investor Personas'!$C$12 -> 0.03 | E21: =IF(D21="",C21,D21) -> 0.03
B22: Segment split check | E22: =IF(ROUND(E11+E12+E13,4)=1,"✓ 100%","✗ "&TEXT(E11+E12+E13,"0%")) -> ✓ 100%
B23: FACTOR WEIGHTS (scoring) | C23: Preset | D23: Your override | E23: In use
B24: Market Cap | C24: =INDEX('Scoring Model'!$E$5:$H$5,Dash_Calc!$B$1) -> 0.07 | E24: =IF(D24="",C24,D24) -> 0.07
B25: Sales Growth YoY | C25: =INDEX('Scoring Model'!$E$6:$H$6,Dash_Calc!$B$1) -> 0.15 | E25: =IF(D25="",C25,D25) -> 0.15
B26: EPS Growth YoY | C26: =INDEX('Scoring Model'!$E$7:$H$7,Dash_Calc!$B$1) -> 0.16 | E26: =IF(D26="",C26,D26) -> 0.16
B27: ROE | C27: =INDEX('Scoring Model'!$E$8:$H$8,Dash_Calc!$B$1) -> 0.08 | E27: =IF(D27="",C27,D27) -> 0.08
B28: ROCE | C28: =INDEX('Scoring Model'!$E$9:$H$9,Dash_Calc!$B$1) -> 0.08 | E28: =IF(D28="",C28,D28) -> 0.08
B29: Trailing P/E | C29: =INDEX('Scoring Model'!$E$10:$H$10,Dash_Calc!$B$1) -> 0.04 | E29: =IF(D29="",C29,D29) -> 0.04
B30: PEG | C30: =INDEX('Scoring Model'!$E$11:$H$11,Dash_Calc!$B$1) -> 0.09 | E30: =IF(D30="",C30,D30) -> 0.09
B31: P/BV | C31: =INDEX('Scoring Model'!$E$12:$H$12,Dash_Calc!$B$1) -> 0.02 | E31: =IF(D31="",C31,D31) -> 0.02
B32: Beta | C32: =INDEX('Scoring Model'!$E$13:$H$13,Dash_Calc!$B$1) -> 0.03 | E32: =IF(D32="",C32,D32) -> 0.03
B33: Annualised SD | C33: =INDEX('Scoring Model'!$E$14:$H$14,Dash_Calc!$B$1) -> 0.03 | E33: =IF(D33="",C33,D33) -> 0.03
B34: Price vs 10M SMA | C34: =INDEX('Scoring Model'!$E$15:$H$15,Dash_Calc!$B$1) -> 0.09 | E34: =IF(D34="",C34,D34) -> 0.09
B35: 6M Momentum | C35: =INDEX('Scoring Model'!$E$16:$H$16,Dash_Calc!$B$1) -> 0.1 | E35: =IF(D35="",C35,D35) -> 0.1
B36: Debt / Equity | C36: =INDEX('Scoring Model'!$E$17:$H$17,Dash_Calc!$B$1) -> 0.06 | E36: =IF(D36="",C36,D36) -> 0.06
B37: Total weight (auto-normalised) | C37: =SUM(C24:C36) -> 1 | D37: =IF(ROUND(E37,4)=1,"✓","rescaled") -> ✓ | E37: =SUM(E24:E36) -> 1
B38: Tip: clear a yellow cell to go back to the preset. Weights that don't add to 100% are rescaled automatically.
B40: ASSET MIX | C40: Weight | D40: ₹ Invested
B41: Large Cap | C41: =Dash_Calc!E22 -> 0.3785887 | D41: =C41*$E$7 -> 3785887
B42: Mid Cap | C42: =Dash_Calc!E23 -> 0.33227356 | D42: =C42*$E$7 -> 3322735.6
B43: Small Cap | C43: =Dash_Calc!E24 -> 0.23745663 | D43: =C43*$E$7 -> 2374566.3
B44: Debt | C44: =Dash_Calc!E25 -> 0.05 | D44: =C44*$E$7 -> 500000
B45: Cash | C45: =Dash_Calc!E26 -> 0.001681106 | D45: =C45*$E$7 -> 16811.06
H50: LIVE HOLDINGS (all 14 stocks + 3 bonds; zero weight = not selected under current settings)
H51: Asset | I51: Segment / Type | J51: Sector / Rating | K51: Live Score | L51: Eligible | M51: Weight | N51: Price (₹) | O51: Units | P51: Invested (₹) | Q51: Exp. Return | R51: Value at Horizon (₹) | S51: Beta
H52: =Dash_Calc!A3 -> RELIANCE | I52: =Dash_Calc!B3 -> Large Cap | J52: =Dash_Calc!C3 -> Oil & Gas / Conglomerate | K52: =Dash_Calc!G3 -> 50.384615 | L52: =IF(Dash_Calc!H3=1,"✓","—") -> ✓ | M52: =Dash_Calc!K3 -> 0.049561928 | N52: =Dash_Calc!E3 -> 1174.6 | O52: =Dash_Calc!L3 -> 421 | P52: =Dash_Calc!M3 -> 494506.6 | Q52: =Dash_Calc!J3 -> 0.11392728 | R52: =Dash_Calc!N3 -> 683506.45 | S52: =Dash_Calc!D3 -> 0.99084157
H53: =Dash_Calc!A4 -> HDFCBANK | I53: =Dash_Calc!B4 -> Large Cap | J53: =Dash_Calc!C4 -> Private Sector Banking | K53: =Dash_Calc!G4 -> 55.403846 | L53: =IF(Dash_Calc!H4=1,"✓","—") -> ✓ | M53: =Dash_Calc!K4 -> 0.054499204 | N53: =Dash_Calc!E4 -> 710.7 | O53: =Dash_Calc!L4 -> 766 | P53: =Dash_Calc!M4 -> 544396.2 | Q53: =Dash_Calc!J4 -> 0.13087713 | R53: =Dash_Calc!N4 -> 787338.26 | S53: =Dash_Calc!D4 -> 0.884506
H54: =Dash_Calc!A5 -> INFY | I54: =Dash_Calc!B5 -> Large Cap | J54: =Dash_Calc!C5 -> IT Services | K54: =Dash_Calc!G5 -> 62.538462 | L54: =IF(Dash_Calc!H5=1,"✓","—") -> ✓ | M54: =Dash_Calc!K5 -> 0.061517324 | N54: =Dash_Calc!E5 -> 1088 | O54: =Dash_Calc!L5 -> 565 | P54: =Dash_Calc!M5 -> 614720 | Q54: =Dash_Calc!J5 -> 0.14926608 | R54: =Dash_Calc!N5 -> 933123.46 | S54: =Dash_Calc!D5 -> 0.75751049
H55: =Dash_Calc!A6 -> ITC | I55: =Dash_Calc!B6 -> Large Cap | J55: =Dash_Calc!C6 -> FMCG (Cigarettes, Foods, Agri) | K55: =Dash_Calc!G6 -> 42.75 | L55: =IF(Dash_Calc!H6=1,"✓","—") -> ✓ | M55: =Dash_Calc!K6 -> 0.042051971 | N55: =Dash_Calc!E6 -> 261.5 | O55: =Dash_Calc!L6 -> 1608 | P55: =Dash_Calc!M6 -> 420492 | Q55: =Dash_Calc!J6 -> 0.10106561 | R55: =Dash_Calc!N6 -> 561302.97 | S55: =Dash_Calc!D6 -> 0.81842432
H56: =Dash_Calc!A7 -> SUNPHARMA | I56: =Dash_Calc!B7 -> Large Cap | J56: =Dash_Calc!C7 -> Pharmaceuticals | K56: =Dash_Calc!G7 -> 61.519231 | L56: =IF(Dash_Calc!H7=1,"✓","—") -> ✓ | M56: =Dash_Calc!K7 -> 0.060514735 | N56: =Dash_Calc!E7 -> 1746.4 | O56: =Dash_Calc!L7 -> 346 | P56: =Dash_Calc!M7 -> 604254.4 | Q56: =Dash_Calc!J7 -> 0.13325309 | R56: =Dash_Calc!N7 -> 879428.54 | S56: =Dash_Calc!D7 -> 0.87112781
H57: =Dash_Calc!A8 -> MARUTI | I57: =Dash_Calc!B8 -> Large Cap | J57: =Dash_Calc!C8 -> Automobiles (Passenger Vehicles) | K57: =Dash_Calc!G8 -> 60.211538 | L57: =IF(Dash_Calc!H8=1,"✓","—") -> ✓ | M57: =Dash_Calc!K8 -> 0.059228395 | N57: =Dash_Calc!E8 -> 11178 | O57: =Dash_Calc!L8 -> 52 | P57: =Dash_Calc!M8 -> 581256 | Q57: =Dash_Calc!J8 -> 0.12271047 | R57: =Dash_Calc!N8 -> 822566.02 | S57: =Dash_Calc!D8 -> 0.68561437
H58: =Dash_Calc!A9 -> TATASTEEL | I58: =Dash_Calc!B9 -> Large Cap | J58: =Dash_Calc!C9 -> Metals & Mining (Steel) | K58: =Dash_Calc!G9 -> 53.5 | L58: =IF(Dash_Calc!H9=1,"✓","—") -> ✓ | M58: =Dash_Calc!K9 -> 0.052626444 | N58: =Dash_Calc!E9 -> 174.49 | O58: =Dash_Calc!L9 -> 3016 | P58: =Dash_Calc!M9 -> 526261.84 | Q58: =Dash_Calc!J9 -> 0.12405777 | R58: =Dash_Calc!N9 -> 747425.28 | S58: =Dash_Calc!D9 -> 1.1923044
H59: =Dash_Calc!A10 -> DABUR | I59: =Dash_Calc!B10 -> Mid Cap | J59: =Dash_Calc!C10 -> Personal Care & Ayurveda | K59: =Dash_Calc!G10 -> 44.403846 | L59: =IF(Dash_Calc!H10=1,"✓","—") -> ✓ | M59: =Dash_Calc!K10 -> 0.09326318 | N59: =Dash_Calc!E10 -> 388.4 | O59: =Dash_Calc!L10 -> 2401 | P59: =Dash_Calc!M10 -> 932548.4 | Q59: =Dash_Calc!J10 -> 0.097559613 | R59: =Dash_Calc!N10 -> 1232979.2 | S59: =Dash_Calc!D10 -> 0.869804
H60: =Dash_Calc!A11 -> ASTRAL | I60: =Dash_Calc!B11 -> Mid Cap | J60: =Dash_Calc!C11 -> Building Materials (Pipes) | K60: =Dash_Calc!G11 -> 45.423077 | L60: =IF(Dash_Calc!H11=1,"✓","—") -> ✓ | M60: =Dash_Calc!K11 -> 0.095403912 | N60: =Dash_Calc!E11 -> 1443.2 | O60: =Dash_Calc!L11 -> 661 | P60: =Dash_Calc!M11 -> 953955.2 | Q60: =Dash_Calc!J11 -> 0.11580232 | R60: =Dash_Calc!N11 -> 1325225.4 | S60: =Dash_Calc!D11 -> 0.69741418
H61: =Dash_Calc!A12 -> KEI | I61: =Dash_Calc!B12 -> Mid Cap | J61: =Dash_Calc!C12 -> Electricals (Cables & Wires) | K61: =Dash_Calc!G12 -> 68.480769 | L61: =IF(Dash_Calc!H12=1,"✓","—") -> ✓ | M61: =Dash_Calc!K12 -> 0.14383291 | N61: =Dash_Calc!E12 -> 4648 | O61: =Dash_Calc!L12 -> 309 | P61: =Dash_Calc!M12 -> 1436232 | Q61: =Dash_Calc!J12 -> 0.16872319 | R61: =Dash_Calc!N12 -> 2292765.2 | S61: =Dash_Calc!D12 -> 1.4331655
H62: =Dash_Calc!A13 -> BATAINDIA | I62: =Dash_Calc!B13 -> Small Cap | J62: =Dash_Calc!C13 -> Footwear & Retail | K62: =Dash_Calc!G13 -> 20.038462 | L62: =IF(Dash_Calc!H13=1,"✓","—") -> — | M62: =Dash_Calc!K13 -> 0 | N62: =Dash_Calc!E13 -> 619.35 | O62: =Dash_Calc!L13 -> 0 | P62: =Dash_Calc!M13 -> 0 | Q62: =Dash_Calc!J13 -> 0.076789637 | R62: =Dash_Calc!N13 -> 0 | S62: =Dash_Calc!D13 -> 1.2813252
H63: =Dash_Calc!A14 -> ZEEL | I63: =Dash_Calc!B14 -> Small Cap | J63: =Dash_Calc!C14 -> Media & Entertainment | K63: =Dash_Calc!G14 -> 20.423077 | L63: =IF(Dash_Calc!H14=1,"✓","—") -> — | M63: =Dash_Calc!K14 -> 0 | N63: =Dash_Calc!E14 -> 73.81 | O63: =Dash_Calc!L14 -> 0 | P63: =Dash_Calc!M14 -> 0 | Q63: =Dash_Calc!J14 -> 0.090070587 | R63: =Dash_Calc!N14 -> 0 | S63: =Dash_Calc!D14 -> 1.6233346
... H65: =Dash_Calc!A16 -> EIHOTEL | I65: =Dash_Calc!B16 -> Small Cap | J65: =Dash_Calc!C16 -> Hotels & Hospitality | K65: =Dash_Calc!G16 -> 55.153846 | L65: =IF(Dash_Calc!H16=1,"✓","—") -> ✓ | M65: =Dash_Calc!K16 -> 0.1230401 | N65: =Dash_Calc!E16 -> 291.95 | O65: =Dash_Calc!L16 -> 4214 | P65: =Dash_Calc!M16 -> 1230277.3 | Q65: =Dash_Calc!J16 -> 0.14405155 | R65: =Dash_Calc!N16 -> 1842212.8 | S65: =Dash_Calc!D16 -> 1.1041444
H66: =Dash_Calc!A17 -> GSEC-3Y | I66: =Dash_Calc!B17 -> Debt | J66: =Dash_Calc!C17 -> Sovereign (SOV) | K66: ="—" -> — | L66: =IF(Dash_Calc!H17=1,"✓","—") -> — | M66: =Dash_Calc!K17 -> 0 | N66: =Dash_Calc!E17 -> 100 | O66: =Dash_Calc!L17 -> 0 | P66: =Dash_Calc!M17 -> 0 | Q66: =Dash_Calc!J17 -> 0.0707 | R66: =Dash_Calc!N17 -> 0 | S66: =Dash_Calc!D17 -> 0
H67: =Dash_Calc!A18 -> RIL-NCD-2036 | I67: =Dash_Calc!B18 -> Debt | J67: =Dash_Calc!C18 -> CRISIL AAA / CARE AAA | K67: ="—" -> — | L67: =IF(Dash_Calc!H18=1,"✓","—") -> — | M67: =Dash_Calc!K18 -> 0 | N67: =Dash_Calc!E18 -> 100000 | O67: =Dash_Calc!L18 -> 0 | P67: =Dash_Calc!M18 -> 0 | Q67: =Dash_Calc!J18 -> 0.07875 | R67: =Dash_Calc!N18 -> 0 | S67: =Dash_Calc!D18 -> 0
H68: =Dash_Calc!A19 -> SMC-NCD-2029 | I68: =Dash_Calc!B19 -> Debt | J68: =Dash_Calc!C19 -> ICRA A (Stable) | K68: ="—" -> — | L68: =IF(Dash_Calc!H19=1,"✓","—") -> ✓ | M68: =Dash_Calc!K19 -> 0.05 | N68: =Dash_Calc!E19 -> 1000 | O68: =Dash_Calc!L19 -> 500 | P68: =Dash_Calc!M19 -> 500000 | Q68: =Dash_Calc!J19 -> 0.0945 | R68: =Dash_Calc!N19 -> 655567.33 | S68: =Dash_Calc!D19 -> 0
H69: TOTAL | M69: =SUM(M52:M68) -> 1 | P69: =SUM(P52:P68) -> 9983188.9 | R69: =SUM(R52:R68) -> 14430402
B71: How it works: Live Score = Σ(factor percentile score × in-use weight) ÷ total weight. Stocks qualify if score ≥ minimum and beta ≤ cap. Equity % × segment share is spread across qualifying stocks in proportion to score; debt follows the debt mix. Expected return = 50% CAPM (Rƒ + β × ERP) + 50% (dividend yield + sustainable growth) ± score tilt.

Sheet Master Fund Sheet
A1: S.No | B1: Type of Asset | C1: Asset Name | D1: Company | E1: Industry | F1: Price 30-Sep-2021 | G1: Price 31-Dec-2025 | H1: Price 31-Jul-2026 | I1: Current Price 14-Oct-2026 | J1: Change Since 1 Aug | K1: % Change in 2026 | L1: % Change since Sep-2021 | M1: CAGR 5Y | N1: CAGR 3Y | O1: CAGR 1Y | P1: Market Cap (₹ Cr) | Q1: EPS (TTM) | R1: Trailing P/E | S1: ROCE | T1: ROE | U1: Book Value / Share | V1: P/BV | W1: Sales Growth YoY | X1: EPS Growth YoY | Y1: Profit CAGR 3Y | Z1: PEG | AA1: Debt / Equity | AB1: Dividend Yield | AC1: 10M SMA | AD1: Price vs 10M SMA | AE1: 6M Momentum | AF1: Trend Signal | AG1: EPS FY25 | AH1: EPS FY26 | AI1: Data Source / Note
A2: 1 | B2: =IF(P2>=100000,"Large Cap",IF(P2>=30000,"Mid Cap","Small Cap")) -> Large Cap | C2: RELIANCE | D2: Reliance Industries Ltd | E2: Oil & Gas / Conglomerate | F2: =Price_Data!B2 -> 1141.01 | G2: =Price_Data!B53 -> 1563.17 | H2: =Price_Data!B60 -> 1307.8 | I2: 1174.6 | J2: =IFERROR((I2-H2)/H2,"N/A") -> -0.10185044 | K2: =IFERROR((I2-G2)/G2,"N/A") -> -0.24857821 | L2: =IFERROR((I2-F2)/F2,"N/A") -> 0.029438831 | M2: =(Price_Data!B62/Price_Data!B2)^(1/5)-1 -> 0.0079343677 | N2: =(Price_Data!B62/Price_Data!B26)^(1/3)-1 -> 0.008125217 | O2: =Price_Data!B62/Price_Data!B50-1 -> -0.12574021 | P2: 1591358 | Q2: 55.22 | R2: =IF(Q2>0,I2/Q2,"N/A") -> 21.271279 | S2: 0.103 | T2: 0.0891 | U2: 668 | V2: =I2/U2 -> 1.7583832 | W2: 0.15 | X2: =IF(AG2>0,AH2/AG2-1,"N/A") -> 0.15970468 | Y2: 0.05 | Z2: =IF(AND(Y2>0,ISNUMBER(R2)),R2/(Y2*100),"N/A") -> 4.2542557 | AA2: 0.446 | AB2: 0.0051 | AC2: =AVERAGE(Price_Data!B53:B62) -> 1348.238 | AD2: =I2/AC2-1 -> -0.12878883 | AE2: =Price_Data!B62/Price_Data!B56-1 -> -0.11266268 | AF2: =IF(AD2>0,"Uptrend","Downtrend") -> Downtrend | AG2: 51.47 | AH2: 59.69 | AI2: Screener (consolidated), 14-Oct-2026
A3: 2 | B3: =IF(P3>=100000,"Large Cap",IF(P3>=30000,"Mid Cap","Small Cap")) -> Large Cap | C3: HDFCBANK | D3: HDFC Bank Ltd | E3: Private Sector Banking | F3: =Price_Data!C2 -> 746.28 | G3: =Price_Data!C53 -> 975.07 | H3: =Price_Data!C60 -> 748.15 | I3: 710.7 | J3: =IFERROR((I3-H3)/H3,"N/A") -> -0.050056807 | K3: =IFERROR((I3-G3)/G3,"N/A") -> -0.27112925 | L3: =IFERROR((I3-F3)/F3,"N/A") -> -0.047676475 | M3: =(Price_Data!C62/Price_Data!C2)^(1/5)-1 -> -0.010280502 | N3: =(Price_Data!C62/Price_Data!C26)^(1/3)-1 -> -0.010156542 | O3: =Price_Data!C62/Price_Data!C50-1 -> -0.24246149 | P3: 1095493 | Q3: 51.35 | R3: =IF(Q3>0,I3/Q3,"N/A") -> 13.840312 | S3: 0.0702 | T3: 0.136 | U3: 390 | V3: =I3/U3 -> 1.8223077 | W3: 0.03 | X3: =IF(AG3>0,AH3/AG3-1,"N/A") -> 0.067661046 | Y3: 0.18 | Z3: =IF(AND(Y3>0,ISNUMBER(R3)),R3/(Y3*100),"N/A") -> 0.7689062 | AA3: Bank | AB3: 0.0183 | AC3: =AVERAGE(Price_Data!C53:C62) -> 793.754 | AD3: =I3/AC3-1 -> -0.10463443 | AE3: =Price_Data!C62/Price_Data!C56-1 -> -0.01521573 | AF3: =IF(AD3>0,"Uptrend","Downtrend") -> Downtrend | AG3: 46.26 | AH3: 49.39 | AI3: Screener (consolidated), 14-Oct-2026. D/E not meaningful for a bank (deposits/borrowings are raw material) - scored neutral.
A4: 3 | B4: =IF(P4>=100000,"Large Cap",IF(P4>=30000,"Mid Cap","Small Cap")) -> Large Cap | C4: INFY | D4: Infosys Ltd | E4: IT Services | F4: =Price_Data!D2 -> 1459.05 | G4: =Price_Data!D53 -> 1581.18 | H4: =Price_Data!D60 -> 1130.1 | I4: 1088 | J4: =IFERROR((I4-H4)/H4,"N/A") -> -0.03725334 | K4: =IFERROR((I4-G4)/G4,"N/A") -> -0.3119063 | L4: =IFERROR((I4-F4)/F4,"N/A") -> -0.25430931 | M4: =(Price_Data!D62/Price_Data!D2)^(1/5)-1 -> -0.073869942 | N4: =(Price_Data!D62/Price_Data!D26)^(1/3)-1 -> -0.086931434 | O4: =Price_Data!D62/Price_Data!D50-1 -> -0.28480985 | P4: 441499 | Q4: 74.25 | R4: =IF(Q4>0,I4/Q4,"N/A") -> 14.653199 | S4: 0.4 | T4: 0.319 | U4: 225 | V4: =I4/U4 -> 4.8355556 | W4: 0.11 | X4: =IF(AG4>0,AH4/AG4-1,"N/A") -> 0.12857587 | Y4: 0.08 | Z4: =IF(AND(Y4>0,ISNUMBER(R4)),R4/(Y4*100),"N/A") -> 1.8316498 | AA4: 0.099 | AB4: 0.0441 | AC4: =AVERAGE(Price_Data!D53:D62) -> 1223.557 | AD4: =I4/AC4-1 -> -0.11078928 | AE4: =Price_Data!D62/Price_Data!D56-1 -> -0.18789978 | AF4: =IF(AD4>0,"Uptrend","Downtrend") -> Downtrend | AG4: 64.32 | AH4: 72.59 | AI4: Screener (consolidated), 14-Oct-2026
A5: 4 | B5: =IF(P5>=100000,"Large Cap",IF(P5>=30000,"Mid Cap","Small Cap")) -> Large Cap | C5: ITC | D5: ITC Ltd | E5: FMCG (Cigarettes, Foods, Agri) | F5: =Price_Data!E2 -> 185.94 | G5: =Price_Data!E53 -> 384.26 | H5: =Price_Data!E60 -> 281 | I5: 261.5 | J5: =IFERROR((I5-H5)/H5,"N/A") -> -0.069395018 | K5: =IFERROR((I5-G5)/G5,"N/A") -> -0.31947119 | L5: =IFERROR((I5-F5)/F5,"N/A") -> 0.40636765 | M5: =(Price_Data!E62/Price_Data!E2)^(1/5)-1 -> 0.071603145 | N5: =(Price_Data!E62/Price_Data!E26)^(1/3)-1 -> -0.11684886 | O5: =Price_Data!E62/Price_Data!E50-1 -> -0.31375366 | P5: 327297 | Q5: 15.84 | R5: =IF(Q5>0,I5/Q5,"N/A") -> 16.508838 | S5: 0.389 | T5: 0.293 | U5: 57.9 | V5: =I5/U5 -> 4.5164076 | W5: -0.03 | X5: =IF(AG5>0,AH5/AG5-1,"N/A") -> -0.40547353 | Y5: 0.03 | Z5: =IF(AND(Y5>0,ISNUMBER(R5)),R5/(Y5*100),"N/A") -> 5.5029461 | AA5: 0.033 | AB5: 0.0555 | AC5: =AVERAGE(Price_Data!E53:E62) -> 295.643 | AD5: =I5/AC5-1 -> -0.11548726 | AE5: =Price_Data!E62/Price_Data!E56-1 -> -0.061841682 | AF5: =IF(AD5>0,"Uptrend","Downtrend") -> Downtrend | AG5: 27.77 | AH5: 16.51 | AI5: Screener (consolidated), 14-Oct-2026. FY25 EPS inflated by one-time hotel-demerger gain, so YoY EPS growth is negative.
A6: 5 | B6: =IF(P6>=100000,"Large Cap",IF(P6>=30000,"Mid Cap","Small Cap")) -> Large Cap | C6: SUNPHARMA | D6: Sun Pharmaceutical Industries Ltd | E6: Pharmaceuticals | F6: =Price_Data!F2 -> 778.82 | G6: =Price_Data!F53 -> 1704.14 | H6: =Price_Data!F60 -> 1990.5 | I6: 1746.4 | J6: =IFERROR((I6-H6)/H6,"N/A") -> -0.1226325 | K6: =IFERROR((I6-G6)/G6,"N/A") -> 0.024798432 | L6: =IFERROR((I6-F6)/F6,"N/A") -> 1.2423667 | M6: =(Price_Data!F62/Price_Data!F2)^(1/5)-1 -> 0.18458013 | N6: =(Price_Data!F62/Price_Data!F26)^(1/3)-1 -> 0.17231688 | O6: =Price_Data!F62/Price_Data!F50-1 -> 0.14984144 | P6: 419399 | Q6: 50.41 | R6: =IF(Q6>0,I6/Q6,"N/A") -> 34.64392 | S6: 0.205 | T6: 0.16 | U6: 348 | V6: =I6/U6 -> 5.0183908 | W6: 0.11 | X6: =IF(AG6>0,AH6/AG6-1,"N/A") -> 0.050274424 | Y6: 0.13 | Z6: =IF(AND(Y6>0,ISNUMBER(R6)),R6/(Y6*100),"N/A") -> 2.6649169 | AA6: 0.055 | AB6: 0.0092 | AC6: =AVERAGE(Price_Data!F53:F62) -> 1801.767 | AD6: =I6/AC6-1 -> -0.030729279 | AE6: =Price_Data!F62/Price_Data!F56-1 -> 0.03651126 | AF6: =IF(AD6>0,"Uptrend","Downtrend") -> Downtrend | AG6: 45.55 | AH6: 47.84 | AI6: Screener (consolidated), 14-Oct-2026
A7: 6 | B7: =IF(P7>=100000,"Large Cap",IF(P7>=30000,"Mid Cap","Small Cap")) -> Large Cap | C7: MARUTI | D7: Maruti Suzuki India Ltd | E7: Automobiles (Passenger Vehicles) | F7: =Price_Data!G2 -> 7007.53 | G7: =Price_Data!G53 -> 16530.98 | H7: =Price_Data!G60 -> 14092.47 | I7: 11178 | J7: =IFERROR((I7-H7)/H7,"N/A") -> -0.20681045 | K7: =IFERROR((I7-G7)/G7,"N/A") -> -0.32381504 | L7: =IFERROR((I7-F7)/F7,"N/A") -> 0.59514123 | M7: =(Price_Data!G62/Price_Data!G2)^(1/5)-1 -> 0.11297156 | N7: =(Price_Data!G62/Price_Data!G26)^(1/3)-1 -> 0.051431807 | O7: =Price_Data!G62/Price_Data!G50-1 -> -0.24591767 | P7: 351130 | Q7: 455.91 | R7: =IF(Q7>0,I7/Q7,"N/A") -> 24.517997 | S7: 0.189 | T7: 0.143 | U7: 3408 | V7: =I7/U7 -> 3.2799296 | W7: 0.27 | X7: =IF(AG7>0,AH7/AG7-1,"N/A") -> 0.012359063 | Y7: 0.21 | Z7: =IF(AND(Y7>0,ISNUMBER(R7)),R7/(Y7*100),"N/A") -> 1.1675237 | AA7: 0.001 | AB7: 0.0125 | AC7: =AVERAGE(Price_Data!G53:G62) -> 13763.695 | AD7: =I7/AC7-1 -> -0.18786343 | AE7: =Price_Data!G62/Price_Data!G56-1 -> -0.017781221 | AF7: =IF(AD7>0,"Uptrend","Downtrend") -> Downtrend | AG7: 461.2 | AH7: 466.9 | AI7: Screener (consolidated), 14-Oct-2026
A8: 7 | B8: =IF(P8>=100000,"Large Cap",IF(P8>=30000,"Mid Cap","Small Cap")) -> Large Cap | C8: TATASTEEL | D8: Tata Steel Ltd | E8: Metals & Mining (Steel) | F8: =Price_Data!H2 -> 111.15 | G8: =Price_Data!H53 -> 176.44 | H8: =Price_Data!H60 -> 189.69 | I8: 174.49 | J8: =IFERROR((I8-H8)/H8,"N/A") -> -0.08013074 | K8: =IFERROR((I8-G8)/G8,"N/A") -> -0.011051916 | L8: =IFERROR((I8-F8)/F8,"N/A") -> 0.56986055 | M8: =(Price_Data!H62/Price_Data!H2)^(1/5)-1 -> 0.10642804 | N8: =(Price_Data!H62/Price_Data!H26)^(1/3)-1 -> 0.15063413 | O8: =Price_Data!H62/Price_Data!H50-1 -> 0.11453798 | P8: 217962 | Q8: 8.83 | R8: =IF(Q8>0,I8/Q8,"N/A") -> 19.761042 | S8: 0.125 | T8: 0.117 | U8: 81.8 | V8: =I8/U8 -> 2.1331296 | W8: 0.11 | X8: =IF(AG8>0,AH8/AG8-1,"N/A") -> 2.1569343 | Y8: 0.1 | Z8: =IF(AND(Y8>0,ISNUMBER(R8)),R8/(Y8*100),"N/A") -> 1.9761042 | AA8: 0.904 | AB8: 0.0229 | AC8: =AVERAGE(Price_Data!H53:H62) -> 191.9 | AD8: =I8/AC8-1 -> -0.090724336 | AE8: =Price_Data!H62/Price_Data!H56-1 -> -0.019576551 | AF8: =IF(AD8>0,"Uptrend","Downtrend") -> Downtrend | AG8: 2.74 | AH8: 8.65 | AI8: Screener (consolidated), 14-Oct-2026. FY24 loss -> FY26 EPS growth flattered by low base.
A9: 8 | B9: =IF(P9>=100000,"Large Cap",IF(P9>=30000,"Mid Cap","Small Cap")) -> Mid Cap | C9: DABUR | D9: Dabur India Ltd | E9: Personal Care & Ayurveda | F9: =Price_Data!I2 -> 580.63 | G9: =Price_Data!I53 -> 497.15 | H9: =Price_Data!I60 -> 421.45 | I9: 388.4 | J9: =IFERROR((I9-H9)/H9,"N/A") -> -0.078419741 | K9: =IFERROR((I9-G9)/G9,"N/A") -> -0.21874686 | L9: =IFERROR((I9-F9)/F9,"N/A") -> -0.33107142 | M9: =(Price_Data!I62/Price_Data!I2)^(1/5)-1 -> -0.081245076 | N9: =(Price_Data!I62/Price_Data!I26)^(1/3)-1 -> -0.10406588 | O9: =Price_Data!I62/Price_Data!I50-1 -> -0.21216267 | P9: 68960 | Q9: 11.11 | R9: =IF(Q9>0,I9/Q9,"N/A") -> 34.959496 | S9: 0.165 | T9: 0.1624 | U9: 64.38 | V9: =I9/U9 -> 6.0329295 | W9: 0.074 | X9: =IF(AG9>0,AH9/AG9-1,"N/A") -> 0.071356784 | Y9: 0.037 | Z9: =IF(AND(Y9>0,ISNUMBER(R9)),R9/(Y9*100),"N/A") -> 9.4485124 | AA9: 0.11 | AB9: 0.0203 | AC9: =AVERAGE(Price_Data!I53:I62) -> 438.722 | AD9: =I9/AC9-1 -> -0.11470134 | AE9: =Price_Data!I62/Price_Data!I56-1 -> -0.061921568 | AF9: =IF(AD9>0,"Uptrend","Downtrend") -> Downtrend | AG9: 9.95 | AH9: 10.66 | AI9: Stockanalysis.com (TTM Jun-2026; FY26 ratios) - Screener cache was stale. Mkt cap = 177.55 Cr shares x 14-Oct price. Profit CAGR 3Y = FY23 Rs1,701 Cr -> FY26 Rs1,895 Cr.
A10: 9 | B10: =IF(P10>=100000,"Large Cap",IF(P10>=30000,"Mid Cap","Small Cap")) -> Mid Cap | C10: ASTRAL | D10: Astral Ltd | E10: Building Materials (Pipes) | F10: =Price_Data!J2 -> 1603.58 | G10: =Price_Data!J53 -> 1386.32 | H10: =Price_Data!J60 -> 1446.33 | I10: 1443.2 | J10: =IFERROR((I10-H10)/H10,"N/A") -> -0.0021640981 | K10: =IFERROR((I10-G10)/G10,"N/A") -> 0.041029488 | L10: =IFERROR((I10-F10)/F10,"N/A") -> -0.10001372 | M10: =(Price_Data!J62/Price_Data!J2)^(1/5)-1 -> -0.030938491 | N10: =(Price_Data!J62/Price_Data!J26)^(1/3)-1 -> -0.10299846 | O10: =Price_Data!J62/Price_Data!J50-1 -> 0.0054660846 | P10: 38943 | Q10: 21.43 | R10: =IF(Q10>0,I10/Q10,"N/A") -> 67.344844 | S10: 0.192 | T10: 0.138 | U10: 151 | V10: =I10/U10 -> 9.5576159 | W10: 0.17 | X10: =IF(AG10>0,AH10/AG10-1,"N/A") -> 0.024102564 | Y10: 0.06 | Z10: =IF(AND(Y10>0,ISNUMBER(R10)),R10/(Y10*100),"N/A") -> 11.224141 | AA10: 0.062 | AB10: 0.0028 | AC10: =AVERAGE(Price_Data!J53:J62) -> 1489.782 | AD10: =I10/AC10-1 -> -0.031267662 | AE10: =Price_Data!J62/Price_Data!J56-1 -> -0.14161692 | AF10: =IF(AD10>0,"Uptrend","Downtrend") -> Downtrend | AG10: 19.5 | AH10: 19.97 | AI10: Screener (consolidated), 14-Oct-2026
A11: 10 | B11: =IF(P11>=100000,"Large Cap",IF(P11>=30000,"Mid Cap","Small Cap")) -> Mid Cap | C11: KEI | D11: KEI Industries Ltd | E11: Electricals (Cables & Wires) | F11: =Price_Data!K2 -> 920.36 | G11: =Price_Data!K53 -> 4454.93 | H11: =Price_Data!K60 -> 4999 | I11: 4648 | J11: =IFERROR((I11-H11)/H11,"N/A") -> -0.070214043 | K11: =IFERROR((I11-G11)/G11,"N/A") -> 0.043338504 | L11: =IFERROR((I11-F11)/F11,"N/A") -> 4.0501977 | M11: =(Price_Data!K62/Price_Data!K2)^(1/5)-1 -> 0.37081231 | N11: =(Price_Data!K62/Price_Data!K26)^(1/3)-1 -> 0.18985111 | O11: =Price_Data!K62/Price_Data!K50-1 -> 0.097966728 | P11: 44393 | Q11: 104.28 | R11: =IF(Q11>0,I11/Q11,"N/A") -> 44.572305 | S11: 0.2 | T11: 0.147 | U11: 697 | V11: =I11/U11 -> 6.6685796 | W11: 0.2 | X11: =IF(AG11>0,AH11/AG11-1,"N/A") -> 0.31819429 | Y11: 0.24 | Z11: =IF(AND(Y11>0,ISNUMBER(R11)),R11/(Y11*100),"N/A") -> 1.8571794 | AA11: 0.038 | AB11: 0.001 | AC11: =AVERAGE(Price_Data!K53:K62) -> 4834.123 | AD11: =I11/AC11-1 -> -0.038501916 | AE11: =Price_Data!K62/Price_Data!K56-1 -> 0.10326895 | AF11: =IF(AD11>0,"Uptrend","Downtrend") -> Downtrend | AG11: 72.88 | AH11: 96.07 | AI11: Screener (consolidated), 14-Oct-2026
A12: 11 | B12: =IF(P12>=100000,"Large Cap",IF(P12>=30000,"Mid Cap","Small Cap")) -> Small Cap | C12: BATAINDIA | D12: Bata India Ltd | E12: Footwear & Retail | F12: =Price_Data!L2 -> 1601.42 | G12: =Price_Data!L53 -> 899.98 | H12: =Price_Data!L60 -> 673.04 | I12: 619.35 | J12: =IFERROR((I12-H12)/H12,"N/A") -> -0.079772376 | K12: =IFERROR((I12-G12)/G12,"N/A") -> -0.31181804 | L12: =IFERROR((I12-F12)/F12,"N/A") -> -0.61324949 | M12: =(Price_Data!L62/Price_Data!L2)^(1/5)-1 -> -0.1731971 | N12: =(Price_Data!L62/Price_Data!L26)^(1/3)-1 -> -0.25578406 | O12: =Price_Data!L62/Price_Data!L50-1 -> -0.44349508 | P12: 7960 | Q12: 10.44 | R12: =IF(Q12>0,I12/Q12,"N/A") -> 59.324713 | S12: 0.113 | T12: 0.0847 | U12: 124.14 | V12: =I12/U12 -> 4.9891252 | W12: 0.0077 | X12: =IF(AG12>0,AH12/AG12-1,"N/A") -> -0.59424796 | Y12: -0.25 | Z12: =IF(AND(Y12>0,ISNUMBER(R12)),R12/(Y12*100),"N/A") -> N/A | AA12: 0.87 | AB12: 0.0145 | AC12: =AVERAGE(Price_Data!L53:L62) -> 700.465 | AD12: =I12/AC12-1 -> -0.11580165 | AE12: =Price_Data!L62/Price_Data!L56-1 -> 0.067215151 | AF12: =IF(AD12>0,"Uptrend","Downtrend") -> Downtrend | AG12: 25.73 | AH12: 10.44 | AI12: Stockanalysis.com (FY26, updated Aug-2026). Mkt cap = 12.85 Cr shares x 14-Oct price. D/E includes lease liabilities.
A13: 12 | B13: =IF(P13>=100000,"Large Cap",IF(P13>=30000,"Mid Cap","Small Cap")) -> Small Cap | C13: ZEEL | D13: Zee Entertainment Enterprises Ltd | E13: Media & Entertainment | F13: =Price_Data!M2 -> 284.62 | G13: =Price_Data!M53 -> 87.86 | H13: =Price_Data!M60 -> 111.88 | I13: 73.81 | J13: =IFERROR((I13-H13)/H13,"N/A") -> -0.34027529 | K13: =IFERROR((I13-G13)/G13,"N/A") -> -0.1599135 | L13: =IFERROR((I13-F13)/F13,"N/A") -> -0.74067177 | M13: =(Price_Data!M62/Price_Data!M2)^(1/5)-1 -> -0.23520826 | N13: =(Price_Data!M62/Price_Data!M26)^(1/3)-1 -> -0.33307119 | O13: =Price_Data!M62/Price_Data!M50-1 -> -0.32145786 | P13: 7089 | Q13: 2.13 | R13: =IF(Q13>0,I13/Q13,"N/A") -> 34.652582 | S13: 0.011 | T13: 0.0233 | U13: 121 | V13: =I13/U13 -> 0.61 | W13: 0.0242 | X13: =IF(AG13>0,AH13/AG13-1,"N/A") -> -0.59830269 | Y13: 0.04 | Z13: =IF(AND(Y13>0,ISNUMBER(R13)),R13/(Y13*100),"N/A") -> 8.6631455 | AA13: 0.02 | AB13: 0.027 | AC13: =AVERAGE(Price_Data!M53:M62) -> 88.357 | AD13: =I13/AC13-1 -> -0.16463891 | AE13: =Price_Data!M62/Price_Data!M56-1 -> 0.056911723 | AF13: =IF(AD13>0,"Uptrend","Downtrend") -> Downtrend | AG13: 7.07 | AH13: 2.84 | AI13: Stockanalysis.com (TTM Jun-2026). FY23 profit base was abnormally low, so 5Y profit CAGR (4%, Screener) is used for PEG.
A14: 13 | B14: =IF(P14>=100000,"Large Cap",IF(P14>=30000,"Mid Cap","Small Cap")) -> Small Cap | C14: JUSTDIAL | D14: Just Dial Ltd | E14: Internet / Local Search Services | F14: =Price_Data!N2 -> 989.2 | G14: =Price_Data!N53 -> 725.3 | H14: =Price_Data!N60 -> 716.7 | I14: 682.75 | J14: =IFERROR((I14-H14)/H14,"N/A") -> -0.04736989 | K14: =IFERROR((I14-G14)/G14,"N/A") -> -0.05866538 | L14: =IFERROR((I14-F14)/F14,"N/A") -> -0.30979579 | M14: =(Price_Data!N62/Price_Data!N2)^(1/5)-1 -> -0.076030608 | N14: =(Price_Data!N62/Price_Data!N26)^(1/3)-1 -> -0.029783273 | O14: =Price_Data!N62/Price_Data!N50-1 -> -0.19663531 | P14: 5807 | Q14: 59.21 | R14: =IF(Q14>0,I14/Q14,"N/A") -> 11.530991 | S14: 0.058 | T14: 0.1023 | U14: 601 | V14: =I14/U14 -> 1.1360233 | W14: 0.0727 | X14: =IF(AG14>0,AH14/AG14-1,"N/A") -> -0.14922114 | Y14: 0.45 | Z14: =IF(AND(Y14>0,ISNUMBER(R14)),R14/(Y14*100),"N/A") -> 0.25624425 | AA14: 0.02 | AB14: 0 | AC14: =AVERAGE(Price_Data!N53:N62) -> 610.325 | AD14: =I14/AC14-1 -> 0.11866628 | AE14: =Price_Data!N62/Price_Data!N56-1 -> 0.35755044 | AF14: =IF(AD14>0,"Uptrend","Downtrend") -> Uptrend | AG14: 68.69 | AH14: 58.44 | AI14: Stockanalysis.com (TTM Jun-2026). Cash-rich balance sheet depresses ROCE. Mkt cap = 8.5 Cr shares x 14-Oct price.
A15: 14 | B15: =IF(P15>=100000,"Large Cap",IF(P15>=30000,"Mid Cap","Small Cap")) -> Small Cap | C15: EIHOTEL | D15: EIH Ltd (The Oberoi Group) | E15: Hotels & Hospitality | F15: =Price_Data!O2 -> 127.24 | G15: =Price_Data!O53 -> 366.59 | H15: =Price_Data!O60 -> 327 | I15: 291.95 | J15: =IFERROR((I15-H15)/H15,"N/A") -> -0.10718654 | K15: =IFERROR((I15-G15)/G15,"N/A") -> -0.20360621 | L15: =IFERROR((I15-F15)/F15,"N/A") -> 1.2944829 | M15: =(Price_Data!O62/Price_Data!O2)^(1/5)-1 -> 0.18800268 | N15: =(Price_Data!O62/Price_Data!O26)^(1/3)-1 -> 0.10933147 | O15: =Price_Data!O62/Price_Data!O50-1 -> -0.15957239 | P15: 18286 | Q15: 11.38 | R15: =IF(Q15>0,I15/Q15,"N/A") -> 25.654657 | S15: 0.207 | T15: 0.145 | U15: 84.2 | V15: =I15/U15 -> 3.4673397 | W15: 0.08 | X15: =IF(AG15>0,AH15/AG15-1,"N/A") -> -0.14974619 | Y15: 0.25 | Z15: =IF(AND(Y15>0,ISNUMBER(R15)),R15/(Y15*100),"N/A") -> 1.0261863 | AA15: 0.048 | AB15: 0.0051 | AC15: =AVERAGE(Price_Data!O53:O62) -> 310.578 | AD15: =I15/AC15-1 -> -0.059978492 | AE15: =Price_Data!O62/Price_Data!O56-1 -> 0.10572509 | AF15: =IF(AD15>0,"Uptrend","Downtrend") -> Downtrend | AG15: 11.82 | AH15: 10.05 | AI15: Screener (consolidated), 14-Oct-2026
A17: S.No | B17: Type of Asset | C17: Asset Name | D17: Instrument | E17: Security | F17: Coupon (p.a.) | G17: Rating | H17: Face Value / Unit (₹) | I17: Yield to Maturity | J17: Annual Default Prob. (assumed) | K17: Loss Given Default | L17: Expected Credit Loss | M17: Credit-Adjusted Return | N17: Source
A18: 15 | B18: Government Bond | C18: GSEC-3Y | D18: 3-Year Government of India Security | E18: Sovereign | F18: 0.0707 | G18: Sovereign (SOV) | H18: 100 | I18: 0.0707 | J18: 0 | K18: 0 | L18: =J18*K18 -> 0 | M18: =I18-L18 -> 0.0707 | N18: 3Y G-Sec yield 7.07% on 13-Oct-2026 (Trading Economics). Bought at par via RBI Retail Direct.
A19: 16 | B19: Corporate Bond | C19: RIL-NCD-2036 | D19: Reliance Industries 7.90% NCD (Oct-2036) | E19: Senior | F19: 0.079 | G19: CRISIL AAA / CARE AAA | H19: 100000 | I19: 0.079 | J19: 0.0005 | K19: 0.5 | L19: =J19*K19 -> 0.00025 | M19: =I19-L19 -> 0.07875 | N19: Rs13,008 Cr NCDs allotted 1-Oct-2026 at 7.90% (PSU Connect). Sold after 3 yrs; assumes flat yields.
A20: 17 | B20: Corporate Bond | C20: SMC-NCD-2029 | D20: SMC Global Securities NCD Series III (36M) | E20: Secured | F20: 0.0975 | G20: ICRA A (Stable) | H20: 1000 | I20: 0.0975 | J20: 0.006 | K20: 0.5 | L20: =J20*K20 -> 0.003 | M20: =I20-L20 -> 0.0945 | N20: Public issue 5-9 Oct 2026, 36-month annual-pay series (Chanakya Nipothi).
A22: S.No | B22: Type of Asset | C22: Asset Name | D22: Benchmark | F22: Price 30-Sep-2021 | G22: Price 31-Dec-2025 | H22: Price 31-Jul-2026 | I22: Current 14-Oct-2026 | J22: Change Since 1 Aug | K22: % Change in 2026 | L22: % Change since Sep-2021 | M22: CAGR 5Y | N22: CAGR 3Y | O22: CAGR 1Y
A23: 18 | B23: Index | C23: NIFTY_50 | D23: NIFTY 50 (^NSEI) | F23: =Price_Data!P2 -> 17618.15 | G23: =Price_Data!P53 -> 26129.6 | H23: =Price_Data!P60 -> 24383.6 | I23: 22622.7 | J23: =(I23-H23)/H23 -> -0.072216572 | K23: =(I23-G23)/G23 -> -0.13421178 | L23: =(I23-F23)/F23 -> 0.2840565 | M23: =(Price_Data!P62/Price_Data!P2)^(1/5)-1 -> 0.051255274 | N23: =(Price_Data!P62/Price_Data!P26)^(1/3)-1 -> 0.048252202 | O23: =Price_Data!P62/Price_Data!P50-1 -> -0.080884235
A25: Legend: blue = sourced input (Screener / Yahoo / Stockanalysis / RBI), black = formula, green = link to another sheet, yellow = live price to update. Cap segment is classified by formula: ≥ ₹1,00,000 Cr Large, ≥ ₹30,000 Cr Mid, else Small.

Sheet Portfolio_History
A1: Snapshot_Date | B1: Persona | C1: Asset_Ticker | D1: Asset_Class | E1: Cap_Sector | F1: Weight | G1: Allocated_Capital | H1: Live_Price | I1: Units_Held | J1: Beta | K1: Target_Price_2029 | L1: Exp_Annual_Return | M1: Current_Position_Value
A2: 46309 | B2: Vikram | C2: KEI | D2: Equity | E2: Mid Cap / Electricals (Cables & Wires) | F2: 0.14 | G2: 1400000 | H2: 4648 | I2: 301 | J2: 1.4331655 | K2: 7316.4879 | L2: 0.1632655 | M2: 1399048
A3: 46309 | B3: Vikram | C3: JUSTDIAL | D3: Equity | E3: Small Cap / Internet / Local Search Services | F3: 0.12 | G3: 1200000 | H3: 682.75 | I3: 1757 | J3: 1.2835508 | K3: 985.48313 | L3: 0.13013197 | M3: 1199591.8
A4: 46309 | B4: Vikram | C4: EIHOTEL | D4: Equity | E4: Small Cap / Hotels & Hospitality | F4: 0.12 | G4: 1200000 | H4: 291.95 | I4: 4110 | J4: 1.1041444 | K4: 434.59503 | L4: 0.1418054 | M4: 1199914.5
A5: 46309 | B5: Vikram | C5: ASTRAL | D5: Equity | E5: Mid Cap / Building Materials (Pipes) | F5: 0.1 | G5: 1000000 | H5: 1443.2 | I5: 692 | J5: 0.69741418 | K5: 1999.6182 | L5: 0.1148254 | M5: 998694.4
A6: 46309 | B6: Vikram | C6: DABUR | D6: Equity | E6: Mid Cap / Personal Care & Ayurveda | F6: 0.09 | G6: 900000 | H6: 388.4 | I6: 2317 | J6: 0.869804 | K6: 514.98095 | L6: 0.098594228 | M6: 899922.8
A7: 46309 | B7: Vikram | C7: HDFCBANK | D7: Equity | E7: Large Cap / Private Sector Banking | F7: 0.06 | G7: 600000 | H7: 710.7 | I7: 844 | J7: 0.884506 | K7: 1033.7935 | L7: 0.13305021 | M7: 599830.8
A8: 46309 | B8: Vikram | C8: INFY | D8: Equity | E8: Large Cap / IT Services | F8: 0.06 | G8: 600000 | H8: 1088 | I8: 551 | J8: 0.75751049 | K8: 1662.3139 | L8: 0.15175839 | M8: 599488
A9: 46309 | B9: Vikram | C9: SUNPHARMA | D9: Equity | E9: Large Cap / Pharmaceuticals | F9: 0.06 | G9: 600000 | H9: 1746.4 | I9: 343 | J9: 0.87112781 | K9: 2536.9164 | L9: 0.13254155 | M9: 599015.2
A10: 46309 | B10: Vikram | C10: MARUTI | D10: Equity | E10: Large Cap / Automobiles (Passenger Vehicles) | F10: 0.06 | G10: 600000 | H10: 11178 | I10: 53 | J10: 0.68561437 | K10: 15934.448 | L10: 0.12544508 | M10: 592434
A11: 46309 | B11: Vikram | C11: RELIANCE | D11: Equity | E11: Large Cap / Oil & Gas / Conglomerate | F11: 0.05 | G11: 500000 | H11: 1174.6 | I11: 425 | J11: 0.99084157 | K11: 1634.2499 | L11: 0.11637344 | M11: 499205
A12: 46309 | B12: Vikram | C12: TATASTEEL | D12: Equity | E12: Large Cap / Metals & Mining (Steel) | F12: 0.05 | G12: 500000 | H12: 174.49 | I12: 2865 | J12: 1.1923044 | K12: 246.76838 | L12: 0.12246547 | M12: 499913.85
A13: 46309 | B13: Vikram | C13: ITC | D13: Equity | E13: Large Cap / FMCG (Cigarettes, Foods, Agri) | F13: 0.04 | G13: 400000 | H13: 261.5 | I13: 1529 | J13: 0.81842432 | K13: 353.57666 | L13: 0.10578484 | M13: 399833.5
... A56: 46309 | B56: Meera | C56: SMC-NCD-2029 | D56: Bonds | E56: ICRA A (Stable) / Corporate Bond | F56: 0.1 | G56: 1000000 | H56: 1000 | I56: 1000 | J56: 0 | K56: 1311.1347 | L56: 0.0945 | M56: 1000000
A58: Entry snapshot at the 14-Oct-2026 close. Append a new block of rows (same columns) at each review date with that day's prices to build the daily/weekly history.

Sheet Vikram
A1: Asset / Ticker | B1: Asset Class | C1: Cap / Sector | D1: Investor Score | E1: Weight | F1: Capital (₹) | G1: Current Price (₹) | H1: Units | I1: Invested (₹) | J1: Beta | K1: Exp. Annual Return | L1: Target Price Oct-2029 (₹) | M1: Value Oct-2029 (₹)
A2: KEI | B2: Equity | C2: ='Master Fund Sheet'!B11&" / "&'Master Fund Sheet'!E11 -> Mid Cap / Electricals (Cables & Wires) | D2: ='Scoring Model'!AD32 -> 68.480769 | E2: 0.14 | F2: =E2*'Investor Personas'!$C$1 -> 1400000 | G2: =IFERROR(INDEX('Master Fund Sheet'!$I$2:$I$15,MATCH(A2,'Master Fund Sheet'!$C$2:$C$15,0)),0) -> 4648 | H2: =IF(G2>0,ROUNDDOWN(F2/G2,0),0) -> 301 | I2: =H2*G2 -> 1399048 | J2: =IFERROR(INDEX('Risk Metrics'!$G$2:$G$15,MATCH(A2,'Risk Metrics'!$A$2:$A$15,0)),0) -> 1.4331655 | K2: =IFERROR(INDEX('Scoring Model'!$AQ$23:$AQ$36,MATCH(A2,'Scoring Model'!$A$23:$A$36,0)),0) -> 0.1632655 | L2: =G2*(1+K2)^'Investor Personas'!$F$1 -> 7316.4879 | M2: =I2*(1+K2)^'Investor Personas'!$F$1 -> 2202262.9
A3: JUSTDIAL | B3: Equity | C3: ='Master Fund Sheet'!B14&" / "&'Master Fund Sheet'!E14 -> Small Cap / Internet / Local Search Services | D3: ='Scoring Model'!AD35 -> 51.307692 | E3: 0.12 | F3: =E3*'Investor Personas'!$C$1 -> 1200000 | G3: =IFERROR(INDEX('Master Fund Sheet'!$I$2:$I$15,MATCH(A3,'Master Fund Sheet'!$C$2:$C$15,0)),0) -> 682.75 | H3: =IF(G3>0,ROUNDDOWN(F3/G3,0),0) -> 1757 | I3: =H3*G3 -> 1199591.8 | J3: =IFERROR(INDEX('Risk Metrics'!$G$2:$G$15,MATCH(A3,'Risk Metrics'!$A$2:$A$15,0)),0) -> 1.2835508 | K3: =IFERROR(INDEX('Scoring Model'!$AQ$23:$AQ$36,MATCH(A3,'Scoring Model'!$A$23:$A$36,0)),0) -> 0.13013197 | L3: =G3*(1+K3)^'Investor Personas'!$F$1 -> 985.48313 | M3: =I3*(1+K3)^'Investor Personas'!$F$1 -> 1731493.9
A4: EIHOTEL | B4: Equity | C4: ='Master Fund Sheet'!B15&" / "&'Master Fund Sheet'!E15 -> Small Cap / Hotels & Hospitality | D4: ='Scoring Model'!AD36 -> 55.153846 | E4: 0.12 | F4: =E4*'Investor Personas'!$C$1 -> 1200000 | G4: =IFERROR(INDEX('Master Fund Sheet'!$I$2:$I$15,MATCH(A4,'Master Fund Sheet'!$C$2:$C$15,0)),0) -> 291.95 | H4: =IF(G4>0,ROUNDDOWN(F4/G4,0),0) -> 4110 | I4: =H4*G4 -> 1199914.5 | J4: =IFERROR(INDEX('Risk Metrics'!$G$2:$G$15,MATCH(A4,'Risk Metrics'!$A$2:$A$15,0)),0) -> 1.1041444 | K4: =IFERROR(INDEX('Scoring Model'!$AQ$23:$AQ$36,MATCH(A4,'Scoring Model'!$A$23:$A$36,0)),0) -> 0.1418054 | L4: =G4*(1+K4)^'Investor Personas'!$F$1 -> 434.59503 | M4: =I4*(1+K4)^'Investor Personas'!$F$1 -> 1786185.6
A5: ASTRAL | B5: Equity | C5: ='Master Fund Sheet'!B10&" / "&'Master Fund Sheet'!E10 -> Mid Cap / Building Materials (Pipes) | D5: ='Scoring Model'!AD31 -> 45.423077 | E5: 0.1 | F5: =E5*'Investor Personas'!$C$1 -> 1000000 | G5: =IFERROR(INDEX('Master Fund Sheet'!$I$2:$I$15,MATCH(A5,'Master Fund Sheet'!$C$2:$C$15,0)),0) -> 1443.2 | H5: =IF(G5>0,ROUNDDOWN(F5/G5,0),0) -> 692 | I5: =H5*G5 -> 998694.4 | J5: =IFERROR(INDEX('Risk Metrics'!$G$2:$G$15,MATCH(A5,'Risk Metrics'!$A$2:$A$15,0)),0) -> 0.69741418 | K5: =IFERROR(INDEX('Scoring Model'!$AQ$23:$AQ$36,MATCH(A5,'Scoring Model'!$A$23:$A$36,0)),0) -> 0.1148254 | L5: =G5*(1+K5)^'Investor Personas'!$F$1 -> 1999.6182 | M5: =I5*(1+K5)^'Investor Personas'!$F$1 -> 1383735.8
A6: DABUR | B6: Equity | C6: ='Master Fund Sheet'!B9&" / "&'Master Fund Sheet'!E9 -> Mid Cap / Personal Care & Ayurveda | D6: ='Scoring Model'!AD30 -> 44.403846 | E6: 0.09 | F6: =E6*'Investor Personas'!$C$1 -> 900000 | G6: =IFERROR(INDEX('Master Fund Sheet'!$I$2:$I$15,MATCH(A6,'Master Fund Sheet'!$C$2:$C$15,0)),0) -> 388.4 | H6: =IF(G6>0,ROUNDDOWN(F6/G6,0),0) -> 2317 | I6: =H6*G6 -> 899922.8 | J6: =IFERROR(INDEX('Risk Metrics'!$G$2:$G$15,MATCH(A6,'Risk Metrics'!$A$2:$A$15,0)),0) -> 0.869804 | K6: =IFERROR(INDEX('Scoring Model'!$AQ$23:$AQ$36,MATCH(A6,'Scoring Model'!$A$23:$A$36,0)),0) -> 0.098594228 | L6: =G6*(1+K6)^'Investor Personas'!$F$1 -> 514.98095 | M6: =I6*(1+K6)^'Investor Personas'!$F$1 -> 1193210.9
A7: HDFCBANK | B7: Equity | C7: ='Master Fund Sheet'!B3&" / "&'Master Fund Sheet'!E3 -> Large Cap / Private Sector Banking | D7: ='Scoring Model'!AD24 -> 55.403846 | E7: 0.06 | F7: =E7*'Investor Personas'!$C$1 -> 600000 | G7: =IFERROR(INDEX('Master Fund Sheet'!$I$2:$I$15,MATCH(A7,'Master Fund Sheet'!$C$2:$C$15,0)),0) -> 710.7 | H7: =IF(G7>0,ROUNDDOWN(F7/G7,0),0) -> 844 | I7: =H7*G7 -> 599830.8 | J7: =IFERROR(INDEX('Risk Metrics'!$G$2:$G$15,MATCH(A7,'Risk Metrics'!$A$2:$A$15,0)),0) -> 0.884506 | K7: =IFERROR(INDEX('Scoring Model'!$AQ$23:$AQ$36,MATCH(A7,'Scoring Model'!$A$23:$A$36,0)),0) -> 0.13305021 | L7: =G7*(1+K7)^'Investor Personas'!$F$1 -> 1033.7935 | M7: =I7*(1+K7)^'Investor Personas'!$F$1 -> 872521.69
A8: INFY | B8: Equity | C8: ='Master Fund Sheet'!B4&" / "&'Master Fund Sheet'!E4 -> Large Cap / IT Services | D8: ='Scoring Model'!AD25 -> 62.538462 | E8: 0.06 | F8: =E8*'Investor Personas'!$C$1 -> 600000 | G8: =IFERROR(INDEX('Master Fund Sheet'!$I$2:$I$15,MATCH(A8,'Master Fund Sheet'!$C$2:$C$15,0)),0) -> 1088 | H8: =IF(G8>0,ROUNDDOWN(F8/G8,0),0) -> 551 | I8: =H8*G8 -> 599488 | J8: =IFERROR(INDEX('Risk Metrics'!$G$2:$G$15,MATCH(A8,'Risk Metrics'!$A$2:$A$15,0)),0) -> 0.75751049 | K8: =IFERROR(INDEX('Scoring Model'!$AQ$23:$AQ$36,MATCH(A8,'Scoring Model'!$A$23:$A$36,0)),0) -> 0.15175839 | L8: =G8*(1+K8)^'Investor Personas'!$F$1 -> 1662.3139 | M8: =I8*(1+K8)^'Investor Personas'!$F$1 -> 915934.97
A9: SUNPHARMA | B9: Equity | C9: ='Master Fund Sheet'!B6&" / "&'Master Fund Sheet'!E6 -> Large Cap / Pharmaceuticals | D9: ='Scoring Model'!AD27 -> 61.519231 | E9: 0.06 | F9: =E9*'Investor Personas'!$C$1 -> 600000 | G9: =IFERROR(INDEX('Master Fund Sheet'!$I$2:$I$15,MATCH(A9,'Master Fund Sheet'!$C$2:$C$15,0)),0) -> 1746.4 | H9: =IF(G9>0,ROUNDDOWN(F9/G9,0),0) -> 343 | I9: =H9*G9 -> 599015.2 | J9: =IFERROR(INDEX('Risk Metrics'!$G$2:$G$15,MATCH(A9,'Risk Metrics'!$A$2:$A$15,0)),0) -> 0.87112781 | K9: =IFERROR(INDEX('Scoring Model'!$AQ$23:$AQ$36,MATCH(A9,'Scoring Model'!$A$23:$A$36,0)),0) -> 0.13254155 | L9: =G9*(1+K9)^'Investor Personas'!$F$1 -> 2536.9164 | M9: =I9*(1+K9)^'Investor Personas'!$F$1 -> 870162.32
A10: MARUTI | B10: Equity | C10: ='Master Fund Sheet'!B7&" / "&'Master Fund Sheet'!E7 -> Large Cap / Automobiles (Passenger Vehicles) | D10: ='Scoring Model'!AD28 -> 60.211538 | E10: 0.06 | F10: =E10*'Investor Personas'!$C$1 -> 600000 | G10: =IFERROR(INDEX('Master Fund Sheet'!$I$2:$I$15,MATCH(A10,'Master Fund Sheet'!$C$2:$C$15,0)),0) -> 11178 | H10: =IF(G10>0,ROUNDDOWN(F10/G10,0),0) -> 53 | I10: =H10*G10 -> 592434 | J10: =IFERROR(INDEX('Risk Metrics'!$G$2:$G$15,MATCH(A10,'Risk Metrics'!$A$2:$A$15,0)),0) -> 0.68561437 | K10: =IFERROR(INDEX('Scoring Model'!$AQ$23:$AQ$36,MATCH(A10,'Scoring Model'!$A$23:$A$36,0)),0) -> 0.12544508 | L10: =G10*(1+K10)^'Investor Personas'!$F$1 -> 15934.448 | M10: =I10*(1+K10)^'Investor Personas'!$F$1 -> 844525.75
A11: RELIANCE | B11: Equity | C11: ='Master Fund Sheet'!B2&" / "&'Master Fund Sheet'!E2 -> Large Cap / Oil & Gas / Conglomerate | D11: ='Scoring Model'!AD23 -> 50.384615 | E11: 0.05 | F11: =E11*'Investor Personas'!$C$1 -> 500000 | G11: =IFERROR(INDEX('Master Fund Sheet'!$I$2:$I$15,MATCH(A11,'Master Fund Sheet'!$C$2:$C$15,0)),0) -> 1174.6 | H11: =IF(G11>0,ROUNDDOWN(F11/G11,0),0) -> 425 | I11: =H11*G11 -> 499205 | J11: =IFERROR(INDEX('Risk Metrics'!$G$2:$G$15,MATCH(A11,'Risk Metrics'!$A$2:$A$15,0)),0) -> 0.99084157 | K11: =IFERROR(INDEX('Scoring Model'!$AQ$23:$AQ$36,MATCH(A11,'Scoring Model'!$A$23:$A$36,0)),0) -> 0.11637344 | L11: =G11*(1+K11)^'Investor Personas'!$F$1 -> 1634.2499 | M11: =I11*(1+K11)^'Investor Personas'!$F$1 -> 694556.23
A12: TATASTEEL | B12: Equity | C12: ='Master Fund Sheet'!B8&" / "&'Master Fund Sheet'!E8 -> Large Cap / Metals & Mining (Steel) | D12: ='Scoring Model'!AD29 -> 53.5 | E12: 0.05 | F12: =E12*'Investor Personas'!$C$1 -> 500000 | G12: =IFERROR(INDEX('Master Fund Sheet'!$I$2:$I$15,MATCH(A12,'Master Fund Sheet'!$C$2:$C$15,0)),0) -> 174.49 | H12: =IF(G12>0,ROUNDDOWN(F12/G12,0),0) -> 2865 | I12: =H12*G12 -> 499913.85 | J12: =IFERROR(INDEX('Risk Metrics'!$G$2:$G$15,MATCH(A12,'Risk Metrics'!$A$2:$A$15,0)),0) -> 1.1923044 | K12: =IFERROR(INDEX('Scoring Model'!$AQ$23:$AQ$36,MATCH(A12,'Scoring Model'!$A$23:$A$36,0)),0) -> 0.12246547 | L12: =G12*(1+K12)^'Investor Personas'!$F$1 -> 246.76838 | M12: =I12*(1+K12)^'Investor Personas'!$F$1 -> 706991.41
A13: ITC | B13: Equity | C13: ='Master Fund Sheet'!B5&" / "&'Master Fund Sheet'!E5 -> Large Cap / FMCG (Cigarettes, Foods, Agri) | D13: ='Scoring Model'!AD26 -> 42.75 | E13: 0.04 | F13: =E13*'Investor Personas'!$C$1 -> 400000 | G13: =IFERROR(INDEX('Master Fund Sheet'!$I$2:$I$15,MATCH(A13,'Master Fund Sheet'!$C$2:$C$15,0)),0) -> 261.5 | H13: =IF(G13>0,ROUNDDOWN(F13/G13,0),0) -> 1529 | I13: =H13*G13 -> 399833.5 | J13: =IFERROR(INDEX('Risk Metrics'!$G$2:$G$15,MATCH(A13,'Risk Metrics'!$A$2:$A$15,0)),0) -> 0.81842432 | K13: =IFERROR(INDEX('Scoring Model'!$AQ$23:$AQ$36,MATCH(A13,'Scoring Model'!$A$23:$A$36,0)),0) -> 0.10578484 | L13: =G13*(1+K13)^'Investor Personas'!$F$1 -> 353.57666 | M13: =I13*(1+K13)^'Investor Personas'!$F$1 -> 540618.72
A14: SMC-NCD-2029 | B14: Bonds | C14: ='Master Fund Sheet'!G20&" / "&'Master Fund Sheet'!B20 -> ICRA A (Stable) / Corporate Bond | D14: — | E14: 0.05 | F14: =E14*'Investor Personas'!$C$1 -> 500000 | G14: ='Master Fund Sheet'!H20 -> 1000 | H14: =IF(G14>0,ROUNDDOWN(F14/G14,0),0) -> 500 | I14: =H14*G14 -> 500000 | J14: 0 | K14: ='Master Fund Sheet'!M20 -> 0.0945 | L14: =G14*(1+K14)^'Investor Personas'!$F$1 -> 1311.1347 | M14: =I14*(1+K14)^'Investor Personas'!$F$1 -> 655567.33
A16: TOTAL | E16: =SUM(E2:E14) -> 1 | F16: =SUM(F2:F14) -> 10000000 | H16: =COUNTIF(B2:B14,"Equity")&" stocks" -> 12 stocks | I16: =SUM(I2:I14) -> 9986891.8 | M16: =SUM(M2:M14) -> 14397767
A18: PORTFOLIO SUMMARY
A19: Corpus | B19: ='Investor Personas'!$C$1 -> 10000000 | D19: The Momentum Maverick · 31, start-up founder, no dependants. Chases the upper assignment target and tolerates deep drawdowns.
A20: Invested | B20: =I16 -> 9986891.8 | D20: Policy: 95% equity split 40/35/25 Large/Mid/Small; stocks need investor score ≥ 40 and beta ≤ 2.5; weight ∝ score within each segment, rounded to whole %.
A21: Uninvested cash (earns 3Y G-Sec yield) | B21: =B19-B20 -> 13108.2 | D21: Not selected: BATAINDIA, ZEEL
A22: Weighted portfolio beta | B22: =SUMPRODUCT(I2:I14,J2:J14)/B19 -> 0.96795318
A23: Projected value Oct-2029 | B23: =M16+B21*(1+'Master Fund Sheet'!$I$18)^'Investor Personas'!$F$1 -> 14413857
A24: Expected CAGR | B24: =(B23/B19)^(1/'Investor Personas'!$F$1)-1 -> 0.12960534
A25: Target | B25: ='Investor Personas'!C3 -> 21500000
A26: CAGR required | B26: ='Investor Personas'!D3 -> 0.29066288
A27: Surplus / (shortfall) | B27: =B23-B25 -> -7086143
A28: Portfolio SD (5Y history) | B28: ='Risk Metrics'!B91 -> 0.16173329
A29: Probability of reaching target | B29: =1-NORMSDIST((LN(B25/B19)-LN(1+B24)*'Investor Personas'!$F$1)/(B28*SQRT('Investor Personas'!$F$1))) -> 0.076729768

Sheet Ananya
A1: Asset / Ticker | B1: Asset Class | C1: Cap / Sector | D1: Investor Score | E1: Weight | F1: Capital (₹) | G1: Current Price (₹) | H1: Units | I1: Invested (₹) | J1: Beta | K1: Exp. Annual Return | L1: Target Price Oct-2029 (₹) | M1: Value Oct-2029 (₹)
A2: KEI | B2: Equity | C2: ='Master Fund Sheet'!B11&" / "&'Master Fund Sheet'!E11 -> Mid Cap / Electricals (Cables & Wires) | D2: ='Scoring Model'!AE32 -> 63.403846 | E2: 0.1 | F2: =E2*'Investor Personas'!$C$1 -> 1000000 | G2: =IFERROR(INDEX('Master Fund Sheet'!$I$2:$I$15,MATCH(A2,'Master Fund Sheet'!$C$2:$C$15,0)),0) -> 4648 | H2: =IF(G2>0,ROUNDDOWN(F2/G2,0),0) -> 215 | I2: =H2*G2 -> 999320 | J2: =IFERROR(INDEX('Risk Metrics'!$G$2:$G$15,MATCH(A2,'Risk Metrics'!$A$2:$A$15,0)),0) -> 1.4331655 | K2: =IFERROR(INDEX('Scoring Model'!$AQ$23:$AQ$36,MATCH(A2,'Scoring Model'!$A$23:$A$36,0)),0) -> 0.1632655 | L2: =G2*(1+K2)^'Investor Personas'!$F$1 -> 7316.4879 | M2: =I2*(1+K2)^'Investor Personas'!$F$1 -> 1573044.9
A3: EIHOTEL | B3: Equity | C3: ='Master Fund Sheet'!B15&" / "&'Master Fund Sheet'!E15 -> Small Cap / Hotels & Hospitality | D3: ='Scoring Model'!AE36 -> 52.615385 | E3: 0.09 | F3: =E3*'Investor Personas'!$C$1 -> 900000 | G3: =IFERROR(INDEX('Master Fund Sheet'!$I$2:$I$15,MATCH(A3,'Master Fund Sheet'!$C$2:$C$15,0)),0) -> 291.95 | H3: =IF(G3>0,ROUNDDOWN(F3/G3,0),0) -> 3082 | I3: =H3*G3 -> 899789.9 | J3: =IFERROR(INDEX('Risk Metrics'!$G$2:$G$15,MATCH(A3,'Risk Metrics'!$A$2:$A$15,0)),0) -> 1.1041444 | K3: =IFERROR(INDEX('Scoring Model'!$AQ$23:$AQ$36,MATCH(A3,'Scoring Model'!$A$23:$A$36,0)),0) -> 0.1418054 | L3: =G3*(1+K3)^'Investor Personas'!$F$1 -> 434.59503 | M3: =I3*(1+K3)^'Investor Personas'!$F$1 -> 1339421.9
A4: DABUR | B4: Equity | C4: ='Master Fund Sheet'!B9&" / "&'Master Fund Sheet'!E9 -> Mid Cap / Personal Care & Ayurveda | D4: ='Scoring Model'!AE30 -> 46.480769 | E4: 0.08 | F4: =E4*'Investor Personas'!$C$1 -> 800000 | G4: =IFERROR(INDEX('Master Fund Sheet'!$I$2:$I$15,MATCH(A4,'Master Fund Sheet'!$C$2:$C$15,0)),0) -> 388.4 | H4: =IF(G4>0,ROUNDDOWN(F4/G4,0),0) -> 2059 | I4: =H4*G4 -> 799715.6 | J4: =IFERROR(INDEX('Risk Metrics'!$G$2:$G$15,MATCH(A4,'Risk Metrics'!$A$2:$A$15,0)),0) -> 0.869804 | K4: =IFERROR(INDEX('Scoring Model'!$AQ$23:$AQ$36,MATCH(A4,'Scoring Model'!$A$23:$A$36,0)),0) -> 0.098594228 | L4: =G4*(1+K4)^'Investor Personas'!$F$1 -> 514.98095 | M4: =I4*(1+K4)^'Investor Personas'!$F$1 -> 1060345.8
A5: JUSTDIAL | B5: Equity | C5: ='Master Fund Sheet'!B14&" / "&'Master Fund Sheet'!E14 -> Small Cap / Internet / Local Search Services | D5: ='Scoring Model'!AE35 -> 46.230769 | E5: 0.08 | F5: =E5*'Investor Personas'!$C$1 -> 800000 | G5: =IFERROR(INDEX('Master Fund Sheet'!$I$2:$I$15,MATCH(A5,'Master Fund Sheet'!$C$2:$C$15,0)),0) -> 682.75 | H5: =IF(G5>0,ROUNDDOWN(F5/G5,0),0) -> 1171 | I5: =H5*G5 -> 799500.25 | J5: =IFERROR(INDEX('Risk Metrics'!$G$2:$G$15,MATCH(A5,'Risk Metrics'!$A$2:$A$15,0)),0) -> 1.2835508 | K5: =IFERROR(INDEX('Scoring Model'!$AQ$23:$AQ$36,MATCH(A5,'Scoring Model'!$A$23:$A$36,0)),0) -> 0.13013197 | L5: =G5*(1+K5)^'Investor Personas'!$F$1 -> 985.48313 | M5: =I5*(1+K5)^'Investor Personas'!$F$1 -> 1154000.7
A6: INFY | B6: Equity | C6: ='Master Fund Sheet'!B4&" / "&'Master Fund Sheet'!E4 -> Large Cap / IT Services | D6: ='Scoring Model'!AE25 -> 66.538462 | E6: 0.07 | F6: =E6*'Investor Personas'!$C$1 -> 700000 | G6: =IFERROR(INDEX('Master Fund Sheet'!$I$2:$I$15,MATCH(A6,'Master Fund Sheet'!$C$2:$C$15,0)),0) -> 1088 | H6: =IF(G6>0,ROUNDDOWN(F6/G6,0),0) -> 643 | I6: =H6*G6 -> 699584 | J6: =IFERROR(INDEX('Risk Metrics'!$G$2:$G$15,MATCH(A6,'Risk Metrics'!$A$2:$A$15,0)),0) -> 0.75751049 | K6: =IFERROR(INDEX('Scoring Model'!$AQ$23:$AQ$36,MATCH(A6,'Scoring Model'!$A$23:$A$36,0)),0) -> 0.15175839 | L6: =G6*(1+K6)^'Investor Personas'!$F$1 -> 1662.3139 | M6: =I6*(1+K6)^'Investor Personas'!$F$1 -> 1068867.9
A7: MARUTI | B7: Equity | C7: ='Master Fund Sheet'!B7&" / "&'Master Fund Sheet'!E7 -> Large Cap / Automobiles (Passenger Vehicles) | D7: ='Scoring Model'!AE28 -> 63.134615 | E7: 0.07 | F7: =E7*'Investor Personas'!$C$1 -> 700000 | G7: =IFERROR(INDEX('Master Fund Sheet'!$I$2:$I$15,MATCH(A7,'Master Fund Sheet'!$C$2:$C$15,0)),0) -> 11178 | H7: =IF(G7>0,ROUNDDOWN(F7/G7,0),0) -> 62 | I7: =H7*G7 -> 693036 | J7: =IFERROR(INDEX('Risk Metrics'!$G$2:$G$15,MATCH(A7,'Risk Metrics'!$A$2:$A$15,0)),0) -> 0.68561437 | K7: =IFERROR(INDEX('Scoring Model'!$AQ$23:$AQ$36,MATCH(A7,'Scoring Model'!$A$23:$A$36,0)),0) -> 0.12544508 | L7: =G7*(1+K7)^'Investor Personas'!$F$1 -> 15934.448 | M7: =I7*(1+K7)^'Investor Personas'!$F$1 -> 987935.79
A8: ASTRAL | B8: Equity | C8: ='Master Fund Sheet'!B10&" / "&'Master Fund Sheet'!E10 -> Mid Cap / Building Materials (Pipes) | D8: ='Scoring Model'!AE31 -> 45.115385 | E8: 0.07 | F8: =E8*'Investor Personas'!$C$1 -> 700000 | G8: =IFERROR(INDEX('Master Fund Sheet'!$I$2:$I$15,MATCH(A8,'Master Fund Sheet'!$C$2:$C$15,0)),0) -> 1443.2 | H8: =IF(G8>0,ROUNDDOWN(F8/G8,0),0) -> 485 | I8: =H8*G8 -> 699952 | J8: =IFERROR(INDEX('Risk Metrics'!$G$2:$G$15,MATCH(A8,'Risk Metrics'!$A$2:$A$15,0)),0) -> 0.69741418 | K8: =IFERROR(INDEX('Scoring Model'!$AQ$23:$AQ$36,MATCH(A8,'Scoring Model'!$A$23:$A$36,0)),0) -> 0.1148254 | L8: =G8*(1+K8)^'Investor Personas'!$F$1 -> 1999.6182 | M8: =I8*(1+K8)^'Investor Personas'!$F$1 -> 969814.83
A9: RELIANCE | B9: Equity | C9: ='Master Fund Sheet'!B2&" / "&'Master Fund Sheet'!E2 -> Large Cap / Oil & Gas / Conglomerate | D9: ='Scoring Model'!AE23 -> 53.307692 | E9: 0.06 | F9: =E9*'Investor Personas'!$C$1 -> 600000 | G9: =IFERROR(INDEX('Master Fund Sheet'!$I$2:$I$15,MATCH(A9,'Master Fund Sheet'!$C$2:$C$15,0)),0) -> 1174.6 | H9: =IF(G9>0,ROUNDDOWN(F9/G9,0),0) -> 510 | I9: =H9*G9 -> 599046 | J9: =IFERROR(INDEX('Risk Metrics'!$G$2:$G$15,MATCH(A9,'Risk Metrics'!$A$2:$A$15,0)),0) -> 0.99084157 | K9: =IFERROR(INDEX('Scoring Model'!$AQ$23:$AQ$36,MATCH(A9,'Scoring Model'!$A$23:$A$36,0)),0) -> 0.11637344 | L9: =G9*(1+K9)^'Investor Personas'!$F$1 -> 1634.2499 | M9: =I9*(1+K9)^'Investor Personas'!$F$1 -> 833467.47
A10: HDFCBANK | B10: Equity | C10: ='Master Fund Sheet'!B3&" / "&'Master Fund Sheet'!E3 -> Large Cap / Private Sector Banking | D10: ='Scoring Model'!AE24 -> 57.019231 | E10: 0.06 | F10: =E10*'Investor Personas'!$C$1 -> 600000 | G10: =IFERROR(INDEX('Master Fund Sheet'!$I$2:$I$15,MATCH(A10,'Master Fund Sheet'!$C$2:$C$15,0)),0) -> 710.7 | H10: =IF(G10>0,ROUNDDOWN(F10/G10,0),0) -> 844 | I10: =H10*G10 -> 599830.8 | J10: =IFERROR(INDEX('Risk Metrics'!$G$2:$G$15,MATCH(A10,'Risk Metrics'!$A$2:$A$15,0)),0) -> 0.884506 | K10: =IFERROR(INDEX('Scoring Model'!$AQ$23:$AQ$36,MATCH(A10,'Scoring Model'!$A$23:$A$36,0)),0) -> 0.13305021 | L10: =G10*(1+K10)^'Investor Personas'!$F$1 -> 1033.7935 | M10: =I10*(1+K10)^'Investor Personas'!$F$1 -> 872521.69
A11: SUNPHARMA | B11: Equity | C11: ='Master Fund Sheet'!B6&" / "&'Master Fund Sheet'!E6 -> Large Cap / Pharmaceuticals | D11: ='Scoring Model'!AE27 -> 60.75 | E11: 0.06 | F11: =E11*'Investor Personas'!$C$1 -> 600000 | G11: =IFERROR(INDEX('Master Fund Sheet'!$I$2:$I$15,MATCH(A11,'Master Fund Sheet'!$C$2:$C$15,0)),0) -> 1746.4 | H11: =IF(G11>0,ROUNDDOWN(F11/G11,0),0) -> 343 | I11: =H11*G11 -> 599015.2 | J11: =IFERROR(INDEX('Risk Metrics'!$G$2:$G$15,MATCH(A11,'Risk Metrics'!$A$2:$A$15,0)),0) -> 0.87112781 | K11: =IFERROR(INDEX('Scoring Model'!$AQ$23:$AQ$36,MATCH(A11,'Scoring Model'!$A$23:$A$36,0)),0) -> 0.13254155 | L11: =G11*(1+K11)^'Investor Personas'!$F$1 -> 2536.9164 | M11: =I11*(1+K11)^'Investor Personas'!$F$1 -> 870162.32
A12: TATASTEEL | B12: Equity | C12: ='Master Fund Sheet'!B8&" / "&'Master Fund Sheet'!E8 -> Large Cap / Metals & Mining (Steel) | D12: ='Scoring Model'!AE29 -> 52.576923 | E12: 0.06 | F12: =E12*'Investor Personas'!$C$1 -> 600000 | G12: =IFERROR(INDEX('Master Fund Sheet'!$I$2:$I$15,MATCH(A12,'Master Fund Sheet'!$C$2:$C$15,0)),0) -> 174.49 | H12: =IF(G12>0,ROUNDDOWN(F12/G12,0),0) -> 3438 | I12: =H12*G12 -> 599896.62 | J12: =IFERROR(INDEX('Risk Metrics'!$G$2:$G$15,MATCH(A12,'Risk Metrics'!$A$2:$A$15,0)),0) -> 1.1923044 | K12: =IFERROR(INDEX('Scoring Model'!$AQ$23:$AQ$36,MATCH(A12,'Scoring Model'!$A$23:$A$36,0)),0) -> 0.12246547 | L12: =G12*(1+K12)^'Investor Personas'!$F$1 -> 246.76838 | M12: =I12*(1+K12)^'Investor Personas'!$F$1 -> 848389.69
A13: ITC | B13: Equity | C13: ='Master Fund Sheet'!B5&" / "&'Master Fund Sheet'!E5 -> Large Cap / FMCG (Cigarettes, Foods, Agri) | D13: ='Scoring Model'!AE26 -> 47.211538 | E13: 0.05 | F13: =E13*'Investor Personas'!$C$1 -> 500000 | G13: =IFERROR(INDEX('Master Fund Sheet'!$I$2:$I$15,MATCH(A13,'Master Fund Sheet'!$C$2:$C$15,0)),0) -> 261.5 | H13: =IF(G13>0,ROUNDDOWN(F13/G13,0),0) -> 1912 | I13: =H13*G13 -> 499988 | J13: =IFERROR(INDEX('Risk Metrics'!$G$2:$G$15,MATCH(A13,'Risk Metrics'!$A$2:$A$15,0)),0) -> 0.81842432 | K13: =IFERROR(INDEX('Scoring Model'!$AQ$23:$AQ$36,MATCH(A13,'Scoring Model'!$A$23:$A$36,0)),0) -> 0.10578484 | L13: =G13*(1+K13)^'Investor Personas'!$F$1 -> 353.57666 | M13: =I13*(1+K13)^'Investor Personas'!$F$1 -> 676038.58
A14: GSEC-3Y | B14: Bonds | C14: ='Master Fund Sheet'!G18&" / "&'Master Fund Sheet'!B18 -> Sovereign (SOV) / Government Bond | D14: — | E14: 0.05 | F14: =E14*'Investor Personas'!$C$1 -> 500000 | G14: ='Master Fund Sheet'!H18 -> 100 | H14: =IF(G14>0,ROUNDDOWN(F14/G14,0),0) -> 5000 | I14: =H14*G14 -> 500000 | J14: 0 | K14: ='Master Fund Sheet'!M18 -> 0.0707 | L14: =G14*(1+K14)^'Investor Personas'!$F$1 -> 122.74489 | M14: =I14*(1+K14)^'Investor Personas'!$F$1 -> 613724.43
A15: RIL-NCD-2036 | B15: Bonds | C15: ='Master Fund Sheet'!G19&" / "&'Master Fund Sheet'!B19 -> CRISIL AAA / CARE AAA / Corporate Bond | D15: — | E15: 0.05 | F15: =E15*'Investor Personas'!$C$1 -> 500000 | G15: ='Master Fund Sheet'!H19 -> 100000 | H15: =IF(G15>0,ROUNDDOWN(F15/G15,0),0) -> 5 | I15: =H15*G15 -> 500000 | J15: 0 | K15: ='Master Fund Sheet'!M19 -> 0.07875 | L15: =G15*(1+K15)^'Investor Personas'!$F$1 -> 125534.31 | M15: =I15*(1+K15)^'Investor Personas'!$F$1 -> 627671.53
A16: SMC-NCD-2029 | B16: Bonds | C16: ='Master Fund Sheet'!G20&" / "&'Master Fund Sheet'!B20 -> ICRA A (Stable) / Corporate Bond | D16: — | E16: 0.05 | F16: =E16*'Investor Personas'!$C$1 -> 500000 | G16: ='Master Fund Sheet'!H20 -> 1000 | H16: =IF(G16>0,ROUNDDOWN(F16/G16,0),0) -> 500 | I16: =H16*G16 -> 500000 | J16: 0 | K16: ='Master Fund Sheet'!M20 -> 0.0945 | L16: =G16*(1+K16)^'Investor Personas'!$F$1 -> 1311.1347 | M16: =I16*(1+K16)^'Investor Personas'!$F$1 -> 655567.33
A18: TOTAL | E18: =SUM(E2:E16) -> 1 | F18: =SUM(F2:F16) -> 10000000 | H18: =COUNTIF(B2:B16,"Equity")&" stocks" -> 12 stocks | I18: =SUM(I2:I16) -> 9988674.4 | M18: =SUM(M2:M16) -> 14150975
A20: PORTFOLIO SUMMARY
A21: Corpus | B21: ='Investor Personas'!$C$1 -> 10000000 | D21: The Growth Architect · 38, strategy consultant, dual income. Targets the lower assignment target with some debt ballast.
A22: Invested | B22: =I18 -> 9988674.4 | D22: Policy: 85% equity split 50/30/20 Large/Mid/Small; stocks need investor score ≥ 40 and beta ≤ 1.7; weight ∝ score within each segment, rounded to whole %.
A23: Uninvested cash (earns 3Y G-Sec yield) | B23: =B21-B22 -> 11325.63 | D23: Not selected: BATAINDIA, ZEEL
A24: Weighted portfolio beta | B24: =SUMPRODUCT(I2:I16,J2:J16)/B21 -> 0.84111323
A25: Projected value Oct-2029 | B25: =M18+B23*(1+'Master Fund Sheet'!$I$18)^'Investor Personas'!$F$1 -> 14164876
A26: Expected CAGR | B26: =(B25/B21)^(1/'Investor Personas'!$F$1)-1 -> 0.12306337
A27: Target | B27: ='Investor Personas'!C4 -> 20000000
A28: CAGR required | B28: ='Investor Personas'!D4 -> 0.25992105
A29: Surplus / (shortfall) | B29: =B25-B27 -> -5835123.6
A30: Portfolio SD (5Y history) | B30: ='Risk Metrics'!C91 -> 0.13370298
A31: Probability of reaching target | B31: =1-NORMSDIST((LN(B27/B21)-LN(1+B26)*'Investor Personas'!$F$1)/(B30*SQRT('Investor Personas'!$F$1))) -> 0.068162017

Sheet Rohan
A1: Asset / Ticker | B1: Asset Class | C1: Cap / Sector | D1: Investor Score | E1: Weight | F1: Capital (₹) | G1: Current Price (₹) | H1: Units | I1: Invested (₹) | J1: Beta | K1: Exp. Annual Return | L1: Target Price Oct-2029 (₹) | M1: Value Oct-2029 (₹)
A2: INFY | B2: Equity | C2: ='Master Fund Sheet'!B4&" / "&'Master Fund Sheet'!E4 -> Large Cap / IT Services | D2: ='Scoring Model'!AF25 -> 67.717949 | E2: 0.07 | F2: =E2*'Investor Personas'!$C$1 -> 700000 | G2: =IFERROR(INDEX('Master Fund Sheet'!$I$2:$I$15,MATCH(A2,'Master Fund Sheet'!$C$2:$C$15,0)),0) -> 1088 | H2: =IF(G2>0,ROUNDDOWN(F2/G2,0),0) -> 643 | I2: =H2*G2 -> 699584 | J2: =IFERROR(INDEX('Risk Metrics'!$G$2:$G$15,MATCH(A2,'Risk Metrics'!$A$2:$A$15,0)),0) -> 0.75751049 | K2: =IFERROR(INDEX('Scoring Model'!$AQ$23:$AQ$36,MATCH(A2,'Scoring Model'!$A$23:$A$36,0)),0) -> 0.15175839 | L2: =G2*(1+K2)^'Investor Personas'!$F$1 -> 1662.3139 | M2: =I2*(1+K2)^'Investor Personas'!$F$1 -> 1068867.9
A3: MARUTI | B3: Equity | C3: ='Master Fund Sheet'!B7&" / "&'Master Fund Sheet'!E7 -> Large Cap / Automobiles (Passenger Vehicles) | D3: ='Scoring Model'!AF28 -> 65.865385 | E3: 0.07 | F3: =E3*'Investor Personas'!$C$1 -> 700000 | G3: =IFERROR(INDEX('Master Fund Sheet'!$I$2:$I$15,MATCH(A3,'Master Fund Sheet'!$C$2:$C$15,0)),0) -> 11178 | H3: =IF(G3>0,ROUNDDOWN(F3/G3,0),0) -> 62 | I3: =H3*G3 -> 693036 | J3: =IFERROR(INDEX('Risk Metrics'!$G$2:$G$15,MATCH(A3,'Risk Metrics'!$A$2:$A$15,0)),0) -> 0.68561437 | K3: =IFERROR(INDEX('Scoring Model'!$AQ$23:$AQ$36,MATCH(A3,'Scoring Model'!$A$23:$A$36,0)),0) -> 0.12544508 | L3: =G3*(1+K3)^'Investor Personas'!$F$1 -> 15934.448 | M3: =I3*(1+K3)^'Investor Personas'!$F$1 -> 987935.79
A4: RELIANCE | B4: Equity | C4: ='Master Fund Sheet'!B2&" / "&'Master Fund Sheet'!E2 -> Large Cap / Oil & Gas / Conglomerate | D4: ='Scoring Model'!AF23 -> 56.205128 | E4: 0.06 | F4: =E4*'Investor Personas'!$C$1 -> 600000 | G4: =IFERROR(INDEX('Master Fund Sheet'!$I$2:$I$15,MATCH(A4,'Master Fund Sheet'!$C$2:$C$15,0)),0) -> 1174.6 | H4: =IF(G4>0,ROUNDDOWN(F4/G4,0),0) -> 510 | I4: =H4*G4 -> 599046 | J4: =IFERROR(INDEX('Risk Metrics'!$G$2:$G$15,MATCH(A4,'Risk Metrics'!$A$2:$A$15,0)),0) -> 0.99084157 | K4: =IFERROR(INDEX('Scoring Model'!$AQ$23:$AQ$36,MATCH(A4,'Scoring Model'!$A$23:$A$36,0)),0) -> 0.11637344 | L4: =G4*(1+K4)^'Investor Personas'!$F$1 -> 1634.2499 | M4: =I4*(1+K4)^'Investor Personas'!$F$1 -> 833467.47
A5: HDFCBANK | B5: Equity | C5: ='Master Fund Sheet'!B3&" / "&'Master Fund Sheet'!E3 -> Large Cap / Private Sector Banking | D5: ='Scoring Model'!AF24 -> 59.49359 | E5: 0.06 | F5: =E5*'Investor Personas'!$C$1 -> 600000 | G5: =IFERROR(INDEX('Master Fund Sheet'!$I$2:$I$15,MATCH(A5,'Master Fund Sheet'!$C$2:$C$15,0)),0) -> 710.7 | H5: =IF(G5>0,ROUNDDOWN(F5/G5,0),0) -> 844 | I5: =H5*G5 -> 599830.8 | J5: =IFERROR(INDEX('Risk Metrics'!$G$2:$G$15,MATCH(A5,'Risk Metrics'!$A$2:$A$15,0)),0) -> 0.884506 | K5: =IFERROR(INDEX('Scoring Model'!$AQ$23:$AQ$36,MATCH(A5,'Scoring Model'!$A$23:$A$36,0)),0) -> 0.13305021 | L5: =G5*(1+K5)^'Investor Personas'!$F$1 -> 1033.7935 | M5: =I5*(1+K5)^'Investor Personas'!$F$1 -> 872521.69
A6: SUNPHARMA | B6: Equity | C6: ='Master Fund Sheet'!B6&" / "&'Master Fund Sheet'!E6 -> Large Cap / Pharmaceuticals | D6: ='Scoring Model'!AF27 -> 60.455128 | E6: 0.06 | F6: =E6*'Investor Personas'!$C$1 -> 600000 | G6: =IFERROR(INDEX('Master Fund Sheet'!$I$2:$I$15,MATCH(A6,'Master Fund Sheet'!$C$2:$C$15,0)),0) -> 1746.4 | H6: =IF(G6>0,ROUNDDOWN(F6/G6,0),0) -> 343 | I6: =H6*G6 -> 599015.2 | J6: =IFERROR(INDEX('Risk Metrics'!$G$2:$G$15,MATCH(A6,'Risk Metrics'!$A$2:$A$15,0)),0) -> 0.87112781 | K6: =IFERROR(INDEX('Scoring Model'!$AQ$23:$AQ$36,MATCH(A6,'Scoring Model'!$A$23:$A$36,0)),0) -> 0.13254155 | L6: =G6*(1+K6)^'Investor Personas'!$F$1 -> 2536.9164 | M6: =I6*(1+K6)^'Investor Personas'!$F$1 -> 870162.32
A7: KEI | B7: Equity | C7: ='Master Fund Sheet'!B11&" / "&'Master Fund Sheet'!E11 -> Mid Cap / Electricals (Cables & Wires) | D7: ='Scoring Model'!AF32 -> 57.801282 | E7: 0.06 | F7: =E7*'Investor Personas'!$C$1 -> 600000 | G7: =IFERROR(INDEX('Master Fund Sheet'!$I$2:$I$15,MATCH(A7,'Master Fund Sheet'!$C$2:$C$15,0)),0) -> 4648 | H7: =IF(G7>0,ROUNDDOWN(F7/G7,0),0) -> 129 | I7: =H7*G7 -> 599592 | J7: =IFERROR(INDEX('Risk Metrics'!$G$2:$G$15,MATCH(A7,'Risk Metrics'!$A$2:$A$15,0)),0) -> 1.4331655 | K7: =IFERROR(INDEX('Scoring Model'!$AQ$23:$AQ$36,MATCH(A7,'Scoring Model'!$A$23:$A$36,0)),0) -> 0.1632655 | L7: =G7*(1+K7)^'Investor Personas'!$F$1 -> 7316.4879 | M7: =I7*(1+K7)^'Investor Personas'!$F$1 -> 943826.94
A8: ITC | B8: Equity | C8: ='Master Fund Sheet'!B5&" / "&'Master Fund Sheet'!E5 -> Large Cap / FMCG (Cigarettes, Foods, Agri) | D8: ='Scoring Model'!AF26 -> 51.903846 | E8: 0.05 | F8: =E8*'Investor Personas'!$C$1 -> 500000 | G8: =IFERROR(INDEX('Master Fund Sheet'!$I$2:$I$15,MATCH(A8,'Master Fund Sheet'!$C$2:$C$15,0)),0) -> 261.5 | H8: =IF(G8>0,ROUNDDOWN(F8/G8,0),0) -> 1912 | I8: =H8*G8 -> 499988 | J8: =IFERROR(INDEX('Risk Metrics'!$G$2:$G$15,MATCH(A8,'Risk Metrics'!$A$2:$A$15,0)),0) -> 0.81842432 | K8: =IFERROR(INDEX('Scoring Model'!$AQ$23:$AQ$36,MATCH(A8,'Scoring Model'!$A$23:$A$36,0)),0) -> 0.10578484 | L8: =G8*(1+K8)^'Investor Personas'!$F$1 -> 353.57666 | M8: =I8*(1+K8)^'Investor Personas'!$F$1 -> 676038.58
A9: TATASTEEL | B9: Equity | C9: ='Master Fund Sheet'!B8&" / "&'Master Fund Sheet'!E8 -> Large Cap / Metals & Mining (Steel) | D9: ='Scoring Model'!AF29 -> 50.576923 | E9: 0.05 | F9: =E9*'Investor Personas'!$C$1 -> 500000 | G9: =IFERROR(INDEX('Master Fund Sheet'!$I$2:$I$15,MATCH(A9,'Master Fund Sheet'!$C$2:$C$15,0)),0) -> 174.49 | H9: =IF(G9>0,ROUNDDOWN(F9/G9,0),0) -> 2865 | I9: =H9*G9 -> 499913.85 | J9: =IFERROR(INDEX('Risk Metrics'!$G$2:$G$15,MATCH(A9,'Risk Metrics'!$A$2:$A$15,0)),0) -> 1.1923044 | K9: =IFERROR(INDEX('Scoring Model'!$AQ$23:$AQ$36,MATCH(A9,'Scoring Model'!$A$23:$A$36,0)),0) -> 0.12246547 | L9: =G9*(1+K9)^'Investor Personas'!$F$1 -> 246.76838 | M9: =I9*(1+K9)^'Investor Personas'!$F$1 -> 706991.41
A10: DABUR | B10: Equity | C10: ='Master Fund Sheet'!B9&" / "&'Master Fund Sheet'!E9 -> Mid Cap / Personal Care & Ayurveda | D10: ='Scoring Model'!AF30 -> 47.429487 | E10: 0.05 | F10: =E10*'Investor Personas'!$C$1 -> 500000 | G10: =IFERROR(INDEX('Master Fund Sheet'!$I$2:$I$15,MATCH(A10,'Master Fund Sheet'!$C$2:$C$15,0)),0) -> 388.4 | H10: =IF(G10>0,ROUNDDOWN(F10/G10,0),0) -> 1287 | I10: =H10*G10 -> 499870.8 | J10: =IFERROR(INDEX('Risk Metrics'!$G$2:$G$15,MATCH(A10,'Risk Metrics'!$A$2:$A$15,0)),0) -> 0.869804 | K10: =IFERROR(INDEX('Scoring Model'!$AQ$23:$AQ$36,MATCH(A10,'Scoring Model'!$A$23:$A$36,0)),0) -> 0.098594228 | L10: =G10*(1+K10)^'Investor Personas'!$F$1 -> 514.98095 | M10: =I10*(1+K10)^'Investor Personas'!$F$1 -> 662780.48
A11: ASTRAL | B11: Equity | C11: ='Master Fund Sheet'!B10&" / "&'Master Fund Sheet'!E10 -> Mid Cap / Building Materials (Pipes) | D11: ='Scoring Model'!AF31 -> 44.410256 | E11: 0.05 | F11: =E11*'Investor Personas'!$C$1 -> 500000 | G11: =IFERROR(INDEX('Master Fund Sheet'!$I$2:$I$15,MATCH(A11,'Master Fund Sheet'!$C$2:$C$15,0)),0) -> 1443.2 | H11: =IF(G11>0,ROUNDDOWN(F11/G11,0),0) -> 346 | I11: =H11*G11 -> 499347.2 | J11: =IFERROR(INDEX('Risk Metrics'!$G$2:$G$15,MATCH(A11,'Risk Metrics'!$A$2:$A$15,0)),0) -> 0.69741418 | K11: =IFERROR(INDEX('Scoring Model'!$AQ$23:$AQ$36,MATCH(A11,'Scoring Model'!$A$23:$A$36,0)),0) -> 0.1148254 | L11: =G11*(1+K11)^'Investor Personas'!$F$1 -> 1999.6182 | M11: =I11*(1+K11)^'Investor Personas'!$F$1 -> 691867.9
A12: EIHOTEL | B12: Equity | C12: ='Master Fund Sheet'!B15&" / "&'Master Fund Sheet'!E15 -> Small Cap / Hotels & Hospitality | D12: ='Scoring Model'!AF36 -> 49.807692 | E12: 0.04 | F12: =E12*'Investor Personas'!$C$1 -> 400000 | G12: =IFERROR(INDEX('Master Fund Sheet'!$I$2:$I$15,MATCH(A12,'Master Fund Sheet'!$C$2:$C$15,0)),0) -> 291.95 | H12: =IF(G12>0,ROUNDDOWN(F12/G12,0),0) -> 1370 | I12: =H12*G12 -> 399971.5 | J12: =IFERROR(INDEX('Risk Metrics'!$G$2:$G$15,MATCH(A12,'Risk Metrics'!$A$2:$A$15,0)),0) -> 1.1041444 | K12: =IFERROR(INDEX('Scoring Model'!$AQ$23:$AQ$36,MATCH(A12,'Scoring Model'!$A$23:$A$36,0)),0) -> 0.1418054 | L12: =G12*(1+K12)^'Investor Personas'!$F$1 -> 434.59503 | M12: =I12*(1+K12)^'Investor Personas'!$F$1 -> 595395.19
A13: JUSTDIAL | B13: Equity | C13: ='Master Fund Sheet'!B14&" / "&'Master Fund Sheet'!E14 -> Small Cap / Internet / Local Search Services | D13: ='Scoring Model'!AF35 -> 42.666667 | E13: 0.03 | F13: =E13*'Investor Personas'!$C$1 -> 300000 | G13: =IFERROR(INDEX('Master Fund Sheet'!$I$2:$I$15,MATCH(A13,'Master Fund Sheet'!$C$2:$C$15,0)),0) -> 682.75 | H13: =IF(G13>0,ROUNDDOWN(F13/G13,0),0) -> 439 | I13: =H13*G13 -> 299727.25 | J13: =IFERROR(INDEX('Risk Metrics'!$G$2:$G$15,MATCH(A13,'Risk Metrics'!$A$2:$A$15,0)),0) -> 1.2835508 | K13: =IFERROR(INDEX('Scoring Model'!$AQ$23:$AQ$36,MATCH(A13,'Scoring Model'!$A$23:$A$36,0)),0) -> 0.13013197 | L13: =G13*(1+K13)^'Investor Personas'!$F$1 -> 985.48313 | M13: =I13*(1+K13)^'Investor Personas'!$F$1 -> 432627.09
A14: GSEC-3Y | B14: Bonds | C14: ='Master Fund Sheet'!G18&" / "&'Master Fund Sheet'!B18 -> Sovereign (SOV) / Government Bond | D14: — | E14: 0.15 | F14: =E14*'Investor Personas'!$C$1 -> 1500000 | G14: ='Master Fund Sheet'!H18 -> 100 | H14: =IF(G14>0,ROUNDDOWN(F14/G14,0),0) -> 15000 | I14: =H14*G14 -> 1500000 | J14: 0 | K14: ='Master Fund Sheet'!M18 -> 0.0707 | L14: =G14*(1+K14)^'Investor Personas'!$F$1 -> 122.74489 | M14: =I14*(1+K14)^'Investor Personas'!$F$1 -> 1841173.3
A15: RIL-NCD-2036 | B15: Bonds | C15: ='Master Fund Sheet'!G19&" / "&'Master Fund Sheet'!B19 -> CRISIL AAA / CARE AAA / Corporate Bond | D15: — | E15: 0.12 | F15: =E15*'Investor Personas'!$C$1 -> 1200000 | G15: ='Master Fund Sheet'!H19 -> 100000 | H15: =IF(G15>0,ROUNDDOWN(F15/G15,0),0) -> 12 | I15: =H15*G15 -> 1200000 | J15: 0 | K15: ='Master Fund Sheet'!M19 -> 0.07875 | L15: =G15*(1+K15)^'Investor Personas'!$F$1 -> 125534.31 | M15: =I15*(1+K15)^'Investor Personas'!$F$1 -> 1506411.7
A16: SMC-NCD-2029 | B16: Bonds | C16: ='Master Fund Sheet'!G20&" / "&'Master Fund Sheet'!B20 -> ICRA A (Stable) / Corporate Bond | D16: — | E16: 0.08 | F16: =E16*'Investor Personas'!$C$1 -> 800000 | G16: ='Master Fund Sheet'!H20 -> 1000 | H16: =IF(G16>0,ROUNDDOWN(F16/G16,0),0) -> 800 | I16: =H16*G16 -> 800000 | J16: 0 | K16: ='Master Fund Sheet'!M20 -> 0.0945 | L16: =G16*(1+K16)^'Investor Personas'!$F$1 -> 1311.1347 | M16: =I16*(1+K16)^'Investor Personas'!$F$1 -> 1048907.7
A18: TOTAL | E18: =SUM(E2:E16) -> 1 | F18: =SUM(F2:F16) -> 10000000 | H18: =COUNTIF(B2:B16,"Equity")&" stocks" -> 12 stocks | I18: =SUM(I2:I16) -> 9988922.6 | M18: =SUM(M2:M16) -> 13738975
A20: PORTFOLIO SUMMARY
A21: Corpus | B21: ='Investor Personas'!$C$1 -> 10000000 | D21: The Balanced Planner · 46, surgeon saving for two children's higher education in 3 years.
A22: Invested | B22: =I18 -> 9988922.6 | D22: Policy: 65% equity split 65/25/10 Large/Mid/Small; stocks need investor score ≥ 40 and beta ≤ 1.5; weight ∝ score within each segment, rounded to whole %.
A23: Uninvested cash (earns 3Y G-Sec yield) | B23: =B21-B22 -> 11077.4 | D23: Not selected: BATAINDIA, ZEEL
A24: Weighted portfolio beta | B24: =SUMPRODUCT(I2:I16,J2:J16)/B21 -> 0.61249794
A25: Projected value Oct-2029 | B25: =M18+B23*(1+'Master Fund Sheet'!$I$18)^'Investor Personas'!$F$1 -> 13752572
A26: Expected CAGR | B26: =(B25/B21)^(1/'Investor Personas'!$F$1)-1 -> 0.11205938
A27: Target | B27: ='Investor Personas'!C5 -> 16000000
A28: CAGR required | B28: ='Investor Personas'!D5 -> 0.1696071
A29: Surplus / (shortfall) | B29: =B25-B27 -> -2247427.7
A30: Portfolio SD (5Y history) | B30: ='Risk Metrics'!D91 -> 0.092753311
A31: Probability of reaching target | B31: =1-NORMSDIST((LN(B27/B21)-LN(1+B26)*'Investor Personas'!$F$1)/(B30*SQRT('Investor Personas'!$F$1))) -> 0.17305284

Sheet Meera
A1: Asset / Ticker | B1: Asset Class | C1: Cap / Sector | D1: Investor Score | E1: Weight | F1: Capital (₹) | G1: Current Price (₹) | H1: Units | I1: Invested (₹) | J1: Beta | K1: Exp. Annual Return | L1: Target Price Oct-2029 (₹) | M1: Value Oct-2029 (₹)
A2: DABUR | B2: Equity | C2: ='Master Fund Sheet'!B9&" / "&'Master Fund Sheet'!E9 -> Mid Cap / Personal Care & Ayurveda | D2: ='Scoring Model'!AG30 -> 49.730769 | E2: 0.06 | F2: =E2*'Investor Personas'!$C$1 -> 600000 | G2: =IFERROR(INDEX('Master Fund Sheet'!$I$2:$I$15,MATCH(A2,'Master Fund Sheet'!$C$2:$C$15,0)),0) -> 388.4 | H2: =IF(G2>0,ROUNDDOWN(F2/G2,0),0) -> 1544 | I2: =H2*G2 -> 599689.6 | J2: =IFERROR(INDEX('Risk Metrics'!$G$2:$G$15,MATCH(A2,'Risk Metrics'!$A$2:$A$15,0)),0) -> 0.869804 | K2: =IFERROR(INDEX('Scoring Model'!$AQ$23:$AQ$36,MATCH(A2,'Scoring Model'!$A$23:$A$36,0)),0) -> 0.098594228 | L2: =G2*(1+K2)^'Investor Personas'!$F$1 -> 514.98095 | M2: =I2*(1+K2)^'Investor Personas'!$F$1 -> 795130.58
A3: HDFCBANK | B3: Equity | C3: ='Master Fund Sheet'!B3&" / "&'Master Fund Sheet'!E3 -> Large Cap / Private Sector Banking | D3: ='Scoring Model'!AG24 -> 62.730769 | E3: 0.05 | F3: =E3*'Investor Personas'!$C$1 -> 500000 | G3: =IFERROR(INDEX('Master Fund Sheet'!$I$2:$I$15,MATCH(A3,'Master Fund Sheet'!$C$2:$C$15,0)),0) -> 710.7 | H3: =IF(G3>0,ROUNDDOWN(F3/G3,0),0) -> 703 | I3: =H3*G3 -> 499622.1 | J3: =IFERROR(INDEX('Risk Metrics'!$G$2:$G$15,MATCH(A3,'Risk Metrics'!$A$2:$A$15,0)),0) -> 0.884506 | K3: =IFERROR(INDEX('Scoring Model'!$AQ$23:$AQ$36,MATCH(A3,'Scoring Model'!$A$23:$A$36,0)),0) -> 0.13305021 | L3: =G3*(1+K3)^'Investor Personas'!$F$1 -> 1033.7935 | M3: =I3*(1+K3)^'Investor Personas'!$F$1 -> 726756.81
A4: INFY | B4: Equity | C4: ='Master Fund Sheet'!B4&" / "&'Master Fund Sheet'!E4 -> Large Cap / IT Services | D4: ='Scoring Model'!AG25 -> 71.358974 | E4: 0.05 | F4: =E4*'Investor Personas'!$C$1 -> 500000 | G4: =IFERROR(INDEX('Master Fund Sheet'!$I$2:$I$15,MATCH(A4,'Master Fund Sheet'!$C$2:$C$15,0)),0) -> 1088 | H4: =IF(G4>0,ROUNDDOWN(F4/G4,0),0) -> 459 | I4: =H4*G4 -> 499392 | J4: =IFERROR(INDEX('Risk Metrics'!$G$2:$G$15,MATCH(A4,'Risk Metrics'!$A$2:$A$15,0)),0) -> 0.75751049 | K4: =IFERROR(INDEX('Scoring Model'!$AQ$23:$AQ$36,MATCH(A4,'Scoring Model'!$A$23:$A$36,0)),0) -> 0.15175839 | L4: =G4*(1+K4)^'Investor Personas'!$F$1 -> 1662.3139 | M4: =I4*(1+K4)^'Investor Personas'!$F$1 -> 763002.09
A5: SUNPHARMA | B5: Equity | C5: ='Master Fund Sheet'!B6&" / "&'Master Fund Sheet'!E6 -> Large Cap / Pharmaceuticals | D5: ='Scoring Model'!AG27 -> 60.576923 | E5: 0.05 | F5: =E5*'Investor Personas'!$C$1 -> 500000 | G5: =IFERROR(INDEX('Master Fund Sheet'!$I$2:$I$15,MATCH(A5,'Master Fund Sheet'!$C$2:$C$15,0)),0) -> 1746.4 | H5: =IF(G5>0,ROUNDDOWN(F5/G5,0),0) -> 286 | I5: =H5*G5 -> 499470.4 | J5: =IFERROR(INDEX('Risk Metrics'!$G$2:$G$15,MATCH(A5,'Risk Metrics'!$A$2:$A$15,0)),0) -> 0.87112781 | K5: =IFERROR(INDEX('Scoring Model'!$AQ$23:$AQ$36,MATCH(A5,'Scoring Model'!$A$23:$A$36,0)),0) -> 0.13254155 | L5: =G5*(1+K5)^'Investor Personas'!$F$1 -> 2536.9164 | M5: =I5*(1+K5)^'Investor Personas'!$F$1 -> 725558.09
A6: MARUTI | B6: Equity | C6: ='Master Fund Sheet'!B7&" / "&'Master Fund Sheet'!E7 -> Large Cap / Automobiles (Passenger Vehicles) | D6: ='Scoring Model'!AG28 -> 67.576923 | E6: 0.05 | F6: =E6*'Investor Personas'!$C$1 -> 500000 | G6: =IFERROR(INDEX('Master Fund Sheet'!$I$2:$I$15,MATCH(A6,'Master Fund Sheet'!$C$2:$C$15,0)),0) -> 11178 | H6: =IF(G6>0,ROUNDDOWN(F6/G6,0),0) -> 44 | I6: =H6*G6 -> 491832 | J6: =IFERROR(INDEX('Risk Metrics'!$G$2:$G$15,MATCH(A6,'Risk Metrics'!$A$2:$A$15,0)),0) -> 0.68561437 | K6: =IFERROR(INDEX('Scoring Model'!$AQ$23:$AQ$36,MATCH(A6,'Scoring Model'!$A$23:$A$36,0)),0) -> 0.12544508 | L6: =G6*(1+K6)^'Investor Personas'!$F$1 -> 15934.448 | M6: =I6*(1+K6)^'Investor Personas'!$F$1 -> 701115.72
A7: RELIANCE | B7: Equity | C7: ='Master Fund Sheet'!B2&" / "&'Master Fund Sheet'!E2 -> Large Cap / Oil & Gas / Conglomerate | D7: ='Scoring Model'!AG23 -> 58.102564 | E7: 0.04 | F7: =E7*'Investor Personas'!$C$1 -> 400000 | G7: =IFERROR(INDEX('Master Fund Sheet'!$I$2:$I$15,MATCH(A7,'Master Fund Sheet'!$C$2:$C$15,0)),0) -> 1174.6 | H7: =IF(G7>0,ROUNDDOWN(F7/G7,0),0) -> 340 | I7: =H7*G7 -> 399364 | J7: =IFERROR(INDEX('Risk Metrics'!$G$2:$G$15,MATCH(A7,'Risk Metrics'!$A$2:$A$15,0)),0) -> 0.99084157 | K7: =IFERROR(INDEX('Scoring Model'!$AQ$23:$AQ$36,MATCH(A7,'Scoring Model'!$A$23:$A$36,0)),0) -> 0.11637344 | L7: =G7*(1+K7)^'Investor Personas'!$F$1 -> 1634.2499 | M7: =I7*(1+K7)^'Investor Personas'!$F$1 -> 555644.98
A8: ITC | B8: Equity | C8: ='Master Fund Sheet'!B5&" / "&'Master Fund Sheet'!E5 -> Large Cap / FMCG (Cigarettes, Foods, Agri) | D8: ='Scoring Model'!AG26 -> 59.346154 | E8: 0.04 | F8: =E8*'Investor Personas'!$C$1 -> 400000 | G8: =IFERROR(INDEX('Master Fund Sheet'!$I$2:$I$15,MATCH(A8,'Master Fund Sheet'!$C$2:$C$15,0)),0) -> 261.5 | H8: =IF(G8>0,ROUNDDOWN(F8/G8,0),0) -> 1529 | I8: =H8*G8 -> 399833.5 | J8: =IFERROR(INDEX('Risk Metrics'!$G$2:$G$15,MATCH(A8,'Risk Metrics'!$A$2:$A$15,0)),0) -> 0.81842432 | K8: =IFERROR(INDEX('Scoring Model'!$AQ$23:$AQ$36,MATCH(A8,'Scoring Model'!$A$23:$A$36,0)),0) -> 0.10578484 | L8: =G8*(1+K8)^'Investor Personas'!$F$1 -> 353.57666 | M8: =I8*(1+K8)^'Investor Personas'!$F$1 -> 540618.72
A9: TATASTEEL | B9: Equity | C9: ='Master Fund Sheet'!B8&" / "&'Master Fund Sheet'!E8 -> Large Cap / Metals & Mining (Steel) | D9: ='Scoring Model'!AG29 -> 48.461538 | E9: 0.04 | F9: =E9*'Investor Personas'!$C$1 -> 400000 | G9: =IFERROR(INDEX('Master Fund Sheet'!$I$2:$I$15,MATCH(A9,'Master Fund Sheet'!$C$2:$C$15,0)),0) -> 174.49 | H9: =IF(G9>0,ROUNDDOWN(F9/G9,0),0) -> 2292 | I9: =H9*G9 -> 399931.08 | J9: =IFERROR(INDEX('Risk Metrics'!$G$2:$G$15,MATCH(A9,'Risk Metrics'!$A$2:$A$15,0)),0) -> 1.1923044 | K9: =IFERROR(INDEX('Scoring Model'!$AQ$23:$AQ$36,MATCH(A9,'Scoring Model'!$A$23:$A$36,0)),0) -> 0.12246547 | L9: =G9*(1+K9)^'Investor Personas'!$F$1 -> 246.76838 | M9: =I9*(1+K9)^'Investor Personas'!$F$1 -> 565593.13
A10: EIHOTEL | B10: Equity | C10: ='Master Fund Sheet'!B15&" / "&'Master Fund Sheet'!E15 -> Small Cap / Hotels & Hospitality | D10: ='Scoring Model'!AG36 -> 47.512821 | E10: 0.02 | F10: =E10*'Investor Personas'!$C$1 -> 200000 | G10: =IFERROR(INDEX('Master Fund Sheet'!$I$2:$I$15,MATCH(A10,'Master Fund Sheet'!$C$2:$C$15,0)),0) -> 291.95 | H10: =IF(G10>0,ROUNDDOWN(F10/G10,0),0) -> 685 | I10: =H10*G10 -> 199985.75 | J10: =IFERROR(INDEX('Risk Metrics'!$G$2:$G$15,MATCH(A10,'Risk Metrics'!$A$2:$A$15,0)),0) -> 1.1041444 | K10: =IFERROR(INDEX('Scoring Model'!$AQ$23:$AQ$36,MATCH(A10,'Scoring Model'!$A$23:$A$36,0)),0) -> 0.1418054 | L10: =G10*(1+K10)^'Investor Personas'!$F$1 -> 434.59503 | M10: =I10*(1+K10)^'Investor Personas'!$F$1 -> 297697.6
A11: GSEC-3Y | B11: Bonds | C11: ='Master Fund Sheet'!G18&" / "&'Master Fund Sheet'!B18 -> Sovereign (SOV) / Government Bond | D11: — | E11: 0.3 | F11: =E11*'Investor Personas'!$C$1 -> 3000000 | G11: ='Master Fund Sheet'!H18 -> 100 | H11: =IF(G11>0,ROUNDDOWN(F11/G11,0),0) -> 30000 | I11: =H11*G11 -> 3000000 | J11: 0 | K11: ='Master Fund Sheet'!M18 -> 0.0707 | L11: =G11*(1+K11)^'Investor Personas'!$F$1 -> 122.74489 | M11: =I11*(1+K11)^'Investor Personas'!$F$1 -> 3682346.6
A12: RIL-NCD-2036 | B12: Bonds | C12: ='Master Fund Sheet'!G19&" / "&'Master Fund Sheet'!B19 -> CRISIL AAA / CARE AAA / Corporate Bond | D12: — | E12: 0.2 | F12: =E12*'Investor Personas'!$C$1 -> 2000000 | G12: ='Master Fund Sheet'!H19 -> 100000 | H12: =IF(G12>0,ROUNDDOWN(F12/G12,0),0) -> 20 | I12: =H12*G12 -> 2000000 | J12: 0 | K12: ='Master Fund Sheet'!M19 -> 0.07875 | L12: =G12*(1+K12)^'Investor Personas'!$F$1 -> 125534.31 | M12: =I12*(1+K12)^'Investor Personas'!$F$1 -> 2510686.1
A13: SMC-NCD-2029 | B13: Bonds | C13: ='Master Fund Sheet'!G20&" / "&'Master Fund Sheet'!B20 -> ICRA A (Stable) / Corporate Bond | D13: — | E13: 0.1 | F13: =E13*'Investor Personas'!$C$1 -> 1000000 | G13: ='Master Fund Sheet'!H20 -> 1000 | H13: =IF(G13>0,ROUNDDOWN(F13/G13,0),0) -> 1000 | I13: =H13*G13 -> 1000000 | J13: 0 | K13: ='Master Fund Sheet'!M20 -> 0.0945 | L13: =G13*(1+K13)^'Investor Personas'!$F$1 -> 1311.1347 | M13: =I13*(1+K13)^'Investor Personas'!$F$1 -> 1311134.7
A15: TOTAL | E15: =SUM(E2:E13) -> 1 | F15: =SUM(F2:F13) -> 10000000 | H15: =COUNTIF(B2:B13,"Equity")&" stocks" -> 9 stocks | I15: =SUM(I2:I13) -> 9989120.4 | M15: =SUM(M2:M13) -> 13175285
A17: PORTFOLIO SUMMARY
A18: Corpus | B18: ='Investor Personas'!$C$1 -> 10000000 | D18: The Capital Guardian · 58, school principal retiring soon. Capital protection first, inflation-beating second.
A19: Invested | B19: =I15 -> 9989120.4 | D19: Policy: 40% equity split 80/15/5 Large/Mid/Small; stocks need investor score ≥ 45 and beta ≤ 1.3; weight ∝ score within each segment, rounded to whole %.
A20: Uninvested cash (earns 3Y G-Sec yield) | B20: =B18-B19 -> 10879.57 | D20: Not selected: ASTRAL, KEI, BATAINDIA, ZEEL, JUSTDIAL
A21: Weighted portfolio beta | B21: =SUMPRODUCT(I2:I13,J2:J13)/B18 -> 0.35347281
A22: Projected value Oct-2029 | B22: =M15+B20*(1+'Master Fund Sheet'!$I$18)^'Investor Personas'!$F$1 -> 13188639
A23: Expected CAGR | B23: =(B22/B18)^(1/'Investor Personas'!$F$1)-1 -> 0.096646514
A24: Target | B24: ='Investor Personas'!C6 -> 13000000
A25: CAGR required | B25: ='Investor Personas'!D6 -> 0.091392883
A26: Surplus / (shortfall) | B26: =B22-B24 -> 188639.19
A27: Portfolio SD (5Y history) | B27: ='Risk Metrics'!E91 -> 0.052433242
A28: Probability of reaching target | B28: =1-NORMSDIST((LN(B24/B18)-LN(1+B23)*'Investor Personas'!$F$1)/(B27*SQRT('Investor Personas'!$F$1))) -> 0.56302036

Sheet Risk Metrics
A1: Ticker | B1: Company | C1: Sector | D1: Cap | E1: Monthly SD (%) | F1: Annualized SD (%) | G1: Beta (vs NIFTY 50) | H1: R-Squared | I1: Correlation | J1: Sharpe Ratio (5Y) | K1: Systematic Risk Profile
A2: ='Master Fund Sheet'!C2 -> RELIANCE | B2: ='Master Fund Sheet'!D2 -> Reliance Industries Ltd | C2: ='Master Fund Sheet'!E2 -> Oil & Gas / Conglomerate | D2: ='Master Fund Sheet'!B2 -> Large Cap | E2: =STDEV(Monthly_Returns!B$2:B$61) -> 0.056243663 | F2: =E2*SQRT(12) -> 0.19483376 | G2: =SLOPE(Monthly_Returns!B$2:B$61,Monthly_Returns!$P$2:$P$61) -> 0.99084157 | H2: =RSQ(Monthly_Returns!B$2:B$61,Monthly_Returns!$P$2:$P$61) -> 0.46556832 | I2: =CORREL(Monthly_Returns!B$2:B$61,Monthly_Returns!$P$2:$P$61) -> 0.68232567 | J2: =('Master Fund Sheet'!M2-'Investor Personas'!$C$13)/F2 -> -0.33652089 | K2: =IF(G2<0.8,"Defensive (Low Beta < 0.8)",IF(G2<=1.2,"Market Correlated (0.8 - 1.2)","Aggressive (High Beta > 1.2)")) -> Market Correlated (0.8 - 1.2)
A3: ='Master Fund Sheet'!C3 -> HDFCBANK | B3: ='Master Fund Sheet'!D3 -> HDFC Bank Ltd | C3: ='Master Fund Sheet'!E3 -> Private Sector Banking | D3: ='Master Fund Sheet'!B3 -> Large Cap | E3: =STDEV(Monthly_Returns!C$2:C$61) -> 0.052811002 | F3: =E3*SQRT(12) -> 0.18294268 | G3: =SLOPE(Monthly_Returns!C$2:C$61,Monthly_Returns!$P$2:$P$61) -> 0.884506 | H3: =RSQ(Monthly_Returns!C$2:C$61,Monthly_Returns!$P$2:$P$61) -> 0.42079922 | I3: =CORREL(Monthly_Returns!C$2:C$61,Monthly_Returns!$P$2:$P$61) -> 0.64869039 | J3: =('Master Fund Sheet'!M3-'Investor Personas'!$C$13)/F3 -> -0.4579604 | K3: =IF(G3<0.8,"Defensive (Low Beta < 0.8)",IF(G3<=1.2,"Market Correlated (0.8 - 1.2)","Aggressive (High Beta > 1.2)")) -> Market Correlated (0.8 - 1.2)
A4: ='Master Fund Sheet'!C4 -> INFY | B4: ='Master Fund Sheet'!D4 -> Infosys Ltd | C4: ='Master Fund Sheet'!E4 -> IT Services | D4: ='Master Fund Sheet'!B4 -> Large Cap | E4: =STDEV(Monthly_Returns!D$2:D$61) -> 0.074673717 | F4: =E4*SQRT(12) -> 0.25867734 | G4: =SLOPE(Monthly_Returns!D$2:D$61,Monthly_Returns!$P$2:$P$61) -> 0.75751049 | H4: =RSQ(Monthly_Returns!D$2:D$61,Monthly_Returns!$P$2:$P$61) -> 0.15437037 | I4: =CORREL(Monthly_Returns!D$2:D$61,Monthly_Returns!$P$2:$P$61) -> 0.39289995 | J4: =('Master Fund Sheet'!M4-'Investor Personas'!$C$13)/F4 -> -0.56970564 | K4: =IF(G4<0.8,"Defensive (Low Beta < 0.8)",IF(G4<=1.2,"Market Correlated (0.8 - 1.2)","Aggressive (High Beta > 1.2)")) -> Defensive (Low Beta < 0.8)
A5: ='Master Fund Sheet'!C5 -> ITC | B5: ='Master Fund Sheet'!D5 -> ITC Ltd | C5: ='Master Fund Sheet'!E5 -> FMCG (Cigarettes, Foods, Agri) | D5: ='Master Fund Sheet'!B5 -> Large Cap | E5: =STDEV(Monthly_Returns!E$2:E$61) -> 0.061375623 | F5: =E5*SQRT(12) -> 0.2126114 | G5: =SLOPE(Monthly_Returns!E$2:E$61,Monthly_Returns!$P$2:$P$61) -> 0.81842432 | H5: =RSQ(Monthly_Returns!E$2:E$61,Monthly_Returns!$P$2:$P$61) -> 0.26673955 | I5: =CORREL(Monthly_Returns!E$2:E$61,Monthly_Returns!$P$2:$P$61) -> 0.51646834 | J5: =('Master Fund Sheet'!M5-'Investor Personas'!$C$13)/F5 -> -0.0089216986 | K5: =IF(G5<0.8,"Defensive (Low Beta < 0.8)",IF(G5<=1.2,"Market Correlated (0.8 - 1.2)","Aggressive (High Beta > 1.2)")) -> Market Correlated (0.8 - 1.2)
A6: ='Master Fund Sheet'!C6 -> SUNPHARMA | B6: ='Master Fund Sheet'!D6 -> Sun Pharmaceutical Industries Ltd | C6: ='Master Fund Sheet'!E6 -> Pharmaceuticals | D6: ='Master Fund Sheet'!B6 -> Large Cap | E6: =STDEV(Monthly_Returns!F$2:F$61) -> 0.064075023 | F6: =E6*SQRT(12) -> 0.22196239 | G6: =SLOPE(Monthly_Returns!F$2:F$61,Monthly_Returns!$P$2:$P$61) -> 0.87112781 | H6: =RSQ(Monthly_Returns!F$2:F$61,Monthly_Returns!$P$2:$P$61) -> 0.27727352 | I6: =CORREL(Monthly_Returns!F$2:F$61,Monthly_Returns!$P$2:$P$61) -> 0.52656768 | J6: =('Master Fund Sheet'!M6-'Investor Personas'!$C$13)/F6 -> 0.50044572 | K6: =IF(G6<0.8,"Defensive (Low Beta < 0.8)",IF(G6<=1.2,"Market Correlated (0.8 - 1.2)","Aggressive (High Beta > 1.2)")) -> Market Correlated (0.8 - 1.2)
A7: ='Master Fund Sheet'!C7 -> MARUTI | B7: ='Master Fund Sheet'!D7 -> Maruti Suzuki India Ltd | C7: ='Master Fund Sheet'!E7 -> Automobiles (Passenger Vehicles) | D7: ='Master Fund Sheet'!B7 -> Large Cap | E7: =STDEV(Monthly_Returns!G$2:G$61) -> 0.070190359 | F7: =E7*SQRT(12) -> 0.24314654 | G7: =SLOPE(Monthly_Returns!G$2:G$61,Monthly_Returns!$P$2:$P$61) -> 0.68561437 | H7: =RSQ(Monthly_Returns!G$2:G$61,Monthly_Returns!$P$2:$P$61) -> 0.14312881 | I7: =CORREL(Monthly_Returns!G$2:G$61,Monthly_Returns!$P$2:$P$61) -> 0.37832369 | J7: =('Master Fund Sheet'!M7-'Investor Personas'!$C$13)/F7 -> 0.16233649 | K7: =IF(G7<0.8,"Defensive (Low Beta < 0.8)",IF(G7<=1.2,"Market Correlated (0.8 - 1.2)","Aggressive (High Beta > 1.2)")) -> Defensive (Low Beta < 0.8)
A8: ='Master Fund Sheet'!C8 -> TATASTEEL | B8: ='Master Fund Sheet'!D8 -> Tata Steel Ltd | C8: ='Master Fund Sheet'!E8 -> Metals & Mining (Steel) | D8: ='Master Fund Sheet'!B8 -> Large Cap | E8: =STDEV(Monthly_Returns!H$2:H$61) -> 0.082937161 | F8: =E8*SQRT(12) -> 0.28730275 | G8: =SLOPE(Monthly_Returns!H$2:H$61,Monthly_Returns!$P$2:$P$61) -> 1.1923044 | H8: =RSQ(Monthly_Returns!H$2:H$61,Monthly_Returns!$P$2:$P$61) -> 0.31002603 | I8: =CORREL(Monthly_Returns!H$2:H$61,Monthly_Returns!$P$2:$P$61) -> 0.55679981 | J8: =('Master Fund Sheet'!M8-'Investor Personas'!$C$13)/F8 -> 0.11461095 | K8: =IF(G8<0.8,"Defensive (Low Beta < 0.8)",IF(G8<=1.2,"Market Correlated (0.8 - 1.2)","Aggressive (High Beta > 1.2)")) -> Market Correlated (0.8 - 1.2)
A9: ='Master Fund Sheet'!C9 -> DABUR | B9: ='Master Fund Sheet'!D9 -> Dabur India Ltd | C9: ='Master Fund Sheet'!E9 -> Personal Care & Ayurveda | D9: ='Master Fund Sheet'!B9 -> Mid Cap | E9: =STDEV(Monthly_Returns!I$2:I$61) -> 0.05895694 | F9: =E9*SQRT(12) -> 0.20423283 | G9: =SLOPE(Monthly_Returns!I$2:I$61,Monthly_Returns!$P$2:$P$61) -> 0.869804 | H9: =RSQ(Monthly_Returns!I$2:I$61,Monthly_Returns!$P$2:$P$61) -> 0.32650896 | I9: =CORREL(Monthly_Returns!I$2:I$61,Monthly_Returns!$P$2:$P$61) -> 0.57140963 | J9: =('Master Fund Sheet'!M9-'Investor Personas'!$C$13)/F9 -> -0.75768952 | K9: =IF(G9<0.8,"Defensive (Low Beta < 0.8)",IF(G9<=1.2,"Market Correlated (0.8 - 1.2)","Aggressive (High Beta > 1.2)")) -> Market Correlated (0.8 - 1.2)
A10: ='Master Fund Sheet'!C10 -> ASTRAL | B10: ='Master Fund Sheet'!D10 -> Astral Ltd | C10: ='Master Fund Sheet'!E10 -> Building Materials (Pipes) | D10: ='Master Fund Sheet'!B10 -> Mid Cap | E10: =STDEV(Monthly_Returns!J$2:J$61) -> 0.083410465 | F10: =E10*SQRT(12) -> 0.28894233 | G10: =SLOPE(Monthly_Returns!J$2:J$61,Monthly_Returns!$P$2:$P$61) -> 0.69741418 | H10: =RSQ(Monthly_Returns!J$2:J$61,Monthly_Returns!$P$2:$P$61) -> 0.10487275 | I10: =CORREL(Monthly_Returns!J$2:J$61,Monthly_Returns!$P$2:$P$61) -> 0.32384062 | J10: =('Master Fund Sheet'!M10-'Investor Personas'!$C$13)/F10 -> -0.36145099 | K10: =IF(G10<0.8,"Defensive (Low Beta < 0.8)",IF(G10<=1.2,"Market Correlated (0.8 - 1.2)","Aggressive (High Beta > 1.2)")) -> Defensive (Low Beta < 0.8)
A11: ='Master Fund Sheet'!C11 -> KEI | B11: ='Master Fund Sheet'!D11 -> KEI Industries Ltd | C11: ='Master Fund Sheet'!E11 -> Electricals (Cables & Wires) | D11: ='Master Fund Sheet'!B11 -> Mid Cap | E11: =STDEV(Monthly_Returns!K$2:K$61) -> 0.10863099 | F11: =E11*SQRT(12) -> 0.3763088 | G11: =SLOPE(Monthly_Returns!K$2:K$61,Monthly_Returns!$P$2:$P$61) -> 1.4331655 | H11: =RSQ(Monthly_Returns!K$2:K$61,Monthly_Returns!$P$2:$P$61) -> 0.2611003 | I11: =CORREL(Monthly_Returns!K$2:K$61,Monthly_Returns!$P$2:$P$61) -> 0.51097974 | J11: =('Master Fund Sheet'!M11-'Investor Personas'!$C$13)/F11 -> 0.79007536 | K11: =IF(G11<0.8,"Defensive (Low Beta < 0.8)",IF(G11<=1.2,"Market Correlated (0.8 - 1.2)","Aggressive (High Beta > 1.2)")) -> Aggressive (High Beta > 1.2)
A12: ='Master Fund Sheet'!C12 -> BATAINDIA | B12: ='Master Fund Sheet'!D12 -> Bata India Ltd | C12: ='Master Fund Sheet'!E12 -> Footwear & Retail | D12: ='Master Fund Sheet'!B12 -> Small Cap | E12: =STDEV(Monthly_Returns!L$2:L$61) -> 0.072533767 | F12: =E12*SQRT(12) -> 0.25126434 | G12: =SLOPE(Monthly_Returns!L$2:L$61,Monthly_Returns!$P$2:$P$61) -> 1.2813252 | H12: =RSQ(Monthly_Returns!L$2:L$61,Monthly_Returns!$P$2:$P$61) -> 0.46812352 | I12: =CORREL(Monthly_Returns!L$2:L$61,Monthly_Returns!$P$2:$P$61) -> 0.68419553 | J12: =('Master Fund Sheet'!M12-'Investor Personas'!$C$13)/F12 -> -0.98182296 | K12: =IF(G12<0.8,"Defensive (Low Beta < 0.8)",IF(G12<=1.2,"Market Correlated (0.8 - 1.2)","Aggressive (High Beta > 1.2)")) -> Aggressive (High Beta > 1.2)
A13: ='Master Fund Sheet'!C13 -> ZEEL | B13: ='Master Fund Sheet'!D13 -> Zee Entertainment Enterprises Ltd | C13: ='Master Fund Sheet'!E13 -> Media & Entertainment | D13: ='Master Fund Sheet'!B13 -> Small Cap | E13: =STDEV(Monthly_Returns!M$2:M$61) -> 0.12554605 | F13: =E13*SQRT(12) -> 0.43490426 | G13: =SLOPE(Monthly_Returns!M$2:M$61,Monthly_Returns!$P$2:$P$61) -> 1.6233346 | H13: =RSQ(Monthly_Returns!M$2:M$61,Monthly_Returns!$P$2:$P$61) -> 0.25080269 | I13: =CORREL(Monthly_Returns!M$2:M$61,Monthly_Returns!$P$2:$P$61) -> 0.50080204 | J13: =('Master Fund Sheet'!M13-'Investor Personas'!$C$13)/F13 -> -0.70983039 | K13: =IF(G13<0.8,"Defensive (Low Beta < 0.8)",IF(G13<=1.2,"Market Correlated (0.8 - 1.2)","Aggressive (High Beta > 1.2)")) -> Aggressive (High Beta > 1.2)
A14: ='Master Fund Sheet'!C14 -> JUSTDIAL | B14: ='Master Fund Sheet'!D14 -> Just Dial Ltd | C14: ='Master Fund Sheet'!E14 -> Internet / Local Search Services | D14: ='Master Fund Sheet'!B14 -> Small Cap | E14: =STDEV(Monthly_Returns!N$2:N$61) -> 0.12730985 | F14: =E14*SQRT(12) -> 0.44101425 | G14: =SLOPE(Monthly_Returns!N$2:N$61,Monthly_Returns!$P$2:$P$61) -> 1.2835508 | H14: =RSQ(Monthly_Returns!N$2:N$61,Monthly_Returns!$P$2:$P$61) -> 0.15248402 | I14: =CORREL(Monthly_Returns!N$2:N$61,Monthly_Returns!$P$2:$P$61) -> 0.39049202 | J14: =('Master Fund Sheet'!M14-'Investor Personas'!$C$13)/F14 -> -0.33906071 | K14: =IF(G14<0.8,"Defensive (Low Beta < 0.8)",IF(G14<=1.2,"Market Correlated (0.8 - 1.2)","Aggressive (High Beta > 1.2)")) -> Aggressive (High Beta > 1.2)
A15: ='Master Fund Sheet'!C15 -> EIHOTEL | B15: ='Master Fund Sheet'!D15 -> EIH Ltd (The Oberoi Group) | C15: ='Master Fund Sheet'!E15 -> Hotels & Hospitality | D15: ='Master Fund Sheet'!B15 -> Small Cap | E15: =STDEV(Monthly_Returns!O$2:O$61) -> 0.10475152 | F15: =E15*SQRT(12) -> 0.36286992 | G15: =SLOPE(Monthly_Returns!O$2:O$61,Monthly_Returns!$P$2:$P$61) -> 1.1041444 | H15: =RSQ(Monthly_Returns!O$2:O$61,Monthly_Returns!$P$2:$P$61) -> 0.1666684 | I15: =CORREL(Monthly_Returns!O$2:O$61,Monthly_Returns!$P$2:$P$61) -> 0.40825041 | J15: =('Master Fund Sheet'!M15-'Investor Personas'!$C$13)/F15 -> 0.31554744 | K15: =IF(G15<0.8,"Defensive (Low Beta < 0.8)",IF(G15<=1.2,"Market Correlated (0.8 - 1.2)","Aggressive (High Beta > 1.2)")) -> Market Correlated (0.8 - 1.2)
A17: NIFTY_50 | B17: Benchmark | E17: =STDEV(Monthly_Returns!P2:P61) -> 0.038731212 | F17: =E17*SQRT(12) -> 0.13416885 | G17: 1
A19: Method: 60 monthly returns (Oct-2021 to Sep-2026) from dividend-adjusted closes. Beta = SLOPE(stock, NIFTY 50) - the same 5Y-monthly convention Yahoo uses. SD annualised by √12.
A21: PORTFOLIO RISK FROM 5-YEAR HISTORY (today's weights applied to past monthly returns)
A22: Persona | B22: RELIANCE | C22: HDFCBANK | D22: INFY | E22: ITC | F22: SUNPHARMA | G22: MARUTI | H22: TATASTEEL | I22: DABUR | J22: ASTRAL | K22: KEI | L22: BATAINDIA | M22: ZEEL | N22: JUSTDIAL | O22: EIHOTEL | P22: Debt Weight | Q22: Debt Yield
A23: Vikram | B23: =SUMIF(Vikram!$A$2:$A$14,"RELIANCE",Vikram!$E$2:$E$14) -> 0.05 | C23: =SUMIF(Vikram!$A$2:$A$14,"HDFCBANK",Vikram!$E$2:$E$14) -> 0.06 | D23: =SUMIF(Vikram!$A$2:$A$14,"INFY",Vikram!$E$2:$E$14) -> 0.06 | E23: =SUMIF(Vikram!$A$2:$A$14,"ITC",Vikram!$E$2:$E$14) -> 0.04 | F23: =SUMIF(Vikram!$A$2:$A$14,"SUNPHARMA",Vikram!$E$2:$E$14) -> 0.06 | G23: =SUMIF(Vikram!$A$2:$A$14,"MARUTI",Vikram!$E$2:$E$14) -> 0.06 | H23: =SUMIF(Vikram!$A$2:$A$14,"TATASTEEL",Vikram!$E$2:$E$14) -> 0.05 | I23: =SUMIF(Vikram!$A$2:$A$14,"DABUR",Vikram!$E$2:$E$14) -> 0.09 | J23: =SUMIF(Vikram!$A$2:$A$14,"ASTRAL",Vikram!$E$2:$E$14) -> 0.1 | K23: =SUMIF(Vikram!$A$2:$A$14,"KEI",Vikram!$E$2:$E$14) -> 0.14 | L23: =SUMIF(Vikram!$A$2:$A$14,"BATAINDIA",Vikram!$E$2:$E$14) -> 0 | M23: =SUMIF(Vikram!$A$2:$A$14,"ZEEL",Vikram!$E$2:$E$14) -> 0 | N23: =SUMIF(Vikram!$A$2:$A$14,"JUSTDIAL",Vikram!$E$2:$E$14) -> 0.12 | O23: =SUMIF(Vikram!$A$2:$A$14,"EIHOTEL",Vikram!$E$2:$E$14) -> 0.12 | P23: =SUMIF(Vikram!$B$2:$B$14,"Bonds",Vikram!$E$2:$E$14) -> 0.05 | Q23: =IF(P23>0,SUMPRODUCT((Vikram!$B$2:$B$14="Bonds")*Vikram!$E$2:$E$14*Vikram!$K$2:$K$14)/P23,0) -> 0.0945
A24: Ananya | B24: =SUMIF(Ananya!$A$2:$A$16,"RELIANCE",Ananya!$E$2:$E$16) -> 0.06 | C24: =SUMIF(Ananya!$A$2:$A$16,"HDFCBANK",Ananya!$E$2:$E$16) -> 0.06 | D24: =SUMIF(Ananya!$A$2:$A$16,"INFY",Ananya!$E$2:$E$16) -> 0.07 | E24: =SUMIF(Ananya!$A$2:$A$16,"ITC",Ananya!$E$2:$E$16) -> 0.05 | F24: =SUMIF(Ananya!$A$2:$A$16,"SUNPHARMA",Ananya!$E$2:$E$16) -> 0.06 | G24: =SUMIF(Ananya!$A$2:$A$16,"MARUTI",Ananya!$E$2:$E$16) -> 0.07 | H24: =SUMIF(Ananya!$A$2:$A$16,"TATASTEEL",Ananya!$E$2:$E$16) -> 0.06 | I24: =SUMIF(Ananya!$A$2:$A$16,"DABUR",Ananya!$E$2:$E$16) -> 0.08 | J24: =SUMIF(Ananya!$A$2:$A$16,"ASTRAL",Ananya!$E$2:$E$16) -> 0.07 | K24: =SUMIF(Ananya!$A$2:$A$16,"KEI",Ananya!$E$2:$E$16) -> 0.1 | L24: =SUMIF(Ananya!$A$2:$A$16,"BATAINDIA",Ananya!$E$2:$E$16) -> 0 | M24: =SUMIF(Ananya!$A$2:$A$16,"ZEEL",Ananya!$E$2:$E$16) -> 0 | N24: =SUMIF(Ananya!$A$2:$A$16,"JUSTDIAL",Ananya!$E$2:$E$16) -> 0.08 | O24: =SUMIF(Ananya!$A$2:$A$16,"EIHOTEL",Ananya!$E$2:$E$16) -> 0.09 | P24: =SUMIF(Ananya!$B$2:$B$16,"Bonds",Ananya!$E$2:$E$16) -> 0.15 | Q24: =IF(P24>0,SUMPRODUCT((Ananya!$B$2:$B$16="Bonds")*Ananya!$E$2:$E$16*Ananya!$K$2:$K$16)/P24,0) -> 0.081316667
A25: Rohan | B25: =SUMIF(Rohan!$A$2:$A$16,"RELIANCE",Rohan!$E$2:$E$16) -> 0.06 | C25: =SUMIF(Rohan!$A$2:$A$16,"HDFCBANK",Rohan!$E$2:$E$16) -> 0.06 | D25: =SUMIF(Rohan!$A$2:$A$16,"INFY",Rohan!$E$2:$E$16) -> 0.07 | E25: =SUMIF(Rohan!$A$2:$A$16,"ITC",Rohan!$E$2:$E$16) -> 0.05 | F25: =SUMIF(Rohan!$A$2:$A$16,"SUNPHARMA",Rohan!$E$2:$E$16) -> 0.06 | G25: =SUMIF(Rohan!$A$2:$A$16,"MARUTI",Rohan!$E$2:$E$16) -> 0.07 | H25: =SUMIF(Rohan!$A$2:$A$16,"TATASTEEL",Rohan!$E$2:$E$16) -> 0.05 | I25: =SUMIF(Rohan!$A$2:$A$16,"DABUR",Rohan!$E$2:$E$16) -> 0.05 | J25: =SUMIF(Rohan!$A$2:$A$16,"ASTRAL",Rohan!$E$2:$E$16) -> 0.05 | K25: =SUMIF(Rohan!$A$2:$A$16,"KEI",Rohan!$E$2:$E$16) -> 0.06 | L25: =SUMIF(Rohan!$A$2:$A$16,"BATAINDIA",Rohan!$E$2:$E$16) -> 0 | M25: =SUMIF(Rohan!$A$2:$A$16,"ZEEL",Rohan!$E$2:$E$16) -> 0 | N25: =SUMIF(Rohan!$A$2:$A$16,"JUSTDIAL",Rohan!$E$2:$E$16) -> 0.03 | O25: =SUMIF(Rohan!$A$2:$A$16,"EIHOTEL",Rohan!$E$2:$E$16) -> 0.04 | P25: =SUMIF(Rohan!$B$2:$B$16,"Bonds",Rohan!$E$2:$E$16) -> 0.35 | Q25: =IF(P25>0,SUMPRODUCT((Rohan!$B$2:$B$16="Bonds")*Rohan!$E$2:$E$16*Rohan!$K$2:$K$16)/P25,0) -> 0.0789
A26: Meera | B26: =SUMIF(Meera!$A$2:$A$13,"RELIANCE",Meera!$E$2:$E$13) -> 0.04 | C26: =SUMIF(Meera!$A$2:$A$13,"HDFCBANK",Meera!$E$2:$E$13) -> 0.05 | D26: =SUMIF(Meera!$A$2:$A$13,"INFY",Meera!$E$2:$E$13) -> 0.05 | E26: =SUMIF(Meera!$A$2:$A$13,"ITC",Meera!$E$2:$E$13) -> 0.04 | F26: =SUMIF(Meera!$A$2:$A$13,"SUNPHARMA",Meera!$E$2:$E$13) -> 0.05 | G26: =SUMIF(Meera!$A$2:$A$13,"MARUTI",Meera!$E$2:$E$13) -> 0.05 | H26: =SUMIF(Meera!$A$2:$A$13,"TATASTEEL",Meera!$E$2:$E$13) -> 0.04 | I26: =SUMIF(Meera!$A$2:$A$13,"DABUR",Meera!$E$2:$E$13) -> 0.06 | J26: =SUMIF(Meera!$A$2:$A$13,"ASTRAL",Meera!$E$2:$E$13) -> 0 | K26: =SUMIF(Meera!$A$2:$A$13,"KEI",Meera!$E$2:$E$13) -> 0 | L26: =SUMIF(Meera!$A$2:$A$13,"BATAINDIA",Meera!$E$2:$E$13) -> 0 | M26: =SUMIF(Meera!$A$2:$A$13,"ZEEL",Meera!$E$2:$E$13) -> 0 | N26: =SUMIF(Meera!$A$2:$A$13,"JUSTDIAL",Meera!$E$2:$E$13) -> 0 | O26: =SUMIF(Meera!$A$2:$A$13,"EIHOTEL",Meera!$E$2:$E$13) -> 0.02 | P26: =SUMIF(Meera!$B$2:$B$13,"Bonds",Meera!$E$2:$E$13) -> 0.6 | Q26: =IF(P26>0,SUMPRODUCT((Meera!$B$2:$B$13="Bonds")*Meera!$E$2:$E$13*Meera!$K$2:$K$13)/P26,0) -> 0.07735
A28: Month | B28: Vikram | C28: Ananya | D28: Rohan | E28: Meera | F28: NIFTY_50
A29: =Monthly_Returns!A2 -> 44500 | B29: =SUMPRODUCT($B$23:$O$23,Monthly_Returns!$B2:$O2)+$P$23*$Q$23/12 -> -0.021215749 | C29: =SUMPRODUCT($B$24:$O$24,Monthly_Returns!$B2:$O2)+$P$24*$Q$24/12 -> -0.014277112 | D29: =SUMPRODUCT($B$25:$O$25,Monthly_Returns!$B2:$O2)+$P$25*$Q$25/12 -> -0.0052469999 | E29: =SUMPRODUCT($B$26:$O$26,Monthly_Returns!$B2:$O2)+$P$26*$Q$26/12 -> 0.00060420502 | F29: =Monthly_Returns!P2 -> 0.0030366412
A30: =Monthly_Returns!A3 -> 44530 | B30: =SUMPRODUCT($B$23:$O$23,Monthly_Returns!$B3:$O3)+$P$23*$Q$23/12 -> -0.025755257 | C30: =SUMPRODUCT($B$24:$O$24,Monthly_Returns!$B3:$O3)+$P$24*$Q$24/12 -> -0.025494959 | D30: =SUMPRODUCT($B$25:$O$25,Monthly_Returns!$B3:$O3)+$P$25*$Q$25/12 -> -0.015840521 | E30: =SUMPRODUCT($B$26:$O$26,Monthly_Returns!$B3:$O3)+$P$26*$Q$26/12 -> -0.014311684 | F30: =Monthly_Returns!P3 -> -0.038957879
A31: =Monthly_Returns!A4 -> 44561 | B31: =SUMPRODUCT($B$23:$O$23,Monthly_Returns!$B4:$O4)+$P$23*$Q$23/12 -> 0.06054728 | C31: =SUMPRODUCT($B$24:$O$24,Monthly_Returns!$B4:$O4)+$P$24*$Q$24/12 -> 0.048572811 | D31: =SUMPRODUCT($B$25:$O$25,Monthly_Returns!$B4:$O4)+$P$25*$Q$25/12 -> 0.032976592 | E31: =SUMPRODUCT($B$26:$O$26,Monthly_Returns!$B4:$O4)+$P$26*$Q$26/12 -> 0.016653959 | F31: =Monthly_Returns!P4 -> 0.021836285
A32: =Monthly_Returns!A5 -> 44592 | B32: =SUMPRODUCT($B$23:$O$23,Monthly_Returns!$B5:$O5)+$P$23*$Q$23/12 -> 0.0095891345 | C32: =SUMPRODUCT($B$24:$O$24,Monthly_Returns!$B5:$O5)+$P$24*$Q$24/12 -> 0.0081959942 | D32: =SUMPRODUCT($B$25:$O$25,Monthly_Returns!$B5:$O5)+$P$25*$Q$25/12 -> 0.0042690148 | E32: =SUMPRODUCT($B$26:$O$26,Monthly_Returns!$B5:$O5)+$P$26*$Q$26/12 -> 0.0051577311 | F32: =Monthly_Returns!P5 -> -0.0008182528
A33: =Monthly_Returns!A6 -> 44620 | B33: =SUMPRODUCT($B$23:$O$23,Monthly_Returns!$B6:$O6)+$P$23*$Q$23/12 -> -0.045043779 | C33: =SUMPRODUCT($B$24:$O$24,Monthly_Returns!$B6:$O6)+$P$24*$Q$24/12 -> -0.028568016 | D33: =SUMPRODUCT($B$25:$O$25,Monthly_Returns!$B6:$O6)+$P$25*$Q$25/12 -> -0.012088674 | E33: =SUMPRODUCT($B$26:$O$26,Monthly_Returns!$B6:$O6)+$P$26*$Q$26/12 -> 0.0067136493 | F33: =Monthly_Returns!P6 -> -0.031485278
A34: =Monthly_Returns!A7 -> 44651 | B34: =SUMPRODUCT($B$23:$O$23,Monthly_Returns!$B7:$O7)+$P$23*$Q$23/12 -> 0.080441855 | C34: =SUMPRODUCT($B$24:$O$24,Monthly_Returns!$B7:$O7)+$P$24*$Q$24/12 -> 0.069000211 | D34: =SUMPRODUCT($B$25:$O$25,Monthly_Returns!$B7:$O7)+$P$25*$Q$25/12 -> 0.051819365 | E34: =SUMPRODUCT($B$26:$O$26,Monthly_Returns!$B7:$O7)+$P$26*$Q$26/12 -> 0.025543761 | F34: =Monthly_Returns!P7 -> 0.039946052
A35: =Monthly_Returns!A8 -> 44681 | B35: =SUMPRODUCT($B$23:$O$23,Monthly_Returns!$B8:$O8)+$P$23*$Q$23/12 -> 0.024638953 | C35: =SUMPRODUCT($B$24:$O$24,Monthly_Returns!$B8:$O8)+$P$24*$Q$24/12 -> 0.014332212 | D35: =SUMPRODUCT($B$25:$O$25,Monthly_Returns!$B8:$O8)+$P$25*$Q$25/12 -> 0.0029293858 | E35: =SUMPRODUCT($B$26:$O$26,Monthly_Returns!$B8:$O8)+$P$26*$Q$26/12 -> -0.00043771468 | F35: =Monthly_Returns!P8 -> -0.020738917
A36: =Monthly_Returns!A9 -> 44712 | B36: =SUMPRODUCT($B$23:$O$23,Monthly_Returns!$B9:$O9)+$P$23*$Q$23/12 -> -0.080459247 | C36: =SUMPRODUCT($B$24:$O$24,Monthly_Returns!$B9:$O9)+$P$24*$Q$24/12 -> -0.061867088 | D36: =SUMPRODUCT($B$25:$O$25,Monthly_Returns!$B9:$O9)+$P$25*$Q$25/12 -> -0.03451957 | E36: =SUMPRODUCT($B$26:$O$26,Monthly_Returns!$B9:$O9)+$P$26*$Q$26/12 -> -0.012502315 | F36: =Monthly_Returns!P9 -> -0.030287881
A37: =Monthly_Returns!A10 -> 44742 | B37: =SUMPRODUCT($B$23:$O$23,Monthly_Returns!$B10:$O10)+$P$23*$Q$23/12 -> -0.052669332 | C37: =SUMPRODUCT($B$24:$O$24,Monthly_Returns!$B10:$O10)+$P$24*$Q$24/12 -> -0.040528883 | D37: =SUMPRODUCT($B$25:$O$25,Monthly_Returns!$B10:$O10)+$P$25*$Q$25/12 -> -0.021932569 | E37: =SUMPRODUCT($B$26:$O$26,Monthly_Returns!$B10:$O10)+$P$26*$Q$26/12 -> -0.0072626463 | F37: =Monthly_Returns!P10 -> -0.048496944
A38: =Monthly_Returns!A11 -> 44773 | B38: =SUMPRODUCT($B$23:$O$23,Monthly_Returns!$B11:$O11)+$P$23*$Q$23/12 -> 0.097992714 | C38: =SUMPRODUCT($B$24:$O$24,Monthly_Returns!$B11:$O11)+$P$24*$Q$24/12 -> 0.087595126 | D38: =SUMPRODUCT($B$25:$O$25,Monthly_Returns!$B11:$O11)+$P$25*$Q$25/12 -> 0.064145017 | E38: =SUMPRODUCT($B$26:$O$26,Monthly_Returns!$B11:$O11)+$P$26*$Q$26/12 -> 0.046475968 | F38: =Monthly_Returns!P11 -> 0.087324345
A39: =Monthly_Returns!A12 -> 44804 | B39: =SUMPRODUCT($B$23:$O$23,Monthly_Returns!$B12:$O12)+$P$23*$Q$23/12 -> 0.056626455 | C39: =SUMPRODUCT($B$24:$O$24,Monthly_Returns!$B12:$O12)+$P$24*$Q$24/12 -> 0.043721434 | D39: =SUMPRODUCT($B$25:$O$25,Monthly_Returns!$B12:$O12)+$P$25*$Q$25/12 -> 0.030316473 | E39: =SUMPRODUCT($B$26:$O$26,Monthly_Returns!$B12:$O12)+$P$26*$Q$26/12 -> 0.0093494038 | F39: =Monthly_Returns!P12 -> 0.035029796
A40: =Monthly_Returns!A13 -> 44834 | B40: =SUMPRODUCT($B$23:$O$23,Monthly_Returns!$B13:$O13)+$P$23*$Q$23/12 -> 0.0069111524 | C40: =SUMPRODUCT($B$24:$O$24,Monthly_Returns!$B13:$O13)+$P$24*$Q$24/12 -> 0.00072493591 | D40: =SUMPRODUCT($B$25:$O$25,Monthly_Returns!$B13:$O13)+$P$25*$Q$25/12 -> -0.0036356403 | E40: =SUMPRODUCT($B$26:$O$26,Monthly_Returns!$B13:$O13)+$P$26*$Q$26/12 -> -0.0027957187 | F40: =Monthly_Returns!P13 -> -0.037442354
... A88: =Monthly_Returns!A61 -> 46295 | B88: =SUMPRODUCT($B$23:$O$23,Monthly_Returns!$B61:$O61)+$P$23*$Q$23/12 -> -0.062493019 | C88: =SUMPRODUCT($B$24:$O$24,Monthly_Returns!$B61:$O61)+$P$24*$Q$24/12 -> -0.052237704 | D88: =SUMPRODUCT($B$25:$O$25,Monthly_Returns!$B61:$O61)+$P$25*$Q$25/12 -> -0.040157078 | E88: =SUMPRODUCT($B$26:$O$26,Monthly_Returns!$B61:$O61)+$P$26*$Q$26/12 -> -0.01288785 | F88: =Monthly_Returns!P61 -> -0.060628146
A90: Statistic | B90: Vikram | C90: Ananya | D90: Rohan | E90: Meera | F90: NIFTY_50
A91: Annualised SD | B91: =STDEV(B29:B88)*SQRT(12) -> 0.16173329 | C91: =STDEV(C29:C88)*SQRT(12) -> 0.13370298 | D91: =STDEV(D29:D88)*SQRT(12) -> 0.092753311 | E91: =STDEV(E29:E88)*SQRT(12) -> 0.052433242 | F91: =STDEV(F29:F88)*SQRT(12) -> 0.13416885
A92: Beta vs NIFTY 50 | B92: =SLOPE(B29:B88,$F$29:$F$88) -> 0.96901017 | C92: =SLOPE(C29:C88,$F$29:$F$88) -> 0.84204367 | D92: =SLOPE(D29:D88,$F$29:$F$88) -> 0.61336684 | E92: =SLOPE(E29:E88,$F$29:$F$88) -> 0.35427187 | F92: =SLOPE(F29:F88,$F$29:$F$88) -> 1
A93: Best month | B93: =MAX(B29:B88) -> 0.097992714 | C93: =MAX(C29:C88) -> 0.087595126 | D93: =MAX(D29:D88) -> 0.064145017 | E93: =MAX(E29:E88) -> 0.046475968 | F93: =MAX(F29:F88) -> 0.087324345
A94: Worst month | B94: =MIN(B29:B88) -> -0.11185819 | C94: =MIN(C29:C88) -> -0.095801837 | D94: =MIN(D29:D88) -> -0.066485683 | E94: =MIN(E29:E88) -> -0.038487617 | F94: =MIN(F29:F88) -> -0.11308192

Sheet Investor Personas
A1: CORPUS | C1: 10000000 | E1: Horizon (yrs) | F1: 3
A2: Name | B2: Type of Investor | C2: Target (3Y) | D2: CAGR Required | E2: Risk Appetite | F2: Equity % | G2: Debt % | H2: Large / Mid / Small split of equity | I2: Max Beta per Stock | J2: Min Score to Qualify | K2: Profile | L2: Expected CAGR | M2: Projected Value (3Y) | N2: Surplus / (Shortfall) | O2: Probability of Target | Q2: Chart data (₹ Cr) | R2: Target | S2: Projected
A3: Vikram | B3: The Momentum Maverick | C3: 21500000 | D3: =(C3/$C$1)^(1/$F$1)-1 -> 0.29066288 | E3: Very High | F3: 0.95 | G3: =1-F3 -> 0.05 | H3: 40 / 35 / 25 | I3: 2.5 | J3: 40 | K3: 31, start-up founder, no dependants. Chases the upper assignment target and tolerates deep drawdowns. | L3: =Vikram!B24 -> 0.12960534 | M3: =Vikram!B23 -> 14413857 | N3: =Vikram!B27 -> -7086143 | O3: =Vikram!B29 -> 0.076729768 | Q3: =A3 -> Vikram | R3: =C3/10^7 -> 2.15 | S3: =M3/10^7 -> 1.4413857
A4: Ananya | B4: The Growth Architect | C4: 20000000 | D4: =(C4/$C$1)^(1/$F$1)-1 -> 0.25992105 | E4: High | F4: 0.85 | G4: =1-F4 -> 0.15 | H4: 50 / 30 / 20 | I4: 1.7 | J4: 40 | K4: 38, strategy consultant, dual income. Targets the lower assignment target with some debt ballast. | L4: =Ananya!B26 -> 0.12306337 | M4: =Ananya!B25 -> 14164876 | N4: =Ananya!B29 -> -5835123.6 | O4: =Ananya!B31 -> 0.068162017 | Q4: =A4 -> Ananya | R4: =C4/10^7 -> 2 | S4: =M4/10^7 -> 1.4164876
A5: Rohan | B5: The Balanced Planner | C5: 16000000 | D5: =(C5/$C$1)^(1/$F$1)-1 -> 0.1696071 | E5: Moderate | F5: 0.65 | G5: =1-F5 -> 0.35 | H5: 65 / 25 / 10 | I5: 1.5 | J5: 40 | K5: 46, surgeon saving for two children's higher education in 3 years. | L5: =Rohan!B26 -> 0.11205938 | M5: =Rohan!B25 -> 13752572 | N5: =Rohan!B29 -> -2247427.7 | O5: =Rohan!B31 -> 0.17305284 | Q5: =A5 -> Rohan | R5: =C5/10^7 -> 1.6 | S5: =M5/10^7 -> 1.3752572
A6: Meera | B6: The Capital Guardian | C6: 13000000 | D6: =(C6/$C$1)^(1/$F$1)-1 -> 0.091392883 | E6: Low | F6: 0.4 | G6: =1-F6 -> 0.6 | H6: 80 / 15 / 5 | I6: 1.3 | J6: 45 | K6: 58, school principal retiring soon. Capital protection first, inflation-beating second. | L6: =Meera!B23 -> 0.096646514 | M6: =Meera!B22 -> 13188639 | N6: =Meera!B26 -> 188639.19 | O6: =Meera!B28 -> 0.56302036 | Q6: =A6 -> Meera | R6: =C6/10^7 -> 1.3 | S6: =M6/10^7 -> 1.3188639
Q8: Reading: the ₹2-2.15 Cr goal needs 26-29% a year; the model's central estimate is far lower, so the probability column is the honest feasibility test the brief asks for.
A9: Model assumptions
A10: Equity risk premium (India) | C10: 0.07 | D10: Mature-market ERP ~4.5% + India country risk ~2.5% (Damodaran-style).
A11: Weight on CAPM in blended return | C11: 0.5 | D11: Expected return = 50% CAPM + 50% (dividend yield + sustainable growth).
A12: Max score tilt (±) | C12: 0.03 | D12: Score 100 → +3% p.a.; score 0 → −3% p.a.; 50 → none.
A13: Risk-free rate Rƒ (10Y G-Sec) | C13: 0.0735 | D13: India 10Y G-Sec 7.35% on 13-Oct-2026 (Trading Economics).
A14: Sustainable growth cap | C14: 0.22 | D14: g = ROE × (1 − payout), capped so no firm compounds >22% for 3 yrs.
A15: RBI repo rate (context) | C15: 0.055 | D15: Hiked 25 bp to 5.50% at the Oct-2026 MPC.

Sheet Scoring Model
A1: SCORING MODEL - how the 14 stocks are ranked and what return each is expected to earn
A2: Step 1: weights (yellow, editable) · Step 2: percentile scores 0-100 · Step 3: composite score per investor · Step 4: expected return = 50% CAPM + 50% fundamental ± score tilt
A4: # | B4: Factor | C4: Better if | D4: House | E4: Vikram | F4: Ananya | G4: Rohan | H4: Meera | I4: Why this factor / why this weight
A5: 1 | B5: Market Cap | C5: Higher | D5: 0.1 | E5: 0.07 | F5: 0.08 | G5: 0.11 | H5: 0.13 | I5: Flagged 'very important' in the brief; size = liquidity, lower impact cost and survival odds.
A6: 2 | B6: Sales Growth YoY | C6: Higher | D6: 0.12 | E6: 0.15 | F6: 0.14 | G6: 0.12 | H6: 0.08 | I6: Flagged 'very important'; top-line growth is hard to manipulate and feeds future EPS.
A7: 3 | B7: EPS Growth YoY | C7: Higher | D7: 0.13 | E7: 0.16 | F7: 0.15 | G7: 0.13 | H7: 0.1 | I7: Flagged 'very important'; over 3 years price ≈ P/E × EPS, so EPS growth drives returns - largest weight.
A8: 4 | B8: ROE | C8: Higher | D8: 0.08 | E8: 0.08 | F8: 0.09 | G8: 0.08 | H8: 0.09 | I8: Shareholder profitability; with retention it sets sustainable growth in the return model.
A9: 5 | B9: ROCE | C9: Higher | D9: 0.09 | E9: 0.08 | F9: 0.09 | G9: 0.09 | H9: 0.1 | I9: Leverage-neutral profitability, so weighted slightly above ROE.
A10: 6 | B10: Trailing P/E | C10: Lower | D10: 0.06 | E10: 0.04 | F10: 0.05 | G10: 0.06 | H10: 0.08 | I10: Starting valuation drives mean reversion; lower is better.
A11: 7 | B11: PEG | C11: Lower | D11: 0.08 | E11: 0.09 | F11: 0.09 | G11: 0.07 | H11: 0.06 | I11: Links price to growth so fast growers are not rejected on P/E alone; negative growth = 0.
A12: 8 | B12: P/BV | C12: Lower | D12: 0.04 | E12: 0.02 | F12: 0.03 | G12: 0.04 | H12: 0.05 | I12: Asset-backing check for capital-heavy firms; low weight for asset-light ones.
A13: 9 | B13: Beta | C13: Lower | D13: 0.06 | E13: 0.03 | F13: 0.05 | G13: 0.07 | H13: 0.1 | I13: Undiversifiable market risk - matters most to the capital guardian.
A14: 10 | B14: Annualised SD | C14: Lower | D14: 0.06 | E14: 0.03 | F14: 0.05 | G14: 0.07 | H14: 0.1 | I14: Total volatility incl. stock-specific risk.
A15: 11 | B15: Price vs 10M SMA | C15: Higher | D15: 0.05 | E15: 0.09 | F15: 0.06 | G15: 0.04 | H15: 0.02 | I15: Technical trend filter (monthly version of the 200-DMA).
A16: 12 | B16: 6M Momentum | C16: Higher | D16: 0.05 | E16: 0.1 | F16: 0.06 | G16: 0.04 | H16: 0.01 | I16: Momentum anomaly (Jegadeesh & Titman); most weight for the momentum investor.
A17: 13 | B17: Debt / Equity | C17: Lower | D17: 0.08 | E17: 0.06 | F17: 0.06 | G17: 0.08 | H17: 0.08 | I17: RBI hiked repo to 5.50% in Oct-2026; leverage gets costlier.
B18: Total (must be 100%) | D18: =SUM(D5:D17) -> 1 | E18: =SUM(E5:E17) -> 1 | F18: =SUM(F5:F17) -> 1 | G18: =SUM(G5:G17) -> 1 | H18: =SUM(H5:H17) -> 1
B19: Mkt Cap + Sales YoY + EPS share | D19: =D5+D6+D7 -> 0.35 | E19: =E5+E6+E7 -> 0.38 | F19: =F5+F6+F7 -> 0.37 | G19: =G5+G6+G7 -> 0.36 | H19: =H5+H6+H7 -> 0.31 | I19: The brief flags these three as 'very important' - they carry the largest combined share (31-38%) in every set.
A22: Ticker | B22: Cap | C22: Market Cap | D22: Sales Growth YoY | E22: EPS Growth YoY | F22: ROE | G22: ROCE | H22: Trailing P/E | I22: PEG | J22: P/BV | K22: Beta | L22: Annualised SD | M22: Price vs 10M SMA | N22: 6M Momentum | O22: Debt / Equity | P22: Market Cap score | Q22: Sales Growth YoY score | R22: EPS Growth YoY score | S22: ROE score | T22: ROCE score | U22: Trailing P/E score | V22: PEG score | W22: P/BV score | X22: Beta score | Y22: Annualised SD score | Z22: Price vs 10M SMA score | AA22: 6M Momentum score | AB22: Debt / Equity score | AC22: House Score | AD22: Vikram Score | AE22: Ananya Score | AF22: Rohan Score | AG22: Meera Score | AH22: House Rank | AI22: Beta | AJ22: CAPM Return | AK22: Dividend Yield | AL22: Payout | AM22: Sustainable g | AN22: Fundamental Return | AO22: Blended | AP22: Score Tilt | AQ22: Expected Annual Return | AR22: Target Price Oct-2029
A23: ='Master Fund Sheet'!C2 -> RELIANCE | B23: ='Master Fund Sheet'!B2 -> Large Cap | C23: ='Master Fund Sheet'!P2 -> 1591358 | D23: ='Master Fund Sheet'!W2 -> 0.15 | E23: ='Master Fund Sheet'!X2 -> 0.15970468 | F23: ='Master Fund Sheet'!T2 -> 0.0891 | G23: ='Master Fund Sheet'!S2 -> 0.103 | H23: ='Master Fund Sheet'!R2 -> 21.271279 | I23: ='Master Fund Sheet'!Z2 -> 4.2542557 | J23: ='Master Fund Sheet'!V2 -> 1.7583832 | K23: ='Risk Metrics'!G2 -> 0.99084157 | L23: ='Risk Metrics'!F2 -> 0.19483376 | M23: ='Master Fund Sheet'!AD2 -> -0.12878883 | N23: ='Master Fund Sheet'!AE2 -> -0.11266268 | O23: ='Master Fund Sheet'!AA2 -> 0.446 | P23: =IF(ISNUMBER(C23),(RANK(C23,C$23:C$36,1)-1)/(COUNT(C$23:C$36)-1)*100,0) -> 100 | Q23: =IF(ISNUMBER(D23),(RANK(D23,D$23:D$36,1)-1)/(COUNT(D$23:D$36)-1)*100,0) -> 76.923077 | R23: =IF(ISNUMBER(E23),(RANK(E23,E$23:E$36,1)-1)/(COUNT(E$23:E$36)-1)*100,0) -> 84.615385 | S23: =IF(ISNUMBER(F23),(RANK(F23,F$23:F$36,1)-1)/(COUNT(F$23:F$36)-1)*100,0) -> 15.384615 | T23: =IF(ISNUMBER(G23),(RANK(G23,G$23:G$36,1)-1)/(COUNT(G$23:G$36)-1)*100,0) -> 23.076923 | U23: =IF(ISNUMBER(H23),(RANK(H23,H$23:H$36,0)-1)/(COUNT(H$23:H$36)-1)*100,0) -> 61.538462 | V23: =IF(ISNUMBER(I23),(RANK(I23,I$23:I$36,0)-1)/(COUNT(I$23:I$36)-1)*100,0) -> 33.333333 | W23: =IF(ISNUMBER(J23),(RANK(J23,J$23:J$36,0)-1)/(COUNT(J$23:J$36)-1)*100,0) -> 84.615385 | X23: =IF(ISNUMBER(K23),(RANK(K23,K$23:K$36,0)-1)/(COUNT(K$23:K$36)-1)*100,0) -> 46.153846 | Y23: =IF(ISNUMBER(L23),(RANK(L23,L$23:L$36,0)-1)/(COUNT(L$23:L$36)-1)*100,0) -> 92.307692 | Z23: =IF(ISNUMBER(M23),(RANK(M23,M$23:M$36,1)-1)/(COUNT(M$23:M$36)-1)*100,0) -> 15.384615 | AA23: =IF(ISNUMBER(N23),(RANK(N23,N$23:N$36,1)-1)/(COUNT(N$23:N$36)-1)*100,0) -> 15.384615 | AB23: =IF(ISNUMBER(O23),(RANK(O23,O$23:O$36,0)-1)/(COUNT(O$23:O$36)-1)*100,50) -> 16.666667 | AC23: =P23*$D$5+Q23*$D$6+R23*$D$7+S23*$D$8+T23*$D$9+U23*$D$10+V23*$D$11+W23*$D$12+X23*$D$13+Y23*$D$14+Z23*$D$15+AA23*$D$16+AB23*$D$17 -> 54.461538 | AD23: =P23*$E$5+Q23*$E$6+R23*$E$7+S23*$E$8+T23*$E$9+U23*$E$10+V23*$E$11+W23*$E$12+X23*$E$13+Y23*$E$14+Z23*$E$15+AA23*$E$16+AB23*$E$17 -> 50.384615 | AE23: =P23*$F$5+Q23*$F$6+R23*$F$7+S23*$F$8+T23*$F$9+U23*$F$10+V23*$F$11+W23*$F$12+X23*$F$13+Y23*$F$14+Z23*$F$15+AA23*$F$16+AB23*$F$17 -> 53.307692 | AF23: =P23*$G$5+Q23*$G$6+R23*$G$7+S23*$G$8+T23*$G$9+U23*$G$10+V23*$G$11+W23*$G$12+X23*$G$13+Y23*$G$14+Z23*$G$15+AA23*$G$16+AB23*$G$17 -> 56.205128 | AG23: =P23*$H$5+Q23*$H$6+R23*$H$7+S23*$H$8+T23*$H$9+U23*$H$10+V23*$H$11+W23*$H$12+X23*$H$13+Y23*$H$14+Z23*$H$15+AA23*$H$16+AB23*$H$17 -> 58.102564 | AH23: =RANK(AC23,$AC$23:$AC$36,0) -> 6 | AI23: ='Risk Metrics'!G2 -> 0.99084157 | AJ23: ='Investor Personas'!$C$13+AI23*'Investor Personas'!$C$10 -> 0.14285891 | AK23: ='Master Fund Sheet'!AB2 -> 0.0051 | AL23: =IF(ISNUMBER('Master Fund Sheet'!R2),MIN(AK23*'Master Fund Sheet'!R2,1),1) -> 0.10848352 | AM23: =MIN(MAX('Master Fund Sheet'!T2*(1-AL23),0),'Investor Personas'!$C$14) -> 0.079434118 | AN23: =AK23+AM23 -> 0.084534118 | AO23: ='Investor Personas'!$C$11*AJ23+(1-'Investor Personas'!$C$11)*AN23 -> 0.11369651 | AP23: =(AC23-50)/50*'Investor Personas'!$C$12 -> 0.0026769231 | AQ23: =AO23+AP23 -> 0.11637344 | AR23: ='Master Fund Sheet'!I2*(1+AQ23)^'Investor Personas'!$F$1 -> 1634.2499
A24: ='Master Fund Sheet'!C3 -> HDFCBANK | B24: ='Master Fund Sheet'!B3 -> Large Cap | C24: ='Master Fund Sheet'!P3 -> 1095493 | D24: ='Master Fund Sheet'!W3 -> 0.03 | E24: ='Master Fund Sheet'!X3 -> 0.067661046 | F24: ='Master Fund Sheet'!T3 -> 0.136 | G24: ='Master Fund Sheet'!S3 -> 0.0702 | H24: ='Master Fund Sheet'!R3 -> 13.840312 | I24: ='Master Fund Sheet'!Z3 -> 0.7689062 | J24: ='Master Fund Sheet'!V3 -> 1.8223077 | K24: ='Risk Metrics'!G3 -> 0.884506 | L24: ='Risk Metrics'!F3 -> 0.18294268 | M24: ='Master Fund Sheet'!AD3 -> -0.10463443 | N24: ='Master Fund Sheet'!AE3 -> -0.01521573 | O24: ='Master Fund Sheet'!AA3 -> Bank | P24: =IF(ISNUMBER(C24),(RANK(C24,C$23:C$36,1)-1)/(COUNT(C$23:C$36)-1)*100,0) -> 92.307692 | Q24: =IF(ISNUMBER(D24),(RANK(D24,D$23:D$36,1)-1)/(COUNT(D$23:D$36)-1)*100,0) -> 23.076923 | R24: =IF(ISNUMBER(E24),(RANK(E24,E$23:E$36,1)-1)/(COUNT(E$23:E$36)-1)*100,0) -> 61.538462 | S24: =IF(ISNUMBER(F24),(RANK(F24,F$23:F$36,1)-1)/(COUNT(F$23:F$36)-1)*100,0) -> 38.461538 | T24: =IF(ISNUMBER(G24),(RANK(G24,G$23:G$36,1)-1)/(COUNT(G$23:G$36)-1)*100,0) -> 15.384615 | U24: =IF(ISNUMBER(H24),(RANK(H24,H$23:H$36,0)-1)/(COUNT(H$23:H$36)-1)*100,0) -> 92.307692 | V24: =IF(ISNUMBER(I24),(RANK(I24,I$23:I$36,0)-1)/(COUNT(I$23:I$36)-1)*100,0) -> 91.666667 | W24: =IF(ISNUMBER(J24),(RANK(J24,J$23:J$36,0)-1)/(COUNT(J$23:J$36)-1)*100,0) -> 76.923077 | X24: =IF(ISNUMBER(K24),(RANK(K24,K$23:K$36,0)-1)/(COUNT(K$23:K$36)-1)*100,0) -> 53.846154 | Y24: =IF(ISNUMBER(L24),(RANK(L24,L$23:L$36,0)-1)/(COUNT(L$23:L$36)-1)*100,0) -> 100 | Z24: =IF(ISNUMBER(M24),(RANK(M24,M$23:M$36,1)-1)/(COUNT(M$23:M$36)-1)*100,0) -> 53.846154 | AA24: =IF(ISNUMBER(N24),(RANK(N24,N$23:N$36,1)-1)/(COUNT(N$23:N$36)-1)*100,0) -> 53.846154 | AB24: =IF(ISNUMBER(O24),(RANK(O24,O$23:O$36,0)-1)/(COUNT(O$23:O$36)-1)*100,50) -> 50 | AC24: =P24*$D$5+Q24*$D$6+R24*$D$7+S24*$D$8+T24*$D$9+U24*$D$10+V24*$D$11+W24*$D$12+X24*$D$13+Y24*$D$14+Z24*$D$15+AA24*$D$16+AB24*$D$17 -> 59.025641 | AD24: =P24*$E$5+Q24*$E$6+R24*$E$7+S24*$E$8+T24*$E$9+U24*$E$10+V24*$E$11+W24*$E$12+X24*$E$13+Y24*$E$14+Z24*$E$15+AA24*$E$16+AB24*$E$17 -> 55.403846 | AE24: =P24*$F$5+Q24*$F$6+R24*$F$7+S24*$F$8+T24*$F$9+U24*$F$10+V24*$F$11+W24*$F$12+X24*$F$13+Y24*$F$14+Z24*$F$15+AA24*$F$16+AB24*$F$17 -> 57.019231 | AF24: =P24*$G$5+Q24*$G$6+R24*$G$7+S24*$G$8+T24*$G$9+U24*$G$10+V24*$G$11+W24*$G$12+X24*$G$13+Y24*$G$14+Z24*$G$15+AA24*$G$16+AB24*$G$17 -> 59.49359 | AG24: =P24*$H$5+Q24*$H$6+R24*$H$7+S24*$H$8+T24*$H$9+U24*$H$10+V24*$H$11+W24*$H$12+X24*$H$13+Y24*$H$14+Z24*$H$15+AA24*$H$16+AB24*$H$17 -> 62.730769 | AH24: =RANK(AC24,$AC$23:$AC$36,0) -> 5 | AI24: ='Risk Metrics'!G3 -> 0.884506 | AJ24: ='Investor Personas'!$C$13+AI24*'Investor Personas'!$C$10 -> 0.13541542 | AK24: ='Master Fund Sheet'!AB3 -> 0.0183 | AL24: =IF(ISNUMBER('Master Fund Sheet'!R3),MIN(AK24*'Master Fund Sheet'!R3,1),1) -> 0.2532777 | AM24: =MIN(MAX('Master Fund Sheet'!T3*(1-AL24),0),'Investor Personas'!$C$14) -> 0.10155423 | AN24: =AK24+AM24 -> 0.11985423 | AO24: ='Investor Personas'!$C$11*AJ24+(1-'Investor Personas'!$C$11)*AN24 -> 0.12763483 | AP24: =(AC24-50)/50*'Investor Personas'!$C$12 -> 0.0054153846 | AQ24: =AO24+AP24 -> 0.13305021 | AR24: ='Master Fund Sheet'!I3*(1+AQ24)^'Investor Personas'!$F$1 -> 1033.7935
A25: ='Master Fund Sheet'!C4 -> INFY | B25: ='Master Fund Sheet'!B4 -> Large Cap | C25: ='Master Fund Sheet'!P4 -> 441499 | D25: ='Master Fund Sheet'!W4 -> 0.11 | E25: ='Master Fund Sheet'!X4 -> 0.12857587 | F25: ='Master Fund Sheet'!T4 -> 0.319 | G25: ='Master Fund Sheet'!S4 -> 0.4 | H25: ='Master Fund Sheet'!R4 -> 14.653199 | I25: ='Master Fund Sheet'!Z4 -> 1.8316498 | J25: ='Master Fund Sheet'!V4 -> 4.8355556 | K25: ='Risk Metrics'!G4 -> 0.75751049 | L25: ='Risk Metrics'!F4 -> 0.25867734 | M25: ='Master Fund Sheet'!AD4 -> -0.11078928 | N25: ='Master Fund Sheet'!AE4 -> -0.18789978 | O25: ='Master Fund Sheet'!AA4 -> 0.099 | P25: =IF(ISNUMBER(C25),(RANK(C25,C$23:C$36,1)-1)/(COUNT(C$23:C$36)-1)*100,0) -> 84.615385 | Q25: =IF(ISNUMBER(D25),(RANK(D25,D$23:D$36,1)-1)/(COUNT(D$23:D$36)-1)*100,0) -> 53.846154 | R25: =IF(ISNUMBER(E25),(RANK(E25,E$23:E$36,1)-1)/(COUNT(E$23:E$36)-1)*100,0) -> 76.923077 | S25: =IF(ISNUMBER(F25),(RANK(F25,F$23:F$36,1)-1)/(COUNT(F$23:F$36)-1)*100,0) -> 100 | T25: =IF(ISNUMBER(G25),(RANK(G25,G$23:G$36,1)-1)/(COUNT(G$23:G$36)-1)*100,0) -> 100 | U25: =IF(ISNUMBER(H25),(RANK(H25,H$23:H$36,0)-1)/(COUNT(H$23:H$36)-1)*100,0) -> 84.615385 | V25: =IF(ISNUMBER(I25),(RANK(I25,I$23:I$36,0)-1)/(COUNT(I$23:I$36)-1)*100,0) -> 66.666667 | W25: =IF(ISNUMBER(J25),(RANK(J25,J$23:J$36,0)-1)/(COUNT(J$23:J$36)-1)*100,0) -> 38.461538 | X25: =IF(ISNUMBER(K25),(RANK(K25,K$23:K$36,0)-1)/(COUNT(K$23:K$36)-1)*100,0) -> 84.615385 | Y25: =IF(ISNUMBER(L25),(RANK(L25,L$23:L$36,0)-1)/(COUNT(L$23:L$36)-1)*100,0) -> 46.153846 | Z25: =IF(ISNUMBER(M25),(RANK(M25,M$23:M$36,1)-1)/(COUNT(M$23:M$36)-1)*100,0) -> 46.153846 | AA25: =IF(ISNUMBER(N25),(RANK(N25,N$23:N$36,1)-1)/(COUNT(N$23:N$36)-1)*100,0) -> 0 | AB25: =IF(ISNUMBER(O25),(RANK(O25,O$23:O$36,0)-1)/(COUNT(O$23:O$36)-1)*100,50) -> 33.333333 | AC25: =P25*$D$5+Q25*$D$6+R25*$D$7+S25*$D$8+T25*$D$9+U25*$D$10+V25*$D$11+W25*$D$12+X25*$D$13+Y25*$D$14+Z25*$D$15+AA25*$D$16+AB25*$D$17 -> 66.692308 | AD25: =P25*$E$5+Q25*$E$6+R25*$E$7+S25*$E$8+T25*$E$9+U25*$E$10+V25*$E$11+W25*$E$12+X25*$E$13+Y25*$E$14+Z25*$E$15+AA25*$E$16+AB25*$E$17 -> 62.538462 | AE25: =P25*$F$5+Q25*$F$6+R25*$F$7+S25*$F$8+T25*$F$9+U25*$F$10+V25*$F$11+W25*$F$12+X25*$F$13+Y25*$F$14+Z25*$F$15+AA25*$F$16+AB25*$F$17 -> 66.538462 | AF25: =P25*$G$5+Q25*$G$6+R25*$G$7+S25*$G$8+T25*$G$9+U25*$G$10+V25*$G$11+W25*$G$12+X25*$G$13+Y25*$G$14+Z25*$G$15+AA25*$G$16+AB25*$G$17 -> 67.717949 | AG25: =P25*$H$5+Q25*$H$6+R25*$H$7+S25*$H$8+T25*$H$9+U25*$H$10+V25*$H$11+W25*$H$12+X25*$H$13+Y25*$H$14+Z25*$H$15+AA25*$H$16+AB25*$H$17 -> 71.358974 | AH25: =RANK(AC25,$AC$23:$AC$36,0) -> 1 | AI25: ='Risk Metrics'!G4 -> 0.75751049 | AJ25: ='Investor Personas'!$C$13+AI25*'Investor Personas'!$C$10 -> 0.12652573 | AK25: ='Master Fund Sheet'!AB4 -> 0.0441 | AL25: =IF(ISNUMBER('Master Fund Sheet'!R4),MIN(AK25*'Master Fund Sheet'!R4,1),1) -> 0.64620606 | AM25: =MIN(MAX('Master Fund Sheet'!T4*(1-AL25),0),'Investor Personas'!$C$14) -> 0.11286027 | AN25: =AK25+AM25 -> 0.15696027 | AO25: ='Investor Personas'!$C$11*AJ25+(1-'Investor Personas'!$C$11)*AN25 -> 0.141743 | AP25: =(AC25-50)/50*'Investor Personas'!$C$12 -> 0.010015385 | AQ25: =AO25+AP25 -> 0.15175839 | AR25: ='Master Fund Sheet'!I4*(1+AQ25)^'Investor Personas'!$F$1 -> 1662.3139
A26: ='Master Fund Sheet'!C5 -> ITC | B26: ='Master Fund Sheet'!B5 -> Large Cap | C26: ='Master Fund Sheet'!P5 -> 327297 | D26: ='Master Fund Sheet'!W5 -> -0.03 | E26: ='Master Fund Sheet'!X5 -> -0.40547353 | F26: ='Master Fund Sheet'!T5 -> 0.293 | G26: ='Master Fund Sheet'!S5 -> 0.389 | H26: ='Master Fund Sheet'!R5 -> 16.508838 | I26: ='Master Fund Sheet'!Z5 -> 5.5029461 | J26: ='Master Fund Sheet'!V5 -> 4.5164076 | K26: ='Risk Metrics'!G5 -> 0.81842432 | L26: ='Risk Metrics'!F5 -> 0.2126114 | M26: ='Master Fund Sheet'!AD5 -> -0.11548726 | N26: ='Master Fund Sheet'!AE5 -> -0.061841682 | O26: ='Master Fund Sheet'!AA5 -> 0.033 | P26: =IF(ISNUMBER(C26),(RANK(C26,C$23:C$36,1)-1)/(COUNT(C$23:C$36)-1)*100,0) -> 61.538462 | Q26: =IF(ISNUMBER(D26),(RANK(D26,D$23:D$36,1)-1)/(COUNT(D$23:D$36)-1)*100,0) -> 0 | R26: =IF(ISNUMBER(E26),(RANK(E26,E$23:E$36,1)-1)/(COUNT(E$23:E$36)-1)*100,0) -> 15.384615 | S26: =IF(ISNUMBER(F26),(RANK(F26,F$23:F$36,1)-1)/(COUNT(F$23:F$36)-1)*100,0) -> 92.307692 | T26: =IF(ISNUMBER(G26),(RANK(G26,G$23:G$36,1)-1)/(COUNT(G$23:G$36)-1)*100,0) -> 92.307692 | U26: =IF(ISNUMBER(H26),(RANK(H26,H$23:H$36,0)-1)/(COUNT(H$23:H$36)-1)*100,0) -> 76.923077 | V26: =IF(ISNUMBER(I26),(RANK(I26,I$23:I$36,0)-1)/(COUNT(I$23:I$36)-1)*100,0) -> 25 | W26: =IF(ISNUMBER(J26),(RANK(J26,J$23:J$36,0)-1)/(COUNT(J$23:J$36)-1)*100,0) -> 46.153846 | X26: =IF(ISNUMBER(K26),(RANK(K26,K$23:K$36,0)-1)/(COUNT(K$23:K$36)-1)*100,0) -> 76.923077 | Y26: =IF(ISNUMBER(L26),(RANK(L26,L$23:L$36,0)-1)/(COUNT(L$23:L$36)-1)*100,0) -> 76.923077 | Z26: =IF(ISNUMBER(M26),(RANK(M26,M$23:M$36,1)-1)/(COUNT(M$23:M$36)-1)*100,0) -> 30.769231 | AA26: =IF(ISNUMBER(N26),(RANK(N26,N$23:N$36,1)-1)/(COUNT(N$23:N$36)-1)*100,0) -> 30.769231 | AB26: =IF(ISNUMBER(O26),(RANK(O26,O$23:O$36,0)-1)/(COUNT(O$23:O$36)-1)*100,50) -> 75 | AC26: =P26*$D$5+Q26*$D$6+R26*$D$7+S26*$D$8+T26*$D$9+U26*$D$10+V26*$D$11+W26*$D$12+X26*$D$13+Y26*$D$14+Z26*$D$15+AA26*$D$16+AB26*$D$17 -> 50.615385 | AD26: =P26*$E$5+Q26*$E$6+R26*$E$7+S26*$E$8+T26*$E$9+U26*$E$10+V26*$E$11+W26*$E$12+X26*$E$13+Y26*$E$14+Z26*$E$15+AA26*$E$16+AB26*$E$17 -> 42.75 | AE26: =P26*$F$5+Q26*$F$6+R26*$F$7+S26*$F$8+T26*$F$9+U26*$F$10+V26*$F$11+W26*$F$12+X26*$F$13+Y26*$F$14+Z26*$F$15+AA26*$F$16+AB26*$F$17 -> 47.211538 | AF26: =P26*$G$5+Q26*$G$6+R26*$G$7+S26*$G$8+T26*$G$9+U26*$G$10+V26*$G$11+W26*$G$12+X26*$G$13+Y26*$G$14+Z26*$G$15+AA26*$G$16+AB26*$G$17 -> 51.903846 | AG26: =P26*$H$5+Q26*$H$6+R26*$H$7+S26*$H$8+T26*$H$9+U26*$H$10+V26*$H$11+W26*$H$12+X26*$H$13+Y26*$H$14+Z26*$H$15+AA26*$H$16+AB26*$H$17 -> 59.346154 | AH26: =RANK(AC26,$AC$23:$AC$36,0) -> 9 | AI26: ='Risk Metrics'!G5 -> 0.81842432 | AJ26: ='Investor Personas'!$C$13+AI26*'Investor Personas'!$C$10 -> 0.1307897 | AK26: ='Master Fund Sheet'!AB5 -> 0.0555 | AL26: =IF(ISNUMBER('Master Fund Sheet'!R5),MIN(AK26*'Master Fund Sheet'!R5,1),1) -> 0.91624053 | AM26: =MIN(MAX('Master Fund Sheet'!T5*(1-AL26),0),'Investor Personas'!$C$14) -> 0.024541525 | AN26: =AK26+AM26 -> 0.080041525 | AO26: ='Investor Personas'!$C$11*AJ26+(1-'Investor Personas'!$C$11)*AN26 -> 0.10541561 | AP26: =(AC26-50)/50*'Investor Personas'!$C$12 -> 0.00036923077 | AQ26: =AO26+AP26 -> 0.10578484 | AR26: ='Master Fund Sheet'!I5*(1+AQ26)^'Investor Personas'!$F$1 -> 353.57666
A27: ='Master Fund Sheet'!C6 -> SUNPHARMA | B27: ='Master Fund Sheet'!B6 -> Large Cap | C27: ='Master Fund Sheet'!P6 -> 419399 | D27: ='Master Fund Sheet'!W6 -> 0.11 | E27: ='Master Fund Sheet'!X6 -> 0.050274424 | F27: ='Master Fund Sheet'!T6 -> 0.16 | G27: ='Master Fund Sheet'!S6 -> 0.205 | H27: ='Master Fund Sheet'!R6 -> 34.64392 | I27: ='Master Fund Sheet'!Z6 -> 2.6649169 | J27: ='Master Fund Sheet'!V6 -> 5.0183908 | K27: ='Risk Metrics'!G6 -> 0.87112781 | L27: ='Risk Metrics'!F6 -> 0.22196239 | M27: ='Master Fund Sheet'!AD6 -> -0.030729279 | N27: ='Master Fund Sheet'!AE6 -> 0.03651126 | O27: ='Master Fund Sheet'!AA6 -> 0.055 | P27: =IF(ISNUMBER(C27),(RANK(C27,C$23:C$36,1)-1)/(COUNT(C$23:C$36)-1)*100,0) -> 76.923077 | Q27: =IF(ISNUMBER(D27),(RANK(D27,D$23:D$36,1)-1)/(COUNT(D$23:D$36)-1)*100,0) -> 53.846154 | R27: =IF(ISNUMBER(E27),(RANK(E27,E$23:E$36,1)-1)/(COUNT(E$23:E$36)-1)*100,0) -> 53.846154 | S27: =IF(ISNUMBER(F27),(RANK(F27,F$23:F$36,1)-1)/(COUNT(F$23:F$36)-1)*100,0) -> 76.923077 | T27: =IF(ISNUMBER(G27),(RANK(G27,G$23:G$36,1)-1)/(COUNT(G$23:G$36)-1)*100,0) -> 76.923077 | U27: =IF(ISNUMBER(H27),(RANK(H27,H$23:H$36,0)-1)/(COUNT(H$23:H$36)-1)*100,0) -> 38.461538 | V27: =IF(ISNUMBER(I27),(RANK(I27,I$23:I$36,0)-1)/(COUNT(I$23:I$36)-1)*100,0) -> 41.666667 | W27: =IF(ISNUMBER(J27),(RANK(J27,J$23:J$36,0)-1)/(COUNT(J$23:J$36)-1)*100,0) -> 23.076923 | X27: =IF(ISNUMBER(K27),(RANK(K27,K$23:K$36,0)-1)/(COUNT(K$23:K$36)-1)*100,0) -> 61.538462 | Y27: =IF(ISNUMBER(L27),(RANK(L27,L$23:L$36,0)-1)/(COUNT(L$23:L$36)-1)*100,0) -> 69.230769 | Z27: =IF(ISNUMBER(M27),(RANK(M27,M$23:M$36,1)-1)/(COUNT(M$23:M$36)-1)*100,0) -> 92.307692 | AA27: =IF(ISNUMBER(N27),(RANK(N27,N$23:N$36,1)-1)/(COUNT(N$23:N$36)-1)*100,0) -> 61.538462 | AB27: =IF(ISNUMBER(O27),(RANK(O27,O$23:O$36,0)-1)/(COUNT(O$23:O$36)-1)*100,50) -> 50 | AC27: =P27*$D$5+Q27*$D$6+R27*$D$7+S27*$D$8+T27*$D$9+U27*$D$10+V27*$D$11+W27*$D$12+X27*$D$13+Y27*$D$14+Z27*$D$15+AA27*$D$16+AB27*$D$17 -> 60.333333 | AD27: =P27*$E$5+Q27*$E$6+R27*$E$7+S27*$E$8+T27*$E$9+U27*$E$10+V27*$E$11+W27*$E$12+X27*$E$13+Y27*$E$14+Z27*$E$15+AA27*$E$16+AB27*$E$17 -> 61.519231 | AE27: =P27*$F$5+Q27*$F$6+R27*$F$7+S27*$F$8+T27*$F$9+U27*$F$10+V27*$F$11+W27*$F$12+X27*$F$13+Y27*$F$14+Z27*$F$15+AA27*$F$16+AB27*$F$17 -> 60.75 | AF27: =P27*$G$5+Q27*$G$6+R27*$G$7+S27*$G$8+T27*$G$9+U27*$G$10+V27*$G$11+W27*$G$12+X27*$G$13+Y27*$G$14+Z27*$G$15+AA27*$G$16+AB27*$G$17 -> 60.455128 | AG27: =P27*$H$5+Q27*$H$6+R27*$H$7+S27*$H$8+T27*$H$9+U27*$H$10+V27*$H$11+W27*$H$12+X27*$H$13+Y27*$H$14+Z27*$H$15+AA27*$H$16+AB27*$H$17 -> 60.576923 | AH27: =RANK(AC27,$AC$23:$AC$36,0) -> 3 | AI27: ='Risk Metrics'!G6 -> 0.87112781 | AJ27: ='Investor Personas'!$C$13+AI27*'Investor Personas'!$C$10 -> 0.13447895 | AK27: ='Master Fund Sheet'!AB6 -> 0.0092 | AL27: =IF(ISNUMBER('Master Fund Sheet'!R6),MIN(AK27*'Master Fund Sheet'!R6,1),1) -> 0.31872406 | AM27: =MIN(MAX('Master Fund Sheet'!T6*(1-AL27),0),'Investor Personas'!$C$14) -> 0.10900415 | AN27: =AK27+AM27 -> 0.11820415 | AO27: ='Investor Personas'!$C$11*AJ27+(1-'Investor Personas'!$C$11)*AN27 -> 0.12634155 | AP27: =(AC27-50)/50*'Investor Personas'!$C$12 -> 0.0062 | AQ27: =AO27+AP27 -> 0.13254155 | AR27: ='Master Fund Sheet'!I6*(1+AQ27)^'Investor Personas'!$F$1 -> 2536.9164
A28: ='Master Fund Sheet'!C7 -> MARUTI | B28: ='Master Fund Sheet'!B7 -> Large Cap | C28: ='Master Fund Sheet'!P7 -> 351130 | D28: ='Master Fund Sheet'!W7 -> 0.27 | E28: ='Master Fund Sheet'!X7 -> 0.012359063 | F28: ='Master Fund Sheet'!T7 -> 0.143 | G28: ='Master Fund Sheet'!S7 -> 0.189 | H28: ='Master Fund Sheet'!R7 -> 24.517997 | I28: ='Master Fund Sheet'!Z7 -> 1.1675237 | J28: ='Master Fund Sheet'!V7 -> 3.2799296 | K28: ='Risk Metrics'!G7 -> 0.68561437 | L28: ='Risk Metrics'!F7 -> 0.24314654 | M28: ='Master Fund Sheet'!AD7 -> -0.18786343 | N28: ='Master Fund Sheet'!AE7 -> -0.017781221 | O28: ='Master Fund Sheet'!AA7 -> 0.001 | P28: =IF(ISNUMBER(C28),(RANK(C28,C$23:C$36,1)-1)/(COUNT(C$23:C$36)-1)*100,0) -> 69.230769 | Q28: =IF(ISNUMBER(D28),(RANK(D28,D$23:D$36,1)-1)/(COUNT(D$23:D$36)-1)*100,0) -> 100 | R28: =IF(ISNUMBER(E28),(RANK(E28,E$23:E$36,1)-1)/(COUNT(E$23:E$36)-1)*100,0) -> 38.461538 | S28: =IF(ISNUMBER(F28),(RANK(F28,F$23:F$36,1)-1)/(COUNT(F$23:F$36)-1)*100,0) -> 53.846154 | T28: =IF(ISNUMBER(G28),(RANK(G28,G$23:G$36,1)-1)/(COUNT(G$23:G$36)-1)*100,0) -> 53.846154 | U28: =IF(ISNUMBER(H28),(RANK(H28,H$23:H$36,0)-1)/(COUNT(H$23:H$36)-1)*100,0) -> 53.846154 | V28: =IF(ISNUMBER(I28),(RANK(I28,I$23:I$36,0)-1)/(COUNT(I$23:I$36)-1)*100,0) -> 75 | W28: =IF(ISNUMBER(J28),(RANK(J28,J$23:J$36,0)-1)/(COUNT(J$23:J$36)-1)*100,0) -> 61.538462 | X28: =IF(ISNUMBER(K28),(RANK(K28,K$23:K$36,0)-1)/(COUNT(K$23:K$36)-1)*100,0) -> 100 | Y28: =IF(ISNUMBER(L28),(RANK(L28,L$23:L$36,0)-1)/(COUNT(L$23:L$36)-1)*100,0) -> 61.538462 | Z28: =IF(ISNUMBER(M28),(RANK(M28,M$23:M$36,1)-1)/(COUNT(M$23:M$36)-1)*100,0) -> 0 | AA28: =IF(ISNUMBER(N28),(RANK(N28,N$23:N$36,1)-1)/(COUNT(N$23:N$36)-1)*100,0) -> 46.153846 | AB28: =IF(ISNUMBER(O28),(RANK(O28,O$23:O$36,0)-1)/(COUNT(O$23:O$36)-1)*100,50) -> 100 | AC28: =P28*$D$5+Q28*$D$6+R28*$D$7+S28*$D$8+T28*$D$9+U28*$D$10+V28*$D$11+W28*$D$12+X28*$D$13+Y28*$D$14+Z28*$D$15+AA28*$D$16+AB28*$D$17 -> 64.769231 | AD28: =P28*$E$5+Q28*$E$6+R28*$E$7+S28*$E$8+T28*$E$9+U28*$E$10+V28*$E$11+W28*$E$12+X28*$E$13+Y28*$E$14+Z28*$E$15+AA28*$E$16+AB28*$E$17 -> 60.211538 | AE28: =P28*$F$5+Q28*$F$6+R28*$F$7+S28*$F$8+T28*$F$9+U28*$F$10+V28*$F$11+W28*$F$12+X28*$F$13+Y28*$F$14+Z28*$F$15+AA28*$F$16+AB28*$F$17 -> 63.134615 | AF28: =P28*$G$5+Q28*$G$6+R28*$G$7+S28*$G$8+T28*$G$9+U28*$G$10+V28*$G$11+W28*$G$12+X28*$G$13+Y28*$G$14+Z28*$G$15+AA28*$G$16+AB28*$G$17 -> 65.865385 | AG28: =P28*$H$5+Q28*$H$6+R28*$H$7+S28*$H$8+T28*$H$9+U28*$H$10+V28*$H$11+W28*$H$12+X28*$H$13+Y28*$H$14+Z28*$H$15+AA28*$H$16+AB28*$H$17 -> 67.576923 | AH28: =RANK(AC28,$AC$23:$AC$36,0) -> 2 | AI28: ='Risk Metrics'!G7 -> 0.68561437 | AJ28: ='Investor Personas'!$C$13+AI28*'Investor Personas'!$C$10 -> 0.12149301 | AK28: ='Master Fund Sheet'!AB7 -> 0.0125 | AL28: =IF(ISNUMBER('Master Fund Sheet'!R7),MIN(AK28*'Master Fund Sheet'!R7,1),1) -> 0.30647496 | AM28: =MIN(MAX('Master Fund Sheet'!T7*(1-AL28),0),'Investor Personas'!$C$14) -> 0.09917408 | AN28: =AK28+AM28 -> 0.11167408 | AO28: ='Investor Personas'!$C$11*AJ28+(1-'Investor Personas'!$C$11)*AN28 -> 0.11658354 | AP28: =(AC28-50)/50*'Investor Personas'!$C$12 -> 0.0088615385 | AQ28: =AO28+AP28 -> 0.12544508 | AR28: ='Master Fund Sheet'!I7*(1+AQ28)^'Investor Personas'!$F$1 -> 15934.448
A29: ='Master Fund Sheet'!C8 -> TATASTEEL | B29: ='Master Fund Sheet'!B8 -> Large Cap | C29: ='Master Fund Sheet'!P8 -> 217962 | D29: ='Master Fund Sheet'!W8 -> 0.11 | E29: ='Master Fund Sheet'!X8 -> 2.1569343 | F29: ='Master Fund Sheet'!T8 -> 0.117 | G29: ='Master Fund Sheet'!S8 -> 0.125 | H29: ='Master Fund Sheet'!R8 -> 19.761042 | I29: ='Master Fund Sheet'!Z8 -> 1.9761042 | J29: ='Master Fund Sheet'!V8 -> 2.1331296 | K29: ='Risk Metrics'!G8 -> 1.1923044 | L29: ='Risk Metrics'!F8 -> 0.28730275 | M29: ='Master Fund Sheet'!AD8 -> -0.090724336 | N29: ='Master Fund Sheet'!AE8 -> -0.019576551 | O29: ='Master Fund Sheet'!AA8 -> 0.904 | P29: =IF(ISNUMBER(C29),(RANK(C29,C$23:C$36,1)-1)/(COUNT(C$23:C$36)-1)*100,0) -> 53.846154 | Q29: =IF(ISNUMBER(D29),(RANK(D29,D$23:D$36,1)-1)/(COUNT(D$23:D$36)-1)*100,0) -> 53.846154 | R29: =IF(ISNUMBER(E29),(RANK(E29,E$23:E$36,1)-1)/(COUNT(E$23:E$36)-1)*100,0) -> 100 | S29: =IF(ISNUMBER(F29),(RANK(F29,F$23:F$36,1)-1)/(COUNT(F$23:F$36)-1)*100,0) -> 30.769231 | T29: =IF(ISNUMBER(G29),(RANK(G29,G$23:G$36,1)-1)/(COUNT(G$23:G$36)-1)*100,0) -> 38.461538 | U29: =IF(ISNUMBER(H29),(RANK(H29,H$23:H$36,0)-1)/(COUNT(H$23:H$36)-1)*100,0) -> 69.230769 | V29: =IF(ISNUMBER(I29),(RANK(I29,I$23:I$36,0)-1)/(COUNT(I$23:I$36)-1)*100,0) -> 50 | W29: =IF(ISNUMBER(J29),(RANK(J29,J$23:J$36,0)-1)/(COUNT(J$23:J$36)-1)*100,0) -> 69.230769 | X29: =IF(ISNUMBER(K29),(RANK(K29,K$23:K$36,0)-1)/(COUNT(K$23:K$36)-1)*100,0) -> 30.769231 | Y29: =IF(ISNUMBER(L29),(RANK(L29,L$23:L$36,0)-1)/(COUNT(L$23:L$36)-1)*100,0) -> 38.461538 | Z29: =IF(ISNUMBER(M29),(RANK(M29,M$23:M$36,1)-1)/(COUNT(M$23:M$36)-1)*100,0) -> 61.538462 | AA29: =IF(ISNUMBER(N29),(RANK(N29,N$23:N$36,1)-1)/(COUNT(N$23:N$36)-1)*100,0) -> 38.461538 | AB29: =IF(ISNUMBER(O29),(RANK(O29,O$23:O$36,0)-1)/(COUNT(O$23:O$36)-1)*100,50) -> 0 | AC29: =P29*$D$5+Q29*$D$6+R29*$D$7+S29*$D$8+T29*$D$9+U29*$D$10+V29*$D$11+W29*$D$12+X29*$D$13+Y29*$D$14+Z29*$D$15+AA29*$D$16+AB29*$D$17 -> 50.846154 | AD29: =P29*$E$5+Q29*$E$6+R29*$E$7+S29*$E$8+T29*$E$9+U29*$E$10+V29*$E$11+W29*$E$12+X29*$E$13+Y29*$E$14+Z29*$E$15+AA29*$E$16+AB29*$E$17 -> 53.5 | AE29: =P29*$F$5+Q29*$F$6+R29*$F$7+S29*$F$8+T29*$F$9+U29*$F$10+V29*$F$11+W29*$F$12+X29*$F$13+Y29*$F$14+Z29*$F$15+AA29*$F$16+AB29*$F$17 -> 52.576923 | AF29: =P29*$G$5+Q29*$G$6+R29*$G$7+S29*$G$8+T29*$G$9+U29*$G$10+V29*$G$11+W29*$G$12+X29*$G$13+Y29*$G$14+Z29*$G$15+AA29*$G$16+AB29*$G$17 -> 50.576923 | AG29: =P29*$H$5+Q29*$H$6+R29*$H$7+S29*$H$8+T29*$H$9+U29*$H$10+V29*$H$11+W29*$H$12+X29*$H$13+Y29*$H$14+Z29*$H$15+AA29*$H$16+AB29*$H$17 -> 48.461538 | AH29: =RANK(AC29,$AC$23:$AC$36,0) -> 8 | AI29: ='Risk Metrics'!G8 -> 1.1923044 | AJ29: ='Investor Personas'!$C$13+AI29*'Investor Personas'!$C$10 -> 0.15696131 | AK29: ='Master Fund Sheet'!AB8 -> 0.0229 | AL29: =IF(ISNUMBER('Master Fund Sheet'!R8),MIN(AK29*'Master Fund Sheet'!R8,1),1) -> 0.45252786 | AM29: =MIN(MAX('Master Fund Sheet'!T8*(1-AL29),0),'Investor Personas'!$C$14) -> 0.06405424 | AN29: =AK29+AM29 -> 0.08695424 | AO29: ='Investor Personas'!$C$11*AJ29+(1-'Investor Personas'!$C$11)*AN29 -> 0.12195777 | AP29: =(AC29-50)/50*'Investor Personas'!$C$12 -> 0.00050769231 | AQ29: =AO29+AP29 -> 0.12246547 | AR29: ='Master Fund Sheet'!I8*(1+AQ29)^'Investor Personas'!$F$1 -> 246.76838
A30: ='Master Fund Sheet'!C9 -> DABUR | B30: ='Master Fund Sheet'!B9 -> Mid Cap | C30: ='Master Fund Sheet'!P9 -> 68960 | D30: ='Master Fund Sheet'!W9 -> 0.074 | E30: ='Master Fund Sheet'!X9 -> 0.071356784 | F30: ='Master Fund Sheet'!T9 -> 0.1624 | G30: ='Master Fund Sheet'!S9 -> 0.165 | H30: ='Master Fund Sheet'!R9 -> 34.959496 | I30: ='Master Fund Sheet'!Z9 -> 9.4485124 | J30: ='Master Fund Sheet'!V9 -> 6.0329295 | K30: ='Risk Metrics'!G9 -> 0.869804 | L30: ='Risk Metrics'!F9 -> 0.20423283 | M30: ='Master Fund Sheet'!AD9 -> -0.11470134 | N30: ='Master Fund Sheet'!AE9 -> -0.061921568 | O30: ='Master Fund Sheet'!AA9 -> 0.11 | P30: =IF(ISNUMBER(C30),(RANK(C30,C$23:C$36,1)-1)/(COUNT(C$23:C$36)-1)*100,0) -> 46.153846 | Q30: =IF(ISNUMBER(D30),(RANK(D30,D$23:D$36,1)-1)/(COUNT(D$23:D$36)-1)*100,0) -> 38.461538 | R30: =IF(ISNUMBER(E30),(RANK(E30,E$23:E$36,1)-1)/(COUNT(E$23:E$36)-1)*100,0) -> 69.230769 | S30: =IF(ISNUMBER(F30),(RANK(F30,F$23:F$36,1)-1)/(COUNT(F$23:F$36)-1)*100,0) -> 84.615385 | T30: =IF(ISNUMBER(G30),(RANK(G30,G$23:G$36,1)-1)/(COUNT(G$23:G$36)-1)*100,0) -> 46.153846 | U30: =IF(ISNUMBER(H30),(RANK(H30,H$23:H$36,0)-1)/(COUNT(H$23:H$36)-1)*100,0) -> 23.076923 | V30: =IF(ISNUMBER(I30),(RANK(I30,I$23:I$36,0)-1)/(COUNT(I$23:I$36)-1)*100,0) -> 8.3333333 | W30: =IF(ISNUMBER(J30),(RANK(J30,J$23:J$36,0)-1)/(COUNT(J$23:J$36)-1)*100,0) -> 15.384615 | X30: =IF(ISNUMBER(K30),(RANK(K30,K$23:K$36,0)-1)/(COUNT(K$23:K$36)-1)*100,0) -> 69.230769 | Y30: =IF(ISNUMBER(L30),(RANK(L30,L$23:L$36,0)-1)/(COUNT(L$23:L$36)-1)*100,0) -> 84.615385 | Z30: =IF(ISNUMBER(M30),(RANK(M30,M$23:M$36,1)-1)/(COUNT(M$23:M$36)-1)*100,0) -> 38.461538 | AA30: =IF(ISNUMBER(N30),(RANK(N30,N$23:N$36,1)-1)/(COUNT(N$23:N$36)-1)*100,0) -> 23.076923 | AB30: =IF(ISNUMBER(O30),(RANK(O30,O$23:O$36,0)-1)/(COUNT(O$23:O$36)-1)*100,50) -> 25 | AC30: =P30*$D$5+Q30*$D$6+R30*$D$7+S30*$D$8+T30*$D$9+U30*$D$10+V30*$D$11+W30*$D$12+X30*$D$13+Y30*$D$14+Z30*$D$15+AA30*$D$16+AB30*$D$17 -> 46.128205 | AD30: =P30*$E$5+Q30*$E$6+R30*$E$7+S30*$E$8+T30*$E$9+U30*$E$10+V30*$E$11+W30*$E$12+X30*$E$13+Y30*$E$14+Z30*$E$15+AA30*$E$16+AB30*$E$17 -> 44.403846 | AE30: =P30*$F$5+Q30*$F$6+R30*$F$7+S30*$F$8+T30*$F$9+U30*$F$10+V30*$F$11+W30*$F$12+X30*$F$13+Y30*$F$14+Z30*$F$15+AA30*$F$16+AB30*$F$17 -> 46.480769 | AF30: =P30*$G$5+Q30*$G$6+R30*$G$7+S30*$G$8+T30*$G$9+U30*$G$10+V30*$G$11+W30*$G$12+X30*$G$13+Y30*$G$14+Z30*$G$15+AA30*$G$16+AB30*$G$17 -> 47.429487 | AG30: =P30*$H$5+Q30*$H$6+R30*$H$7+S30*$H$8+T30*$H$9+U30*$H$10+V30*$H$11+W30*$H$12+X30*$H$13+Y30*$H$14+Z30*$H$15+AA30*$H$16+AB30*$H$17 -> 49.730769 | AH30: =RANK(AC30,$AC$23:$AC$36,0) -> 10 | AI30: ='Risk Metrics'!G9 -> 0.869804 | AJ30: ='Investor Personas'!$C$13+AI30*'Investor Personas'!$C$10 -> 0.13438628 | AK30: ='Master Fund Sheet'!AB9 -> 0.0203 | AL30: =IF(ISNUMBER('Master Fund Sheet'!R9),MIN(AK30*'Master Fund Sheet'!R9,1),1) -> 0.70967777 | AM30: =MIN(MAX('Master Fund Sheet'!T9*(1-AL30),0),'Investor Personas'!$C$14) -> 0.047148331 | AN30: =AK30+AM30 -> 0.067448331 | AO30: ='Investor Personas'!$C$11*AJ30+(1-'Investor Personas'!$C$11)*AN30 -> 0.10091731 | AP30: =(AC30-50)/50*'Investor Personas'!$C$12 -> -0.0023230769 | AQ30: =AO30+AP30 -> 0.098594228 | AR30: ='Master Fund Sheet'!I9*(1+AQ30)^'Investor Personas'!$F$1 -> 514.98095
A31: ='Master Fund Sheet'!C10 -> ASTRAL | B31: ='Master Fund Sheet'!B10 -> Mid Cap | C31: ='Master Fund Sheet'!P10 -> 38943 | D31: ='Master Fund Sheet'!W10 -> 0.17 | E31: ='Master Fund Sheet'!X10 -> 0.024102564 | F31: ='Master Fund Sheet'!T10 -> 0.138 | G31: ='Master Fund Sheet'!S10 -> 0.192 | H31: ='Master Fund Sheet'!R10 -> 67.344844 | I31: ='Master Fund Sheet'!Z10 -> 11.224141 | J31: ='Master Fund Sheet'!V10 -> 9.5576159 | K31: ='Risk Metrics'!G10 -> 0.69741418 | L31: ='Risk Metrics'!F10 -> 0.28894233 | M31: ='Master Fund Sheet'!AD10 -> -0.031267662 | N31: ='Master Fund Sheet'!AE10 -> -0.14161692 | O31: ='Master Fund Sheet'!AA10 -> 0.062 | P31: =IF(ISNUMBER(C31),(RANK(C31,C$23:C$36,1)-1)/(COUNT(C$23:C$36)-1)*100,0) -> 30.769231 | Q31: =IF(ISNUMBER(D31),(RANK(D31,D$23:D$36,1)-1)/(COUNT(D$23:D$36)-1)*100,0) -> 84.615385 | R31: =IF(ISNUMBER(E31),(RANK(E31,E$23:E$36,1)-1)/(COUNT(E$23:E$36)-1)*100,0) -> 46.153846 | S31: =IF(ISNUMBER(F31),(RANK(F31,F$23:F$36,1)-1)/(COUNT(F$23:F$36)-1)*100,0) -> 46.153846 | T31: =IF(ISNUMBER(G31),(RANK(G31,G$23:G$36,1)-1)/(COUNT(G$23:G$36)-1)*100,0) -> 61.538462 | U31: =IF(ISNUMBER(H31),(RANK(H31,H$23:H$36,0)-1)/(COUNT(H$23:H$36)-1)*100,0) -> 0 | V31: =IF(ISNUMBER(I31),(RANK(I31,I$23:I$36,0)-1)/(COUNT(I$23:I$36)-1)*100,0) -> 0 | W31: =IF(ISNUMBER(J31),(RANK(J31,J$23:J$36,0)-1)/(COUNT(J$23:J$36)-1)*100,0) -> 0 | X31: =IF(ISNUMBER(K31),(RANK(K31,K$23:K$36,0)-1)/(COUNT(K$23:K$36)-1)*100,0) -> 92.307692 | Y31: =IF(ISNUMBER(L31),(RANK(L31,L$23:L$36,0)-1)/(COUNT(L$23:L$36)-1)*100,0) -> 30.769231 | Z31: =IF(ISNUMBER(M31),(RANK(M31,M$23:M$36,1)-1)/(COUNT(M$23:M$36)-1)*100,0) -> 84.615385 | AA31: =IF(ISNUMBER(N31),(RANK(N31,N$23:N$36,1)-1)/(COUNT(N$23:N$36)-1)*100,0) -> 7.6923077 | AB31: =IF(ISNUMBER(O31),(RANK(O31,O$23:O$36,0)-1)/(COUNT(O$23:O$36)-1)*100,50) -> 41.666667 | AC31: =P31*$D$5+Q31*$D$6+R31*$D$7+S31*$D$8+T31*$D$9+U31*$D$10+V31*$D$11+W31*$D$12+X31*$D$13+Y31*$D$14+Z31*$D$15+AA31*$D$16+AB31*$D$17 -> 43.794872 | AD31: =P31*$E$5+Q31*$E$6+R31*$E$7+S31*$E$8+T31*$E$9+U31*$E$10+V31*$E$11+W31*$E$12+X31*$E$13+Y31*$E$14+Z31*$E$15+AA31*$E$16+AB31*$E$17 -> 45.423077 | AE31: =P31*$F$5+Q31*$F$6+R31*$F$7+S31*$F$8+T31*$F$9+U31*$F$10+V31*$F$11+W31*$F$12+X31*$F$13+Y31*$F$14+Z31*$F$15+AA31*$F$16+AB31*$F$17 -> 45.115385 | AF31: =P31*$G$5+Q31*$G$6+R31*$G$7+S31*$G$8+T31*$G$9+U31*$G$10+V31*$G$11+W31*$G$12+X31*$G$13+Y31*$G$14+Z31*$G$15+AA31*$G$16+AB31*$G$17 -> 44.410256 | AG31: =P31*$H$5+Q31*$H$6+R31*$H$7+S31*$H$8+T31*$H$9+U31*$H$10+V31*$H$11+W31*$H$12+X31*$H$13+Y31*$H$14+Z31*$H$15+AA31*$H$16+AB31*$H$17 -> 43.102564 | AH31: =RANK(AC31,$AC$23:$AC$36,0) -> 12 | AI31: ='Risk Metrics'!G10 -> 0.69741418 | AJ31: ='Investor Personas'!$C$13+AI31*'Investor Personas'!$C$10 -> 0.12231899 | AK31: ='Master Fund Sheet'!AB10 -> 0.0028 | AL31: =IF(ISNUMBER('Master Fund Sheet'!R10),MIN(AK31*'Master Fund Sheet'!R10,1),1) -> 0.18856556 | AM31: =MIN(MAX('Master Fund Sheet'!T10*(1-AL31),0),'Investor Personas'!$C$14) -> 0.11197795 | AN31: =AK31+AM31 -> 0.11477795 | AO31: ='Investor Personas'!$C$11*AJ31+(1-'Investor Personas'!$C$11)*AN31 -> 0.11854847 | AP31: =(AC31-50)/50*'Investor Personas'!$C$12 -> -0.0037230769 | AQ31: =AO31+AP31 -> 0.1148254 | AR31: ='Master Fund Sheet'!I10*(1+AQ31)^'Investor Personas'!$F$1 -> 1999.6182
A32: ='Master Fund Sheet'!C11 -> KEI | B32: ='Master Fund Sheet'!B11 -> Mid Cap | C32: ='Master Fund Sheet'!P11 -> 44393 | D32: ='Master Fund Sheet'!W11 -> 0.2 | E32: ='Master Fund Sheet'!X11 -> 0.31819429 | F32: ='Master Fund Sheet'!T11 -> 0.147 | G32: ='Master Fund Sheet'!S11 -> 0.2 | H32: ='Master Fund Sheet'!R11 -> 44.572305 | I32: ='Master Fund Sheet'!Z11 -> 1.8571794 | J32: ='Master Fund Sheet'!V11 -> 6.6685796 | K32: ='Risk Metrics'!G11 -> 1.4331655 | L32: ='Risk Metrics'!F11 -> 0.3763088 | M32: ='Master Fund Sheet'!AD11 -> -0.038501916 | N32: ='Master Fund Sheet'!AE11 -> 0.10326895 | O32: ='Master Fund Sheet'!AA11 -> 0.038 | P32: =IF(ISNUMBER(C32),(RANK(C32,C$23:C$36,1)-1)/(COUNT(C$23:C$36)-1)*100,0) -> 38.461538 | Q32: =IF(ISNUMBER(D32),(RANK(D32,D$23:D$36,1)-1)/(COUNT(D$23:D$36)-1)*100,0) -> 92.307692 | R32: =IF(ISNUMBER(E32),(RANK(E32,E$23:E$36,1)-1)/(COUNT(E$23:E$36)-1)*100,0) -> 92.307692 | S32: =IF(ISNUMBER(F32),(RANK(F32,F$23:F$36,1)-1)/(COUNT(F$23:F$36)-1)*100,0) -> 69.230769 | T32: =IF(ISNUMBER(G32),(RANK(G32,G$23:G$36,1)-1)/(COUNT(G$23:G$36)-1)*100,0) -> 69.230769 | U32: =IF(ISNUMBER(H32),(RANK(H32,H$23:H$36,0)-1)/(COUNT(H$23:H$36)-1)*100,0) -> 15.384615 | V32: =IF(ISNUMBER(I32),(RANK(I32,I$23:I$36,0)-1)/(COUNT(I$23:I$36)-1)*100,0) -> 58.333333 | W32: =IF(ISNUMBER(J32),(RANK(J32,J$23:J$36,0)-1)/(COUNT(J$23:J$36)-1)*100,0) -> 7.6923077 | X32: =IF(ISNUMBER(K32),(RANK(K32,K$23:K$36,0)-1)/(COUNT(K$23:K$36)-1)*100,0) -> 7.6923077 | Y32: =IF(ISNUMBER(L32),(RANK(L32,L$23:L$36,0)-1)/(COUNT(L$23:L$36)-1)*100,0) -> 15.384615 | Z32: =IF(ISNUMBER(M32),(RANK(M32,M$23:M$36,1)-1)/(COUNT(M$23:M$36)-1)*100,0) -> 76.923077 | AA32: =IF(ISNUMBER(N32),(RANK(N32,N$23:N$36,1)-1)/(COUNT(N$23:N$36)-1)*100,0) -> 84.615385 | AB32: =IF(ISNUMBER(O32),(RANK(O32,O$23:O$36,0)-1)/(COUNT(O$23:O$36)-1)*100,50) -> 66.666667 | AC32: =P32*$D$5+Q32*$D$6+R32*$D$7+S32*$D$8+T32*$D$9+U32*$D$10+V32*$D$11+W32*$D$12+X32*$D$13+Y32*$D$14+Z32*$D$15+AA32*$D$16+AB32*$D$17 -> 59.384615 | AD32: =P32*$E$5+Q32*$E$6+R32*$E$7+S32*$E$8+T32*$E$9+U32*$E$10+V32*$E$11+W32*$E$12+X32*$E$13+Y32*$E$14+Z32*$E$15+AA32*$E$16+AB32*$E$17 -> 68.480769 | AE32: =P32*$F$5+Q32*$F$6+R32*$F$7+S32*$F$8+T32*$F$9+U32*$F$10+V32*$F$11+W32*$F$12+X32*$F$13+Y32*$F$14+Z32*$F$15+AA32*$F$16+AB32*$F$17 -> 63.403846 | AF32: =P32*$G$5+Q32*$G$6+R32*$G$7+S32*$G$8+T32*$G$9+U32*$G$10+V32*$G$11+W32*$G$12+X32*$G$13+Y32*$G$14+Z32*$G$15+AA32*$G$16+AB32*$G$17 -> 57.801282 | AG32: =P32*$H$5+Q32*$H$6+R32*$H$7+S32*$H$8+T32*$H$9+U32*$H$10+V32*$H$11+W32*$H$12+X32*$H$13+Y32*$H$14+Z32*$H$15+AA32*$H$16+AB32*$H$17 -> 49.910256 | AH32: =RANK(AC32,$AC$23:$AC$36,0) -> 4 | AI32: ='Risk Metrics'!G11 -> 1.4331655 | AJ32: ='Investor Personas'!$C$13+AI32*'Investor Personas'!$C$10 -> 0.17382158 | AK32: ='Master Fund Sheet'!AB11 -> 0.001 | AL32: =IF(ISNUMBER('Master Fund Sheet'!R11),MIN(AK32*'Master Fund Sheet'!R11,1),1) -> 0.044572305 | AM32: =MIN(MAX('Master Fund Sheet'!T11*(1-AL32),0),'Investor Personas'!$C$14) -> 0.14044787 | AN32: =AK32+AM32 -> 0.14144787 | AO32: ='Investor Personas'!$C$11*AJ32+(1-'Investor Personas'!$C$11)*AN32 -> 0.15763473 | AP32: =(AC32-50)/50*'Investor Personas'!$C$12 -> 0.0056307692 | AQ32: =AO32+AP32 -> 0.1632655 | AR32: ='Master Fund Sheet'!I11*(1+AQ32)^'Investor Personas'!$F$1 -> 7316.4879
A33: ='Master Fund Sheet'!C12 -> BATAINDIA | B33: ='Master Fund Sheet'!B12 -> Small Cap | C33: ='Master Fund Sheet'!P12 -> 7960 | D33: ='Master Fund Sheet'!W12 -> 0.0077 | E33: ='Master Fund Sheet'!X12 -> -0.59424796 | F33: ='Master Fund Sheet'!T12 -> 0.0847 | G33: ='Master Fund Sheet'!S12 -> 0.113 | H33: ='Master Fund Sheet'!R12 -> 59.324713 | I33: ='Master Fund Sheet'!Z12 -> N/A | J33: ='Master Fund Sheet'!V12 -> 4.9891252 | K33: ='Risk Metrics'!G12 -> 1.2813252 | L33: ='Risk Metrics'!F12 -> 0.25126434 | M33: ='Master Fund Sheet'!AD12 -> -0.11580165 | N33: ='Master Fund Sheet'!AE12 -> 0.067215151 | O33: ='Master Fund Sheet'!AA12 -> 0.87 | P33: =IF(ISNUMBER(C33),(RANK(C33,C$23:C$36,1)-1)/(COUNT(C$23:C$36)-1)*100,0) -> 15.384615 | Q33: =IF(ISNUMBER(D33),(RANK(D33,D$23:D$36,1)-1)/(COUNT(D$23:D$36)-1)*100,0) -> 7.6923077 | R33: =IF(ISNUMBER(E33),(RANK(E33,E$23:E$36,1)-1)/(COUNT(E$23:E$36)-1)*100,0) -> 7.6923077 | S33: =IF(ISNUMBER(F33),(RANK(F33,F$23:F$36,1)-1)/(COUNT(F$23:F$36)-1)*100,0) -> 7.6923077 | T33: =IF(ISNUMBER(G33),(RANK(G33,G$23:G$36,1)-1)/(COUNT(G$23:G$36)-1)*100,0) -> 30.769231 | U33: =IF(ISNUMBER(H33),(RANK(H33,H$23:H$36,0)-1)/(COUNT(H$23:H$36)-1)*100,0) -> 7.6923077 | V33: =IF(ISNUMBER(I33),(RANK(I33,I$23:I$36,0)-1)/(COUNT(I$23:I$36)-1)*100,0) -> 0 | W33: =IF(ISNUMBER(J33),(RANK(J33,J$23:J$36,0)-1)/(COUNT(J$23:J$36)-1)*100,0) -> 30.769231 | X33: =IF(ISNUMBER(K33),(RANK(K33,K$23:K$36,0)-1)/(COUNT(K$23:K$36)-1)*100,0) -> 23.076923 | Y33: =IF(ISNUMBER(L33),(RANK(L33,L$23:L$36,0)-1)/(COUNT(L$23:L$36)-1)*100,0) -> 53.846154 | Z33: =IF(ISNUMBER(M33),(RANK(M33,M$23:M$36,1)-1)/(COUNT(M$23:M$36)-1)*100,0) -> 23.076923 | AA33: =IF(ISNUMBER(N33),(RANK(N33,N$23:N$36,1)-1)/(COUNT(N$23:N$36)-1)*100,0) -> 76.923077 | AB33: =IF(ISNUMBER(O33),(RANK(O33,O$23:O$36,0)-1)/(COUNT(O$23:O$36)-1)*100,50) -> 8.3333333 | AC33: =P33*$D$5+Q33*$D$6+R33*$D$7+S33*$D$8+T33*$D$9+U33*$D$10+V33*$D$11+W33*$D$12+X33*$D$13+Y33*$D$14+Z33*$D$15+AA33*$D$16+AB33*$D$17 -> 18.820513 | AD33: =P33*$E$5+Q33*$E$6+R33*$E$7+S33*$E$8+T33*$E$9+U33*$E$10+V33*$E$11+W33*$E$12+X33*$E$13+Y33*$E$14+Z33*$E$15+AA33*$E$16+AB33*$E$17 -> 20.038462 | AE33: =P33*$F$5+Q33*$F$6+R33*$F$7+S33*$F$8+T33*$F$9+U33*$F$10+V33*$F$11+W33*$F$12+X33*$F$13+Y33*$F$14+Z33*$F$15+AA33*$F$16+AB33*$F$17 -> 18.576923 | AF33: =P33*$G$5+Q33*$G$6+R33*$G$7+S33*$G$8+T33*$G$9+U33*$G$10+V33*$G$11+W33*$G$12+X33*$G$13+Y33*$G$14+Z33*$G$15+AA33*$G$16+AB33*$G$17 -> 18.74359 | AG33: =P33*$H$5+Q33*$H$6+R33*$H$7+S33*$H$8+T33*$H$9+U33*$H$10+V33*$H$11+W33*$H$12+X33*$H$13+Y33*$H$14+Z33*$H$15+AA33*$H$16+AB33*$H$17 -> 18.897436 | AH33: =RANK(AC33,$AC$23:$AC$36,0) -> 14 | AI33: ='Risk Metrics'!G12 -> 1.2813252 | AJ33: ='Investor Personas'!$C$13+AI33*'Investor Personas'!$C$10 -> 0.16319277 | AK33: ='Master Fund Sheet'!AB12 -> 0.0145 | AL33: =IF(ISNUMBER('Master Fund Sheet'!R12),MIN(AK33*'Master Fund Sheet'!R12,1),1) -> 0.86020833 | AM33: =MIN(MAX('Master Fund Sheet'!T12*(1-AL33),0),'Investor Personas'!$C$14) -> 0.011840354 | AN33: =AK33+AM33 -> 0.026340354 | AO33: ='Investor Personas'!$C$11*AJ33+(1-'Investor Personas'!$C$11)*AN33 -> 0.09476656 | AP33: =(AC33-50)/50*'Investor Personas'!$C$12 -> -0.018707692 | AQ33: =AO33+AP33 -> 0.076058867 | AR33: ='Master Fund Sheet'!I12*(1+AQ33)^'Investor Personas'!$F$1 -> 771.69242
A34: ='Master Fund Sheet'!C13 -> ZEEL | B34: ='Master Fund Sheet'!B13 -> Small Cap | C34: ='Master Fund Sheet'!P13 -> 7089 | D34: ='Master Fund Sheet'!W13 -> 0.0242 | E34: ='Master Fund Sheet'!X13 -> -0.59830269 | F34: ='Master Fund Sheet'!T13 -> 0.0233 | G34: ='Master Fund Sheet'!S13 -> 0.011 | H34: ='Master Fund Sheet'!R13 -> 34.652582 | I34: ='Master Fund Sheet'!Z13 -> 8.6631455 | J34: ='Master Fund Sheet'!V13 -> 0.61 | K34: ='Risk Metrics'!G13 -> 1.6233346 | L34: ='Risk Metrics'!F13 -> 0.43490426 | M34: ='Master Fund Sheet'!AD13 -> -0.16463891 | N34: ='Master Fund Sheet'!AE13 -> 0.056911723 | O34: ='Master Fund Sheet'!AA13 -> 0.02 | P34: =IF(ISNUMBER(C34),(RANK(C34,C$23:C$36,1)-1)/(COUNT(C$23:C$36)-1)*100,0) -> 7.6923077 | Q34: =IF(ISNUMBER(D34),(RANK(D34,D$23:D$36,1)-1)/(COUNT(D$23:D$36)-1)*100,0) -> 15.384615 | R34: =IF(ISNUMBER(E34),(RANK(E34,E$23:E$36,1)-1)/(COUNT(E$23:E$36)-1)*100,0) -> 0 | S34: =IF(ISNUMBER(F34),(RANK(F34,F$23:F$36,1)-1)/(COUNT(F$23:F$36)-1)*100,0) -> 0 | T34: =IF(ISNUMBER(G34),(RANK(G34,G$23:G$36,1)-1)/(COUNT(G$23:G$36)-1)*100,0) -> 0 | U34: =IF(ISNUMBER(H34),(RANK(H34,H$23:H$36,0)-1)/(COUNT(H$23:H$36)-1)*100,0) -> 30.769231 | V34: =IF(ISNUMBER(I34),(RANK(I34,I$23:I$36,0)-1)/(COUNT(I$23:I$36)-1)*100,0) -> 16.666667 | W34: =IF(ISNUMBER(J34),(RANK(J34,J$23:J$36,0)-1)/(COUNT(J$23:J$36)-1)*100,0) -> 100 | X34: =IF(ISNUMBER(K34),(RANK(K34,K$23:K$36,0)-1)/(COUNT(K$23:K$36)-1)*100,0) -> 0 | Y34: =IF(ISNUMBER(L34),(RANK(L34,L$23:L$36,0)-1)/(COUNT(L$23:L$36)-1)*100,0) -> 7.6923077 | Z34: =IF(ISNUMBER(M34),(RANK(M34,M$23:M$36,1)-1)/(COUNT(M$23:M$36)-1)*100,0) -> 7.6923077 | AA34: =IF(ISNUMBER(N34),(RANK(N34,N$23:N$36,1)-1)/(COUNT(N$23:N$36)-1)*100,0) -> 69.230769 | AB34: =IF(ISNUMBER(O34),(RANK(O34,O$23:O$36,0)-1)/(COUNT(O$23:O$36)-1)*100,50) -> 83.333333 | AC34: =P34*$D$5+Q34*$D$6+R34*$D$7+S34*$D$8+T34*$D$9+U34*$D$10+V34*$D$11+W34*$D$12+X34*$D$13+Y34*$D$14+Z34*$D$15+AA34*$D$16+AB34*$D$17 -> 20.769231 | AD34: =P34*$E$5+Q34*$E$6+R34*$E$7+S34*$E$8+T34*$E$9+U34*$E$10+V34*$E$11+W34*$E$12+X34*$E$13+Y34*$E$14+Z34*$E$15+AA34*$E$16+AB34*$E$17 -> 20.423077 | AE34: =P34*$F$5+Q34*$F$6+R34*$F$7+S34*$F$8+T34*$F$9+U34*$F$10+V34*$F$11+W34*$F$12+X34*$F$13+Y34*$F$14+Z34*$F$15+AA34*$F$16+AB34*$F$17 -> 18.807692 | AF34: =P34*$G$5+Q34*$G$6+R34*$G$7+S34*$G$8+T34*$G$9+U34*$G$10+V34*$G$11+W34*$G$12+X34*$G$13+Y34*$G$14+Z34*$G$15+AA34*$G$16+AB34*$G$17 -> 19.987179 | AG34: =P34*$H$5+Q34*$H$6+R34*$H$7+S34*$H$8+T34*$H$9+U34*$H$10+V34*$H$11+W34*$H$12+X34*$H$13+Y34*$H$14+Z34*$H$15+AA34*$H$16+AB34*$H$17 -> 18.974359 | AH34: =RANK(AC34,$AC$23:$AC$36,0) -> 13 | AI34: ='Risk Metrics'!G13 -> 1.6233346 | AJ34: ='Investor Personas'!$C$13+AI34*'Investor Personas'!$C$10 -> 0.18713342 | AK34: ='Master Fund Sheet'!AB13 -> 0.027 | AL34: =IF(ISNUMBER('Master Fund Sheet'!R13),MIN(AK34*'Master Fund Sheet'!R13,1),1) -> 0.93561972 | AM34: =MIN(MAX('Master Fund Sheet'!T13*(1-AL34),0),'Investor Personas'!$C$14) -> 0.0015000606 | AN34: =AK34+AM34 -> 0.028500061 | AO34: ='Investor Personas'!$C$11*AJ34+(1-'Investor Personas'!$C$11)*AN34 -> 0.10781674 | AP34: =(AC34-50)/50*'Investor Personas'!$C$12 -> -0.017538462 | AQ34: =AO34+AP34 -> 0.090278279 | AR34: ='Master Fund Sheet'!I13*(1+AQ34)^'Investor Personas'!$F$1 -> 95.659319
... A36: ='Master Fund Sheet'!C15 -> EIHOTEL | B36: ='Master Fund Sheet'!B15 -> Small Cap | C36: ='Master Fund Sheet'!P15 -> 18286 | D36: ='Master Fund Sheet'!W15 -> 0.08 | E36: ='Master Fund Sheet'!X15 -> -0.14974619 | F36: ='Master Fund Sheet'!T15 -> 0.145 | G36: ='Master Fund Sheet'!S15 -> 0.207 | H36: ='Master Fund Sheet'!R15 -> 25.654657 | I36: ='Master Fund Sheet'!Z15 -> 1.0261863 | J36: ='Master Fund Sheet'!V15 -> 3.4673397 | K36: ='Risk Metrics'!G15 -> 1.1041444 | L36: ='Risk Metrics'!F15 -> 0.36286992 | M36: ='Master Fund Sheet'!AD15 -> -0.059978492 | N36: ='Master Fund Sheet'!AE15 -> 0.10572509 | O36: ='Master Fund Sheet'!AA15 -> 0.048 | P36: =IF(ISNUMBER(C36),(RANK(C36,C$23:C$36,1)-1)/(COUNT(C$23:C$36)-1)*100,0) -> 23.076923 | Q36: =IF(ISNUMBER(D36),(RANK(D36,D$23:D$36,1)-1)/(COUNT(D$23:D$36)-1)*100,0) -> 46.153846 | R36: =IF(ISNUMBER(E36),(RANK(E36,E$23:E$36,1)-1)/(COUNT(E$23:E$36)-1)*100,0) -> 23.076923 | S36: =IF(ISNUMBER(F36),(RANK(F36,F$23:F$36,1)-1)/(COUNT(F$23:F$36)-1)*100,0) -> 61.538462 | T36: =IF(ISNUMBER(G36),(RANK(G36,G$23:G$36,1)-1)/(COUNT(G$23:G$36)-1)*100,0) -> 84.615385 | U36: =IF(ISNUMBER(H36),(RANK(H36,H$23:H$36,0)-1)/(COUNT(H$23:H$36)-1)*100,0) -> 46.153846 | V36: =IF(ISNUMBER(I36),(RANK(I36,I$23:I$36,0)-1)/(COUNT(I$23:I$36)-1)*100,0) -> 83.333333 | W36: =IF(ISNUMBER(J36),(RANK(J36,J$23:J$36,0)-1)/(COUNT(J$23:J$36)-1)*100,0) -> 53.846154 | X36: =IF(ISNUMBER(K36),(RANK(K36,K$23:K$36,0)-1)/(COUNT(K$23:K$36)-1)*100,0) -> 38.461538 | Y36: =IF(ISNUMBER(L36),(RANK(L36,L$23:L$36,0)-1)/(COUNT(L$23:L$36)-1)*100,0) -> 23.076923 | Z36: =IF(ISNUMBER(M36),(RANK(M36,M$23:M$36,1)-1)/(COUNT(M$23:M$36)-1)*100,0) -> 69.230769 | AA36: =IF(ISNUMBER(N36),(RANK(N36,N$23:N$36,1)-1)/(COUNT(N$23:N$36)-1)*100,0) -> 92.307692 | AB36: =IF(ISNUMBER(O36),(RANK(O36,O$23:O$36,0)-1)/(COUNT(O$23:O$36)-1)*100,50) -> 58.333333 | AC36: =P36*$D$5+Q36*$D$6+R36*$D$7+S36*$D$8+T36*$D$9+U36*$D$10+V36*$D$11+W36*$D$12+X36*$D$13+Y36*$D$14+Z36*$D$15+AA36*$D$16+AB36*$D$17 -> 51.410256 | AD36: =P36*$E$5+Q36*$E$6+R36*$E$7+S36*$E$8+T36*$E$9+U36*$E$10+V36*$E$11+W36*$E$12+X36*$E$13+Y36*$E$14+Z36*$E$15+AA36*$E$16+AB36*$E$17 -> 55.153846 | AE36: =P36*$F$5+Q36*$F$6+R36*$F$7+S36*$F$8+T36*$F$9+U36*$F$10+V36*$F$11+W36*$F$12+X36*$F$13+Y36*$F$14+Z36*$F$15+AA36*$F$16+AB36*$F$17 -> 52.615385 | AF36: =P36*$G$5+Q36*$G$6+R36*$G$7+S36*$G$8+T36*$G$9+U36*$G$10+V36*$G$11+W36*$G$12+X36*$G$13+Y36*$G$14+Z36*$G$15+AA36*$G$16+AB36*$G$17 -> 49.807692 | AG36: =P36*$H$5+Q36*$H$6+R36*$H$7+S36*$H$8+T36*$H$9+U36*$H$10+V36*$H$11+W36*$H$12+X36*$H$13+Y36*$H$14+Z36*$H$15+AA36*$H$16+AB36*$H$17 -> 47.512821 | AH36: =RANK(AC36,$AC$23:$AC$36,0) -> 7 | AI36: ='Risk Metrics'!G15 -> 1.1041444 | AJ36: ='Investor Personas'!$C$13+AI36*'Investor Personas'!$C$10 -> 0.15079011 | AK36: ='Master Fund Sheet'!AB15 -> 0.0051 | AL36: =IF(ISNUMBER('Master Fund Sheet'!R15),MIN(AK36*'Master Fund Sheet'!R15,1),1) -> 0.13083875 | AM36: =MIN(MAX('Master Fund Sheet'!T15*(1-AL36),0),'Investor Personas'!$C$14) -> 0.12602838 | AN36: =AK36+AM36 -> 0.13112838 | AO36: ='Investor Personas'!$C$11*AJ36+(1-'Investor Personas'!$C$11)*AN36 -> 0.14095925 | AP36: =(AC36-50)/50*'Investor Personas'!$C$12 -> 0.00084615385 | AQ36: =AO36+AP36 -> 0.1418054 | AR36: ='Master Fund Sheet'!I15*(1+AQ36)^'Investor Personas'!$F$1 -> 434.59503
A38: Score = (rank − 1) ÷ (n − 1) × 100 in the 'better' direction, so outliers (e.g. Tata Steel's low-base EPS jump) cannot dominate. N/A metrics score 0 (PEG with negative growth) or a neutral 50 (bank Debt/Equity). Expected return: CAPM (Rƒ + β × ERP) blended 50:50 with dividend yield + ROE × retention, then ± up to 3% for the House score. No P/E re-rating assumed.

Sheet Notes
A1: NOTES
A3: Types of assets
A4: Equity (Stock) | B4: E
A5: Government Bond | B5: G
A6: Corporate Bond | B6: B
A8: Industry (from Master Fund Sheet) | B8: Large Cap | C8: Mid Cap | D8: Small Cap | E8: Total | G8: Method notes
A9: ='Master Fund Sheet'!E2 -> Oil & Gas / Conglomerate | B9: =COUNTIFS('Master Fund Sheet'!$E$2:$E$15,$A9,'Master Fund Sheet'!$B$2:$B$15,"Large Cap") -> 1 | C9: =COUNTIFS('Master Fund Sheet'!$E$2:$E$15,$A9,'Master Fund Sheet'!$B$2:$B$15,"Mid Cap") -> 0 | D9: =COUNTIFS('Master Fund Sheet'!$E$2:$E$15,$A9,'Master Fund Sheet'!$B$2:$B$15,"Small Cap") -> 0 | E9: =SUM(B9:D9) -> 1 | G9: Target | H9: ₹1 Cr → ₹2.00-2.15 Cr in 3 years = 26.0%-29.1% CAGR required.
A10: ='Master Fund Sheet'!E3 -> Private Sector Banking | B10: =COUNTIFS('Master Fund Sheet'!$E$2:$E$15,$A10,'Master Fund Sheet'!$B$2:$B$15,"Large Cap") -> 1 | C10: =COUNTIFS('Master Fund Sheet'!$E$2:$E$15,$A10,'Master Fund Sheet'!$B$2:$B$15,"Mid Cap") -> 0 | D10: =COUNTIFS('Master Fund Sheet'!$E$2:$E$15,$A10,'Master Fund Sheet'!$B$2:$B$15,"Small Cap") -> 0 | E10: =SUM(B10:D10) -> 1 | G10: Return metric | H10: Capital appreciation + dividends (equity); interest net of expected credit loss (debt).
A11: ='Master Fund Sheet'!E4 -> IT Services | B11: =COUNTIFS('Master Fund Sheet'!$E$2:$E$15,$A11,'Master Fund Sheet'!$B$2:$B$15,"Large Cap") -> 1 | C11: =COUNTIFS('Master Fund Sheet'!$E$2:$E$15,$A11,'Master Fund Sheet'!$B$2:$B$15,"Mid Cap") -> 0 | D11: =COUNTIFS('Master Fund Sheet'!$E$2:$E$15,$A11,'Master Fund Sheet'!$B$2:$B$15,"Small Cap") -> 0 | E11: =SUM(B11:D11) -> 1 | G11: Risk measures | H11: Beta and SD from 60 monthly returns vs NIFTY 50; portfolio SD from the 5-year hypothetical history (Risk Metrics → portfolio block).
A12: ='Master Fund Sheet'!E5 -> FMCG (Cigarettes, Foods, Agri) | B12: =COUNTIFS('Master Fund Sheet'!$E$2:$E$15,$A12,'Master Fund Sheet'!$B$2:$B$15,"Large Cap") -> 1 | C12: =COUNTIFS('Master Fund Sheet'!$E$2:$E$15,$A12,'Master Fund Sheet'!$B$2:$B$15,"Mid Cap") -> 0 | D12: =COUNTIFS('Master Fund Sheet'!$E$2:$E$15,$A12,'Master Fund Sheet'!$B$2:$B$15,"Small Cap") -> 0 | E12: =SUM(B12:D12) -> 1 | G12: Weights | H12: 13 factors; Market Cap + Sales YoY + EPS growth = 31-38% in every investor's set (see Scoring Model).
A13: ='Master Fund Sheet'!E6 -> Pharmaceuticals | B13: =COUNTIFS('Master Fund Sheet'!$E$2:$E$15,$A13,'Master Fund Sheet'!$B$2:$B$15,"Large Cap") -> 1 | C13: =COUNTIFS('Master Fund Sheet'!$E$2:$E$15,$A13,'Master Fund Sheet'!$B$2:$B$15,"Mid Cap") -> 0 | D13: =COUNTIFS('Master Fund Sheet'!$E$2:$E$15,$A13,'Master Fund Sheet'!$B$2:$B$15,"Small Cap") -> 0 | E13: =SUM(B13:D13) -> 1 | G13: Allocation rule | H13: Equity % × segment split (Large/Mid/Small) → within a segment weight ∝ investor score, subject to max beta & min score → rounded to whole %.
A14: ='Master Fund Sheet'!E7 -> Automobiles (Passenger Vehicles) | B14: =COUNTIFS('Master Fund Sheet'!$E$2:$E$15,$A14,'Master Fund Sheet'!$B$2:$B$15,"Large Cap") -> 1 | C14: =COUNTIFS('Master Fund Sheet'!$E$2:$E$15,$A14,'Master Fund Sheet'!$B$2:$B$15,"Mid Cap") -> 0 | D14: =COUNTIFS('Master Fund Sheet'!$E$2:$E$15,$A14,'Master Fund Sheet'!$B$2:$B$15,"Small Cap") -> 0 | E14: =SUM(B14:D14) -> 1 | G14: Rƒ | H14: 7.35% (10Y G-Sec, 13-Oct-2026). ERP 7%.
A15: ='Master Fund Sheet'!E8 -> Metals & Mining (Steel) | B15: =COUNTIFS('Master Fund Sheet'!$E$2:$E$15,$A15,'Master Fund Sheet'!$B$2:$B$15,"Large Cap") -> 1 | C15: =COUNTIFS('Master Fund Sheet'!$E$2:$E$15,$A15,'Master Fund Sheet'!$B$2:$B$15,"Mid Cap") -> 0 | D15: =COUNTIFS('Master Fund Sheet'!$E$2:$E$15,$A15,'Master Fund Sheet'!$B$2:$B$15,"Small Cap") -> 0 | E15: =SUM(B15:D15) -> 1 | G15: Data sources | H15: Screener.in (fundamentals, 14-Oct-2026); Stockanalysis.com for Dabur, Bata, Zee, Justdial (Screener cache stale); Yahoo Finance (prices); Trading Economics / RBI (yields); PSU Connect & Chanakya Nipothi (NCDs).
A16: ='Master Fund Sheet'!E9 -> Personal Care & Ayurveda | B16: =COUNTIFS('Master Fund Sheet'!$E$2:$E$15,$A16,'Master Fund Sheet'!$B$2:$B$15,"Large Cap") -> 0 | C16: =COUNTIFS('Master Fund Sheet'!$E$2:$E$15,$A16,'Master Fund Sheet'!$B$2:$B$15,"Mid Cap") -> 1 | D16: =COUNTIFS('Master Fund Sheet'!$E$2:$E$15,$A16,'Master Fund Sheet'!$B$2:$B$15,"Small Cap") -> 0 | E16: =SUM(B16:D16) -> 1 | G16: Limitations | H16: Model estimates, not forecasts; taxes/brokerage ignored; default probabilities are indicative; historical portfolio SD uses today's weights (look-ahead).
A17: ='Master Fund Sheet'!E10 -> Building Materials (Pipes) | B17: =COUNTIFS('Master Fund Sheet'!$E$2:$E$15,$A17,'Master Fund Sheet'!$B$2:$B$15,"Large Cap") -> 0 | C17: =COUNTIFS('Master Fund Sheet'!$E$2:$E$15,$A17,'Master Fund Sheet'!$B$2:$B$15,"Mid Cap") -> 1 | D17: =COUNTIFS('Master Fund Sheet'!$E$2:$E$15,$A17,'Master Fund Sheet'!$B$2:$B$15,"Small Cap") -> 0 | E17: =SUM(B17:D17) -> 1
A18: ='Master Fund Sheet'!E11 -> Electricals (Cables & Wires) | B18: =COUNTIFS('Master Fund Sheet'!$E$2:$E$15,$A18,'Master Fund Sheet'!$B$2:$B$15,"Large Cap") -> 0 | C18: =COUNTIFS('Master Fund Sheet'!$E$2:$E$15,$A18,'Master Fund Sheet'!$B$2:$B$15,"Mid Cap") -> 1 | D18: =COUNTIFS('Master Fund Sheet'!$E$2:$E$15,$A18,'Master Fund Sheet'!$B$2:$B$15,"Small Cap") -> 0 | E18: =SUM(B18:D18) -> 1
A19: ='Master Fund Sheet'!E12 -> Footwear & Retail | B19: =COUNTIFS('Master Fund Sheet'!$E$2:$E$15,$A19,'Master Fund Sheet'!$B$2:$B$15,"Large Cap") -> 0 | C19: =COUNTIFS('Master Fund Sheet'!$E$2:$E$15,$A19,'Master Fund Sheet'!$B$2:$B$15,"Mid Cap") -> 0 | D19: =COUNTIFS('Master Fund Sheet'!$E$2:$E$15,$A19,'Master Fund Sheet'!$B$2:$B$15,"Small Cap") -> 1 | E19: =SUM(B19:D19) -> 1
A20: ='Master Fund Sheet'!E13 -> Media & Entertainment | B20: =COUNTIFS('Master Fund Sheet'!$E$2:$E$15,$A20,'Master Fund Sheet'!$B$2:$B$15,"Large Cap") -> 0 | C20: =COUNTIFS('Master Fund Sheet'!$E$2:$E$15,$A20,'Master Fund Sheet'!$B$2:$B$15,"Mid Cap") -> 0 | D20: =COUNTIFS('Master Fund Sheet'!$E$2:$E$15,$A20,'Master Fund Sheet'!$B$2:$B$15,"Small Cap") -> 1 | E20: =SUM(B20:D20) -> 1
A21: ='Master Fund Sheet'!E14 -> Internet / Local Search Services | B21: =COUNTIFS('Master Fund Sheet'!$E$2:$E$15,$A21,'Master Fund Sheet'!$B$2:$B$15,"Large Cap") -> 0 | C21: =COUNTIFS('Master Fund Sheet'!$E$2:$E$15,$A21,'Master Fund Sheet'!$B$2:$B$15,"Mid Cap") -> 0 | D21: =COUNTIFS('Master Fund Sheet'!$E$2:$E$15,$A21,'Master Fund Sheet'!$B$2:$B$15,"Small Cap") -> 1 | E21: =SUM(B21:D21) -> 1
A22: ='Master Fund Sheet'!E15 -> Hotels & Hospitality | B22: =COUNTIFS('Master Fund Sheet'!$E$2:$E$15,$A22,'Master Fund Sheet'!$B$2:$B$15,"Large Cap") -> 0 | C22: =COUNTIFS('Master Fund Sheet'!$E$2:$E$15,$A22,'Master Fund Sheet'!$B$2:$B$15,"Mid Cap") -> 0 | D22: =COUNTIFS('Master Fund Sheet'!$E$2:$E$15,$A22,'Master Fund Sheet'!$B$2:$B$15,"Small Cap") -> 1 | E22: =SUM(B22:D22) -> 1
A23: TOTAL | B23: =SUM(B9:B22) -> 7 | C23: =SUM(C9:C22) -> 3 | D23: =SUM(D9:D22) -> 4 | E23: =SUM(E9:E22) -> 14

Sheet Rebalance_Log
A1: Date | B1: Persona | C1: Action | D1: Asset_Ticker | E1: Units | F1: Price (₹) | G1: Value (₹) | H1: Reason
A2: 46309 | B2: Vikram | C2: BUY | D2: KEI | E2: 301 | F2: 4648 | G2: 1399048 | H2: Initial allocation per scoring model
A3: 46309 | B3: Vikram | C3: BUY | D3: JUSTDIAL | E3: 1757 | F3: 682.75 | G3: 1199591.8 | H3: Initial allocation per scoring model
A4: 46309 | B4: Vikram | C4: BUY | D4: EIHOTEL | E4: 4110 | F4: 291.95 | G4: 1199914.5 | H4: Initial allocation per scoring model
A5: 46309 | B5: Vikram | C5: BUY | D5: ASTRAL | E5: 692 | F5: 1443.2 | G5: 998694.4 | H5: Initial allocation per scoring model
A6: 46309 | B6: Vikram | C6: BUY | D6: DABUR | E6: 2317 | F6: 388.4 | G6: 899922.8 | H6: Initial allocation per scoring model
A7: 46309 | B7: Vikram | C7: BUY | D7: HDFCBANK | E7: 844 | F7: 710.7 | G7: 599830.8 | H7: Initial allocation per scoring model
A8: 46309 | B8: Vikram | C8: BUY | D8: INFY | E8: 551 | F8: 1088 | G8: 599488 | H8: Initial allocation per scoring model
A9: 46309 | B9: Vikram | C9: BUY | D9: SUNPHARMA | E9: 343 | F9: 1746.4 | G9: 599015.2 | H9: Initial allocation per scoring model
A10: 46309 | B10: Vikram | C10: BUY | D10: MARUTI | E10: 53 | F10: 11178 | G10: 592434 | H10: Initial allocation per scoring model
A11: 46309 | B11: Vikram | C11: BUY | D11: RELIANCE | E11: 425 | F11: 1174.6 | G11: 499205 | H11: Initial allocation per scoring model
A12: 46309 | B12: Vikram | C12: BUY | D12: TATASTEEL | E12: 2865 | F12: 174.49 | G12: 499913.85 | H12: Initial allocation per scoring model
A13: 46309 | B13: Vikram | C13: BUY | D13: ITC | E13: 1529 | F13: 261.5 | G13: 399833.5 | H13: Initial allocation per scoring model
... A56: 46309 | B56: Meera | C56: BUY | D56: SMC-NCD-2029 | E56: 1000 | F56: 1000 | G56: 1000000 | H56: Initial allocation per scoring model
A58: Log every subsequent rebalance here (BUY / SELL / TRIM), with the trigger from the persona's rebalancing rule in 'Reason'.

Sheet Monthly_Returns
A1: Month | B1: RELIANCE | C1: HDFCBANK | D1: INFY | E1: ITC | F1: SUNPHARMA | G1: MARUTI | H1: TATASTEEL | I1: DABUR | J1: ASTRAL | K1: KEI | L1: BATAINDIA | M1: ZEEL | N1: JUSTDIAL | O1: EIHOTEL | P1: NIFTY_50
A2: =Price_Data!A3 -> 44500 | B2: =Price_Data!B3/Price_Data!B2-1 -> 0.0067484071 | C2: =Price_Data!C3/Price_Data!C2-1 -> -0.0075976845 | D2: =Price_Data!D3/Price_Data!D2-1 -> 0.004379562 | E2: =Price_Data!E3/Price_Data!E2-1 -> -0.054802625 | F2: =Price_Data!F3/Price_Data!F2-1 -> -0.028414781 | G2: =Price_Data!G3/Price_Data!G2-1 -> 0.019671696 | H2: =Price_Data!H3/Price_Data!H2-1 -> 0.020962663 | I2: =Price_Data!I3/Price_Data!I2-1 -> -0.050565765 | ... P2: =Price_Data!P3/Price_Data!P2-1 -> 0.0030366412
A3: =Price_Data!A4 -> 44530 | B3: =Price_Data!B4/Price_Data!B3-1 -> -0.051588303 | C3: =Price_Data!C4/Price_Data!C3-1 -> -0.056412957 | D3: =Price_Data!D4/Price_Data!D3-1 -> 0.026920242 | E3: =Price_Data!E4/Price_Data!E3-1 -> -0.0092176387 | F3: =Price_Data!F4/Price_Data!F3-1 -> -0.052068879 | G3: =Price_Data!G4/Price_Data!G3-1 -> -0.055410629 | H3: =Price_Data!H4/Price_Data!H3-1 -> -0.18593585 | I3: =Price_Data!I4/Price_Data!I3-1 -> 0.019736245 | ... P3: =Price_Data!P4/Price_Data!P3-1 -> -0.038957879
A4: =Price_Data!A5 -> 44561 | B4: =Price_Data!B5/Price_Data!B4-1 -> -0.015484878 | C4: =Price_Data!C5/Price_Data!C4-1 -> -0.0094729763 | D4: =Price_Data!D5/Price_Data!D4-1 -> 0.10224003 | E4: =Price_Data!E5/Price_Data!E4-1 -> -0.014012519 | F4: =Price_Data!F5/Price_Data!F4-1 -> 0.12220998 | G4: =Price_Data!G5/Price_Data!G4-1 -> 0.050744876 | H4: =Price_Data!H5/Price_Data!H4-1 -> 0.037562243 | I4: =Price_Data!I5/Price_Data!I4-1 -> -0.025046696 | ... P4: =Price_Data!P5/Price_Data!P4-1 -> 0.021836285
A5: =Price_Data!A6 -> 44592 | B5: =Price_Data!B6/Price_Data!B5-1 -> 0.0077849671 | C5: =Price_Data!C6/Price_Data!C5-1 -> 0.0042617125 | D5: =Price_Data!D6/Price_Data!D5-1 -> -0.080283346 | E5: =Price_Data!E6/Price_Data!E5-1 -> 0.0098433223 | F5: =Price_Data!F6/Price_Data!F5-1 -> -0.013243059 | G5: =Price_Data!G6/Price_Data!G5-1 -> 0.15765904 | H5: =Price_Data!H6/Price_Data!H5-1 -> -0.023369849 | I5: =Price_Data!I6/Price_Data!I5-1 -> -0.07464375 | ... P5: =Price_Data!P6/Price_Data!P5-1 -> -0.0008182528
A6: =Price_Data!A7 -> 44620 | B6: =Price_Data!B7/Price_Data!B6-1 -> -0.011332834 | C6: =Price_Data!C7/Price_Data!C6-1 -> -0.040019564 | D6: =Price_Data!D7/Price_Data!D6-1 -> -0.01186434 | E6: =Price_Data!E7/Price_Data!E6-1 -> 0.0038066674 | F6: =Price_Data!F7/Price_Data!F6-1 -> 0.019237306 | G6: =Price_Data!G7/Price_Data!G6-1 -> -0.032935204 | H6: =Price_Data!H7/Price_Data!H6-1 -> 0.12455934 | I6: =Price_Data!I7/Price_Data!I6-1 -> 0.049550438 | ... P6: =Price_Data!P7/Price_Data!P6-1 -> -0.031485278
A7: =Price_Data!A8 -> 44651 | B7: =Price_Data!B8/Price_Data!B7-1 -> 0.11663922 | C7: =Price_Data!C8/Price_Data!C7-1 -> 0.030913777 | D7: =Price_Data!D8/Price_Data!D7-1 -> 0.11147743 | E7: =Price_Data!E8/Price_Data!E7-1 -> 0.1612273 | F7: =Price_Data!F8/Price_Data!F7-1 -> 0.083958151 | G7: =Price_Data!G8/Price_Data!G7-1 -> -0.090550477 | H7: =Price_Data!H8/Price_Data!H7-1 -> 0.070865394 | I7: =Price_Data!I8/Price_Data!I7-1 -> -0.048188018 | ... P7: =Price_Data!P8/Price_Data!P7-1 -> 0.039946052
A8: =Price_Data!A9 -> 44681 | B8: =Price_Data!B9/Price_Data!B8-1 -> 0.059011338 | C8: =Price_Data!C9/Price_Data!C8-1 -> -0.058316496 | D8: =Price_Data!D9/Price_Data!D8-1 -> -0.17793773 | E8: =Price_Data!E9/Price_Data!E8-1 -> 0.035526967 | F8: =Price_Data!F9/Price_Data!F8-1 -> 0.015201586 | G8: =Price_Data!G9/Price_Data!G8-1 -> 0.020697382 | H8: =Price_Data!H9/Price_Data!H8-1 -> -0.02767675 | I8: =Price_Data!I9/Price_Data!I8-1 -> 0.038232275 | ... P8: =Price_Data!P9/Price_Data!P8-1 -> -0.020738917
A9: =Price_Data!A10 -> 44712 | B9: =Price_Data!B10/Price_Data!B9-1 -> -0.05648269 | C9: =Price_Data!C10/Price_Data!C9-1 -> 0.014802809 | D9: =Price_Data!D10/Price_Data!D9-1 -> -0.030637655 | E9: =Price_Data!E10/Price_Data!E9-1 -> 0.068186162 | F9: =Price_Data!F10/Price_Data!F9-1 -> -0.073287087 | G9: =Price_Data!G10/Price_Data!G9-1 -> 0.032205499 | H9: =Price_Data!H10/Price_Data!H9-1 -> -0.16951008 | I9: =Price_Data!I10/Price_Data!I9-1 -> -0.067717344 | ... P9: =Price_Data!P10/Price_Data!P9-1 -> -0.030287881
A10: =Price_Data!A11 -> 44742 | B10: =Price_Data!B11/Price_Data!B10-1 -> -0.014047653 | C10: =Price_Data!C11/Price_Data!C10-1 -> -0.029477975 | D10: =Price_Data!D11/Price_Data!D10-1 -> -0.027733881 | E10: =Price_Data!E11/Price_Data!E10-1 -> 0.01051219 | F10: =Price_Data!F11/Price_Data!F10-1 -> -0.034859918 | G10: =Price_Data!G11/Price_Data!G10-1 -> 0.063316214 | H10: =Price_Data!H11/Price_Data!H10-1 -> -0.13424146 | I10: =Price_Data!I11/Price_Data!I10-1 -> -0.04441363 | ... P10: =Price_Data!P11/Price_Data!P10-1 -> -0.048496944
A11: =Price_Data!A12 -> 44773 | B11: =Price_Data!B12/Price_Data!B11-1 -> -0.033216516 | C11: =Price_Data!C12/Price_Data!C11-1 -> 0.06394383 | D11: =Price_Data!D12/Price_Data!D11-1 -> 0.060061934 | E11: =Price_Data!E12/Price_Data!E11-1 -> 0.10805666 | F11: =Price_Data!F12/Price_Data!F11-1 -> 0.13556557 | G11: =Price_Data!G12/Price_Data!G11-1 -> 0.035746383 | H11: =Price_Data!H12/Price_Data!H11-1 -> 0.24095927 | I11: =Price_Data!I12/Price_Data!I11-1 -> 0.18345746 | ... P11: =Price_Data!P12/Price_Data!P11-1 -> 0.087324345
A12: =Price_Data!A13 -> 44804 | B12: =Price_Data!B13/Price_Data!B12-1 -> 0.054638078 | C12: =Price_Data!C13/Price_Data!C12-1 -> 0.036193029 | D12: =Price_Data!D13/Price_Data!D12-1 -> -0.03661718 | E12: =Price_Data!E13/Price_Data!E12-1 -> 0.057568615 | F12: =Price_Data!F13/Price_Data!F12-1 -> -0.050053601 | G12: =Price_Data!G13/Price_Data!G12-1 -> 0.04200101 | H12: =Price_Data!H13/Price_Data!H12-1 -> 0.0064417178 | I12: =Price_Data!I13/Price_Data!I12-1 -> -0.00084748819 | ... P12: =Price_Data!P13/Price_Data!P12-1 -> 0.035029796
A13: =Price_Data!A14 -> 44834 | B13: =Price_Data!B14/Price_Data!B13-1 -> -0.09863432 | C13: =Price_Data!C14/Price_Data!C13-1 -> -0.04357221 | D13: =Price_Data!D14/Price_Data!D13-1 -> -0.053253277 | E13: =Price_Data!E14/Price_Data!E13-1 -> 0.036491387 | F13: =Price_Data!F14/Price_Data!F13-1 -> 0.062254229 | G13: =Price_Data!G14/Price_Data!G13-1 -> -0.027977371 | H13: =Price_Data!H14/Price_Data!H13-1 -> -0.083104744 | I13: =Price_Data!I14/Price_Data!I13-1 -> -0.018245475 | ... P13: =Price_Data!P14/Price_Data!P13-1 -> -0.037442354
... A61: =Price_Data!A62 -> 46295 | B61: =Price_Data!B62/Price_Data!B61-1 -> -0.070477682 | C61: =Price_Data!C62/Price_Data!C61-1 -> -0.00042313117 | D61: =Price_Data!D62/Price_Data!D61-1 -> -0.12321397 | E61: =Price_Data!E62/Price_Data!E61-1 -> 0.028375734 | F61: =Price_Data!F62/Price_Data!F61-1 -> -0.084744055 | G61: =Price_Data!G62/Price_Data!G61-1 -> -0.11663099 | H61: =Price_Data!H62/Price_Data!H61-1 -> -0.00027122322 | I61: =Price_Data!I62/Price_Data!I61-1 -> -0.0023622047 | ... P61: =Price_Data!P62/Price_Data!P61-1 -> -0.060628146

Sheet Price_Data
A1: Month-end | B1: RELIANCE | C1: HDFCBANK | D1: INFY | E1: ITC | F1: SUNPHARMA | G1: MARUTI | H1: TATASTEEL | I1: DABUR | J1: ASTRAL | K1: KEI | L1: BATAINDIA | M1: ZEEL | N1: JUSTDIAL | O1: EIHOTEL | P1: NIFTY_50
A2: 44469 | B2: 1141.01 | C2: 746.28 | D2: 1459.05 | E2: 185.94 | F2: 778.82 | G2: 7007.53 | H2: 111.15 | I2: 580.63 | J2: 1603.58 | K2: 920.36 | L2: 1601.42 | M2: 284.62 | N2: 989.2 | O2: 127.24 | P2: 17618.15
A3: 44500 | B3: 1148.71 | C3: 740.61 | D3: 1465.44 | E3: 175.75 | F3: 756.69 | G3: 7145.38 | H3: 113.48 | I3: 551.27 | J3: 1621.58 | K3: 906.41 | L3: 1782.72 | M3: 282.5 | N3: 797.55 | O3: 136.48 | P3: 17671.65
A4: 44530 | B4: 1089.45 | C4: 698.83 | D4: 1504.89 | E4: 174.13 | F4: 717.29 | G4: 6749.45 | H4: 92.38 | I4: 562.15 | J4: 1632.14 | K4: 1096.86 | L4: 1691.53 | M4: 304.42 | N4: 653.6 | O4: 118.43 | P4: 16983.2
A5: 44561 | B5: 1072.58 | C5: 692.21 | D5: 1658.75 | E5: 171.69 | F5: 804.95 | G5: 7091.95 | H5: 95.85 | I5: 548.07 | J5: 1694.6 | K5: 1159.55 | L5: 1685.63 | M5: 301.14 | N5: 817.05 | O5: 122.46 | P5: 17354.05
A6: 44592 | B6: 1080.93 | C6: 695.16 | D6: 1525.58 | E6: 173.38 | F6: 794.29 | G6: 8210.06 | H6: 93.61 | I6: 507.16 | J6: 1603.73 | K6: 1068.37 | L6: 1858.91 | M6: 271.8 | N6: 906.2 | O6: 138.25 | P6: 17339.85
A7: 44620 | B7: 1068.68 | C7: 667.34 | D7: 1507.48 | E7: 174.04 | F7: 809.57 | G7: 7939.66 | H7: 105.27 | I7: 532.29 | J7: 1442.06 | K7: 983.15 | L7: 1633.26 | M7: 215.2 | N7: 744.95 | O7: 127.68 | P7: 16793.9
A8: 44651 | B8: 1193.33 | C8: 687.97 | D8: 1675.53 | E8: 202.1 | F8: 877.54 | G8: 7220.72 | H8: 112.73 | I8: 506.64 | J8: 1502.36 | K8: 1254.68 | L8: 1766.46 | M8: 270.68 | N8: 711.4 | O8: 152.12 | P8: 17464.75
A9: 44681 | B9: 1263.75 | C9: 647.85 | D9: 1377.39 | E9: 209.28 | F9: 890.88 | G9: 7370.17 | H9: 109.61 | I9: 526.01 | J9: 1599.24 | K9: 1201.15 | L9: 1754.98 | M9: 232.94 | N9: 859 | O9: 157.78 | P9: 17102.55
A10: 44712 | B10: 1192.37 | C10: 657.44 | D10: 1335.19 | E10: 223.55 | F10: 825.59 | G10: 7607.53 | H10: 91.03 | I10: 490.39 | J10: 1284.76 | K10: 1230.11 | L10: 1690.72 | M10: 237.35 | N10: 661.5 | O10: 132.94 | P10: 16584.55
A11: 44742 | B11: 1175.62 | C11: 638.06 | D11: 1298.16 | E11: 225.9 | F11: 796.81 | G11: 8089.21 | H11: 78.81 | I11: 468.61 | J11: 1229.47 | K11: 1146.78 | L11: 1502.85 | M11: 200.98 | N11: 565.25 | O11: 122.86 | P11: 15780.25
A12: 44773 | B12: 1136.57 | C12: 678.86 | D12: 1376.13 | E12: 250.31 | F12: 904.83 | G12: 8378.37 | H12: 97.8 | I12: 554.58 | J12: 1348.29 | K12: 1231.8 | L12: 1766.69 | M12: 231.86 | N12: 581.25 | O12: 148.68 | P12: 17158.25
A13: 44804 | B13: 1198.67 | C13: 703.43 | D13: 1325.74 | E13: 264.72 | F13: 859.54 | G13: 8730.27 | H13: 98.43 | I13: 554.11 | J13: 1555.27 | K13: 1464.62 | L13: 1797.86 | M13: 241.3 | N13: 592.8 | O13: 157.68 | P13: 17759.3
... A62: 46295 | B62: 1187 | C62: 708.7 | D62: 994.1 | E62: 262.75 | F62: 1816.6 | G62: 11967 | H62: 184.3 | I62: 380.1 | J62: 1370.4 | K62: 4455 | L62: 618.75 | M62: 74.47 | N62: 666.15 | O62: 301.1 | P62: 22620.45
A64: Source: Yahoo Finance monthly 'Adj Close' (dividend & split adjusted), NSE tickers *.NS and ^NSEI.

Sheet Dash_Calc
A1: Persona index | B1: =MATCH(Dashboard!$C$4,'Investor Personas'!$A$3:$A$6,0) -> 1 | D1: Engine for the Dashboard - do not edit. Everything here is formula-driven from the Dashboard 'In use' column.
A2: Ticker | B2: Segment | C2: Sector | D2: Beta | E2: Price | F2: Fundamental Return | G2: Live Score | H2: Eligible | I2: CAPM | J2: Exp. Return | K2: Weight | L2: Units | M2: Invested | N2: Value at Horizon | O2: Segment eligible-score sum
A3: ='Scoring Model'!A23 -> RELIANCE | B3: ='Scoring Model'!B23 -> Large Cap | C3: ='Master Fund Sheet'!E2 -> Oil & Gas / Conglomerate | D3: ='Risk Metrics'!G2 -> 0.99084157 | E3: ='Master Fund Sheet'!I2 -> 1174.6 | F3: ='Scoring Model'!AN23 -> 0.084534118 | G3: =IF(Dashboard!$E$37>0,('Scoring Model'!P23*Dashboard!$E$24+'Scoring Model'!Q23*Dashboard!$E$25+'Scoring Model'!R23*Dashboard!$E$26+'Scoring Model'!S23*Dashboard!$E$27+'Scoring Model'!T23*Dashboard!$E$28+'Scoring Model'!U23*Dashboard!$E$29+'Scoring Model'!V23*Dashboard!$E$30+'Scoring Model'!W23*Dashboard!$E$31+'Scoring Model'!X23*Dashboard!$E$32+'Scoring Model'!Y23*Dashboard!$E$33+'Scoring Model'!Z23*Dashboard!$E$34+'Scoring Model'!AA23*Dashboard!$E$35+'Scoring Model'!AB23*Dashboard!$E$36)/Dashboard!$E$37,0) -> 50.384615 | H3: =IF(AND(G3>=Dashboard!$E$15,D3<=Dashboard!$E$14),1,0) -> 1 | I3: =Dashboard!$E$19+D3*Dashboard!$E$20 -> 0.14285891 | J3: ='Investor Personas'!$C$11*I3+(1-'Investor Personas'!$C$11)*F3+(G3-50)/50*Dashboard!$E$21 -> 0.11392728 | K3: =IF(AND(H3=1,O3>0),Dashboard!$E$10*INDEX($D$22:$D$24,MATCH(B3,$A$22:$A$24,0))*G3/O3,0) -> 0.049561928 | L3: =IF(E3>0,ROUNDDOWN(K3*Dashboard!$E$7/E3,0),0) -> 421 | M3: =L3*E3 -> 494506.6 | N3: =M3*(1+J3)^Dashboard!$E$9 -> 683506.45 | O3: =SUMIFS($G$3:$G$16,$B$3:$B$16,B3,$H$3:$H$16,1) -> 386.30769
A4: ='Scoring Model'!A24 -> HDFCBANK | B4: ='Scoring Model'!B24 -> Large Cap | C4: ='Master Fund Sheet'!E3 -> Private Sector Banking | D4: ='Risk Metrics'!G3 -> 0.884506 | E4: ='Master Fund Sheet'!I3 -> 710.7 | F4: ='Scoring Model'!AN24 -> 0.11985423 | G4: =IF(Dashboard!$E$37>0,('Scoring Model'!P24*Dashboard!$E$24+'Scoring Model'!Q24*Dashboard!$E$25+'Scoring Model'!R24*Dashboard!$E$26+'Scoring Model'!S24*Dashboard!$E$27+'Scoring Model'!T24*Dashboard!$E$28+'Scoring Model'!U24*Dashboard!$E$29+'Scoring Model'!V24*Dashboard!$E$30+'Scoring Model'!W24*Dashboard!$E$31+'Scoring Model'!X24*Dashboard!$E$32+'Scoring Model'!Y24*Dashboard!$E$33+'Scoring Model'!Z24*Dashboard!$E$34+'Scoring Model'!AA24*Dashboard!$E$35+'Scoring Model'!AB24*Dashboard!$E$36)/Dashboard!$E$37,0) -> 55.403846 | H4: =IF(AND(G4>=Dashboard!$E$15,D4<=Dashboard!$E$14),1,0) -> 1 | I4: =Dashboard!$E$19+D4*Dashboard!$E$20 -> 0.13541542 | J4: ='Investor Personas'!$C$11*I4+(1-'Investor Personas'!$C$11)*F4+(G4-50)/50*Dashboard!$E$21 -> 0.13087713 | K4: =IF(AND(H4=1,O4>0),Dashboard!$E$10*INDEX($D$22:$D$24,MATCH(B4,$A$22:$A$24,0))*G4/O4,0) -> 0.054499204 | L4: =IF(E4>0,ROUNDDOWN(K4*Dashboard!$E$7/E4,0),0) -> 766 | M4: =L4*E4 -> 544396.2 | N4: =M4*(1+J4)^Dashboard!$E$9 -> 787338.26 | O4: =SUMIFS($G$3:$G$16,$B$3:$B$16,B4,$H$3:$H$16,1) -> 386.30769
A5: ='Scoring Model'!A25 -> INFY | B5: ='Scoring Model'!B25 -> Large Cap | C5: ='Master Fund Sheet'!E4 -> IT Services | D5: ='Risk Metrics'!G4 -> 0.75751049 | E5: ='Master Fund Sheet'!I4 -> 1088 | F5: ='Scoring Model'!AN25 -> 0.15696027 | G5: =IF(Dashboard!$E$37>0,('Scoring Model'!P25*Dashboard!$E$24+'Scoring Model'!Q25*Dashboard!$E$25+'Scoring Model'!R25*Dashboard!$E$26+'Scoring Model'!S25*Dashboard!$E$27+'Scoring Model'!T25*Dashboard!$E$28+'Scoring Model'!U25*Dashboard!$E$29+'Scoring Model'!V25*Dashboard!$E$30+'Scoring Model'!W25*Dashboard!$E$31+'Scoring Model'!X25*Dashboard!$E$32+'Scoring Model'!Y25*Dashboard!$E$33+'Scoring Model'!Z25*Dashboard!$E$34+'Scoring Model'!AA25*Dashboard!$E$35+'Scoring Model'!AB25*Dashboard!$E$36)/Dashboard!$E$37,0) -> 62.538462 | H5: =IF(AND(G5>=Dashboard!$E$15,D5<=Dashboard!$E$14),1,0) -> 1 | I5: =Dashboard!$E$19+D5*Dashboard!$E$20 -> 0.12652573 | J5: ='Investor Personas'!$C$11*I5+(1-'Investor Personas'!$C$11)*F5+(G5-50)/50*Dashboard!$E$21 -> 0.14926608 | K5: =IF(AND(H5=1,O5>0),Dashboard!$E$10*INDEX($D$22:$D$24,MATCH(B5,$A$22:$A$24,0))*G5/O5,0) -> 0.061517324 | L5: =IF(E5>0,ROUNDDOWN(K5*Dashboard!$E$7/E5,0),0) -> 565 | M5: =L5*E5 -> 614720 | N5: =M5*(1+J5)^Dashboard!$E$9 -> 933123.46 | O5: =SUMIFS($G$3:$G$16,$B$3:$B$16,B5,$H$3:$H$16,1) -> 386.30769
A6: ='Scoring Model'!A26 -> ITC | B6: ='Scoring Model'!B26 -> Large Cap | C6: ='Master Fund Sheet'!E5 -> FMCG (Cigarettes, Foods, Agri) | D6: ='Risk Metrics'!G5 -> 0.81842432 | E6: ='Master Fund Sheet'!I5 -> 261.5 | F6: ='Scoring Model'!AN26 -> 0.080041525 | G6: =IF(Dashboard!$E$37>0,('Scoring Model'!P26*Dashboard!$E$24+'Scoring Model'!Q26*Dashboard!$E$25+'Scoring Model'!R26*Dashboard!$E$26+'Scoring Model'!S26*Dashboard!$E$27+'Scoring Model'!T26*Dashboard!$E$28+'Scoring Model'!U26*Dashboard!$E$29+'Scoring Model'!V26*Dashboard!$E$30+'Scoring Model'!W26*Dashboard!$E$31+'Scoring Model'!X26*Dashboard!$E$32+'Scoring Model'!Y26*Dashboard!$E$33+'Scoring Model'!Z26*Dashboard!$E$34+'Scoring Model'!AA26*Dashboard!$E$35+'Scoring Model'!AB26*Dashboard!$E$36)/Dashboard!$E$37,0) -> 42.75 | H6: =IF(AND(G6>=Dashboard!$E$15,D6<=Dashboard!$E$14),1,0) -> 1 | I6: =Dashboard!$E$19+D6*Dashboard!$E$20 -> 0.1307897 | J6: ='Investor Personas'!$C$11*I6+(1-'Investor Personas'!$C$11)*F6+(G6-50)/50*Dashboard!$E$21 -> 0.10106561 | K6: =IF(AND(H6=1,O6>0),Dashboard!$E$10*INDEX($D$22:$D$24,MATCH(B6,$A$22:$A$24,0))*G6/O6,0) -> 0.042051971 | L6: =IF(E6>0,ROUNDDOWN(K6*Dashboard!$E$7/E6,0),0) -> 1608 | M6: =L6*E6 -> 420492 | N6: =M6*(1+J6)^Dashboard!$E$9 -> 561302.97 | O6: =SUMIFS($G$3:$G$16,$B$3:$B$16,B6,$H$3:$H$16,1) -> 386.30769
A7: ='Scoring Model'!A27 -> SUNPHARMA | B7: ='Scoring Model'!B27 -> Large Cap | C7: ='Master Fund Sheet'!E6 -> Pharmaceuticals | D7: ='Risk Metrics'!G6 -> 0.87112781 | E7: ='Master Fund Sheet'!I6 -> 1746.4 | F7: ='Scoring Model'!AN27 -> 0.11820415 | G7: =IF(Dashboard!$E$37>0,('Scoring Model'!P27*Dashboard!$E$24+'Scoring Model'!Q27*Dashboard!$E$25+'Scoring Model'!R27*Dashboard!$E$26+'Scoring Model'!S27*Dashboard!$E$27+'Scoring Model'!T27*Dashboard!$E$28+'Scoring Model'!U27*Dashboard!$E$29+'Scoring Model'!V27*Dashboard!$E$30+'Scoring Model'!W27*Dashboard!$E$31+'Scoring Model'!X27*Dashboard!$E$32+'Scoring Model'!Y27*Dashboard!$E$33+'Scoring Model'!Z27*Dashboard!$E$34+'Scoring Model'!AA27*Dashboard!$E$35+'Scoring Model'!AB27*Dashboard!$E$36)/Dashboard!$E$37,0) -> 61.519231 | H7: =IF(AND(G7>=Dashboard!$E$15,D7<=Dashboard!$E$14),1,0) -> 1 | I7: =Dashboard!$E$19+D7*Dashboard!$E$20 -> 0.13447895 | J7: ='Investor Personas'!$C$11*I7+(1-'Investor Personas'!$C$11)*F7+(G7-50)/50*Dashboard!$E$21 -> 0.13325309 | K7: =IF(AND(H7=1,O7>0),Dashboard!$E$10*INDEX($D$22:$D$24,MATCH(B7,$A$22:$A$24,0))*G7/O7,0) -> 0.060514735 | L7: =IF(E7>0,ROUNDDOWN(K7*Dashboard!$E$7/E7,0),0) -> 346 | M7: =L7*E7 -> 604254.4 | N7: =M7*(1+J7)^Dashboard!$E$9 -> 879428.54 | O7: =SUMIFS($G$3:$G$16,$B$3:$B$16,B7,$H$3:$H$16,1) -> 386.30769
A8: ='Scoring Model'!A28 -> MARUTI | B8: ='Scoring Model'!B28 -> Large Cap | C8: ='Master Fund Sheet'!E7 -> Automobiles (Passenger Vehicles) | D8: ='Risk Metrics'!G7 -> 0.68561437 | E8: ='Master Fund Sheet'!I7 -> 11178 | F8: ='Scoring Model'!AN28 -> 0.11167408 | G8: =IF(Dashboard!$E$37>0,('Scoring Model'!P28*Dashboard!$E$24+'Scoring Model'!Q28*Dashboard!$E$25+'Scoring Model'!R28*Dashboard!$E$26+'Scoring Model'!S28*Dashboard!$E$27+'Scoring Model'!T28*Dashboard!$E$28+'Scoring Model'!U28*Dashboard!$E$29+'Scoring Model'!V28*Dashboard!$E$30+'Scoring Model'!W28*Dashboard!$E$31+'Scoring Model'!X28*Dashboard!$E$32+'Scoring Model'!Y28*Dashboard!$E$33+'Scoring Model'!Z28*Dashboard!$E$34+'Scoring Model'!AA28*Dashboard!$E$35+'Scoring Model'!AB28*Dashboard!$E$36)/Dashboard!$E$37,0) -> 60.211538 | H8: =IF(AND(G8>=Dashboard!$E$15,D8<=Dashboard!$E$14),1,0) -> 1 | I8: =Dashboard!$E$19+D8*Dashboard!$E$20 -> 0.12149301 | J8: ='Investor Personas'!$C$11*I8+(1-'Investor Personas'!$C$11)*F8+(G8-50)/50*Dashboard!$E$21 -> 0.12271047 | K8: =IF(AND(H8=1,O8>0),Dashboard!$E$10*INDEX($D$22:$D$24,MATCH(B8,$A$22:$A$24,0))*G8/O8,0) -> 0.059228395 | L8: =IF(E8>0,ROUNDDOWN(K8*Dashboard!$E$7/E8,0),0) -> 52 | M8: =L8*E8 -> 581256 | N8: =M8*(1+J8)^Dashboard!$E$9 -> 822566.02 | O8: =SUMIFS($G$3:$G$16,$B$3:$B$16,B8,$H$3:$H$16,1) -> 386.30769
A9: ='Scoring Model'!A29 -> TATASTEEL | B9: ='Scoring Model'!B29 -> Large Cap | C9: ='Master Fund Sheet'!E8 -> Metals & Mining (Steel) | D9: ='Risk Metrics'!G8 -> 1.1923044 | E9: ='Master Fund Sheet'!I8 -> 174.49 | F9: ='Scoring Model'!AN29 -> 0.08695424 | G9: =IF(Dashboard!$E$37>0,('Scoring Model'!P29*Dashboard!$E$24+'Scoring Model'!Q29*Dashboard!$E$25+'Scoring Model'!R29*Dashboard!$E$26+'Scoring Model'!S29*Dashboard!$E$27+'Scoring Model'!T29*Dashboard!$E$28+'Scoring Model'!U29*Dashboard!$E$29+'Scoring Model'!V29*Dashboard!$E$30+'Scoring Model'!W29*Dashboard!$E$31+'Scoring Model'!X29*Dashboard!$E$32+'Scoring Model'!Y29*Dashboard!$E$33+'Scoring Model'!Z29*Dashboard!$E$34+'Scoring Model'!AA29*Dashboard!$E$35+'Scoring Model'!AB29*Dashboard!$E$36)/Dashboard!$E$37,0) -> 53.5 | H9: =IF(AND(G9>=Dashboard!$E$15,D9<=Dashboard!$E$14),1,0) -> 1 | I9: =Dashboard!$E$19+D9*Dashboard!$E$20 -> 0.15696131 | J9: ='Investor Personas'!$C$11*I9+(1-'Investor Personas'!$C$11)*F9+(G9-50)/50*Dashboard!$E$21 -> 0.12405777 | K9: =IF(AND(H9=1,O9>0),Dashboard!$E$10*INDEX($D$22:$D$24,MATCH(B9,$A$22:$A$24,0))*G9/O9,0) -> 0.052626444 | L9: =IF(E9>0,ROUNDDOWN(K9*Dashboard!$E$7/E9,0),0) -> 3016 | M9: =L9*E9 -> 526261.84 | N9: =M9*(1+J9)^Dashboard!$E$9 -> 747425.28 | O9: =SUMIFS($G$3:$G$16,$B$3:$B$16,B9,$H$3:$H$16,1) -> 386.30769
A10: ='Scoring Model'!A30 -> DABUR | B10: ='Scoring Model'!B30 -> Mid Cap | C10: ='Master Fund Sheet'!E9 -> Personal Care & Ayurveda | D10: ='Risk Metrics'!G9 -> 0.869804 | E10: ='Master Fund Sheet'!I9 -> 388.4 | F10: ='Scoring Model'!AN30 -> 0.067448331 | G10: =IF(Dashboard!$E$37>0,('Scoring Model'!P30*Dashboard!$E$24+'Scoring Model'!Q30*Dashboard!$E$25+'Scoring Model'!R30*Dashboard!$E$26+'Scoring Model'!S30*Dashboard!$E$27+'Scoring Model'!T30*Dashboard!$E$28+'Scoring Model'!U30*Dashboard!$E$29+'Scoring Model'!V30*Dashboard!$E$30+'Scoring Model'!W30*Dashboard!$E$31+'Scoring Model'!X30*Dashboard!$E$32+'Scoring Model'!Y30*Dashboard!$E$33+'Scoring Model'!Z30*Dashboard!$E$34+'Scoring Model'!AA30*Dashboard!$E$35+'Scoring Model'!AB30*Dashboard!$E$36)/Dashboard!$E$37,0) -> 44.403846 | H10: =IF(AND(G10>=Dashboard!$E$15,D10<=Dashboard!$E$14),1,0) -> 1 | I10: =Dashboard!$E$19+D10*Dashboard!$E$20 -> 0.13438628 | J10: ='Investor Personas'!$C$11*I10+(1-'Investor Personas'!$C$11)*F10+(G10-50)/50*Dashboard!$E$21 -> 0.097559613 | K10: =IF(AND(H10=1,O10>0),Dashboard!$E$10*INDEX($D$22:$D$24,MATCH(B10,$A$22:$A$24,0))*G10/O10,0) -> 0.09326318 | L10: =IF(E10>0,ROUNDDOWN(K10*Dashboard!$E$7/E10,0),0) -> 2401 | M10: =L10*E10 -> 932548.4 | N10: =M10*(1+J10)^Dashboard!$E$9 -> 1232979.2 | O10: =SUMIFS($G$3:$G$16,$B$3:$B$16,B10,$H$3:$H$16,1) -> 158.30769
A11: ='Scoring Model'!A31 -> ASTRAL | B11: ='Scoring Model'!B31 -> Mid Cap | C11: ='Master Fund Sheet'!E10 -> Building Materials (Pipes) | D11: ='Risk Metrics'!G10 -> 0.69741418 | E11: ='Master Fund Sheet'!I10 -> 1443.2 | F11: ='Scoring Model'!AN31 -> 0.11477795 | G11: =IF(Dashboard!$E$37>0,('Scoring Model'!P31*Dashboard!$E$24+'Scoring Model'!Q31*Dashboard!$E$25+'Scoring Model'!R31*Dashboard!$E$26+'Scoring Model'!S31*Dashboard!$E$27+'Scoring Model'!T31*Dashboard!$E$28+'Scoring Model'!U31*Dashboard!$E$29+'Scoring Model'!V31*Dashboard!$E$30+'Scoring Model'!W31*Dashboard!$E$31+'Scoring Model'!X31*Dashboard!$E$32+'Scoring Model'!Y31*Dashboard!$E$33+'Scoring Model'!Z31*Dashboard!$E$34+'Scoring Model'!AA31*Dashboard!$E$35+'Scoring Model'!AB31*Dashboard!$E$36)/Dashboard!$E$37,0) -> 45.423077 | H11: =IF(AND(G11>=Dashboard!$E$15,D11<=Dashboard!$E$14),1,0) -> 1 | I11: =Dashboard!$E$19+D11*Dashboard!$E$20 -> 0.12231899 | J11: ='Investor Personas'!$C$11*I11+(1-'Investor Personas'!$C$11)*F11+(G11-50)/50*Dashboard!$E$21 -> 0.11580232 | K11: =IF(AND(H11=1,O11>0),Dashboard!$E$10*INDEX($D$22:$D$24,MATCH(B11,$A$22:$A$24,0))*G11/O11,0) -> 0.095403912 | L11: =IF(E11>0,ROUNDDOWN(K11*Dashboard!$E$7/E11,0),0) -> 661 | M11: =L11*E11 -> 953955.2 | N11: =M11*(1+J11)^Dashboard!$E$9 -> 1325225.4 | O11: =SUMIFS($G$3:$G$16,$B$3:$B$16,B11,$H$3:$H$16,1) -> 158.30769
A12: ='Scoring Model'!A32 -> KEI | B12: ='Scoring Model'!B32 -> Mid Cap | C12: ='Master Fund Sheet'!E11 -> Electricals (Cables & Wires) | D12: ='Risk Metrics'!G11 -> 1.4331655 | E12: ='Master Fund Sheet'!I11 -> 4648 | F12: ='Scoring Model'!AN32 -> 0.14144787 | G12: =IF(Dashboard!$E$37>0,('Scoring Model'!P32*Dashboard!$E$24+'Scoring Model'!Q32*Dashboard!$E$25+'Scoring Model'!R32*Dashboard!$E$26+'Scoring Model'!S32*Dashboard!$E$27+'Scoring Model'!T32*Dashboard!$E$28+'Scoring Model'!U32*Dashboard!$E$29+'Scoring Model'!V32*Dashboard!$E$30+'Scoring Model'!W32*Dashboard!$E$31+'Scoring Model'!X32*Dashboard!$E$32+'Scoring Model'!Y32*Dashboard!$E$33+'Scoring Model'!Z32*Dashboard!$E$34+'Scoring Model'!AA32*Dashboard!$E$35+'Scoring Model'!AB32*Dashboard!$E$36)/Dashboard!$E$37,0) -> 68.480769 | H12: =IF(AND(G12>=Dashboard!$E$15,D12<=Dashboard!$E$14),1,0) -> 1 | I12: =Dashboard!$E$19+D12*Dashboard!$E$20 -> 0.17382158 | J12: ='Investor Personas'!$C$11*I12+(1-'Investor Personas'!$C$11)*F12+(G12-50)/50*Dashboard!$E$21 -> 0.16872319 | K12: =IF(AND(H12=1,O12>0),Dashboard!$E$10*INDEX($D$22:$D$24,MATCH(B12,$A$22:$A$24,0))*G12/O12,0) -> 0.14383291 | L12: =IF(E12>0,ROUNDDOWN(K12*Dashboard!$E$7/E12,0),0) -> 309 | M12: =L12*E12 -> 1436232 | N12: =M12*(1+J12)^Dashboard!$E$9 -> 2292765.2 | O12: =SUMIFS($G$3:$G$16,$B$3:$B$16,B12,$H$3:$H$16,1) -> 158.30769
A13: ='Scoring Model'!A33 -> BATAINDIA | B13: ='Scoring Model'!B33 -> Small Cap | C13: ='Master Fund Sheet'!E12 -> Footwear & Retail | D13: ='Risk Metrics'!G12 -> 1.2813252 | E13: ='Master Fund Sheet'!I12 -> 619.35 | F13: ='Scoring Model'!AN33 -> 0.026340354 | G13: =IF(Dashboard!$E$37>0,('Scoring Model'!P33*Dashboard!$E$24+'Scoring Model'!Q33*Dashboard!$E$25+'Scoring Model'!R33*Dashboard!$E$26+'Scoring Model'!S33*Dashboard!$E$27+'Scoring Model'!T33*Dashboard!$E$28+'Scoring Model'!U33*Dashboard!$E$29+'Scoring Model'!V33*Dashboard!$E$30+'Scoring Model'!W33*Dashboard!$E$31+'Scoring Model'!X33*Dashboard!$E$32+'Scoring Model'!Y33*Dashboard!$E$33+'Scoring Model'!Z33*Dashboard!$E$34+'Scoring Model'!AA33*Dashboard!$E$35+'Scoring Model'!AB33*Dashboard!$E$36)/Dashboard!$E$37,0) -> 20.038462 | H13: =IF(AND(G13>=Dashboard!$E$15,D13<=Dashboard!$E$14),1,0) -> 0 | I13: =Dashboard!$E$19+D13*Dashboard!$E$20 -> 0.16319277 | J13: ='Investor Personas'!$C$11*I13+(1-'Investor Personas'!$C$11)*F13+(G13-50)/50*Dashboard!$E$21 -> 0.076789637 | K13: =IF(AND(H13=1,O13>0),Dashboard!$E$10*INDEX($D$22:$D$24,MATCH(B13,$A$22:$A$24,0))*G13/O13,0) -> 0 | L13: =IF(E13>0,ROUNDDOWN(K13*Dashboard!$E$7/E13,0),0) -> 0 | M13: =L13*E13 -> 0 | N13: =M13*(1+J13)^Dashboard!$E$9 -> 0 | O13: =SUMIFS($G$3:$G$16,$B$3:$B$16,B13,$H$3:$H$16,1) -> 106.46154
A14: ='Scoring Model'!A34 -> ZEEL | B14: ='Scoring Model'!B34 -> Small Cap | C14: ='Master Fund Sheet'!E13 -> Media & Entertainment | D14: ='Risk Metrics'!G13 -> 1.6233346 | E14: ='Master Fund Sheet'!I13 -> 73.81 | F14: ='Scoring Model'!AN34 -> 0.028500061 | G14: =IF(Dashboard!$E$37>0,('Scoring Model'!P34*Dashboard!$E$24+'Scoring Model'!Q34*Dashboard!$E$25+'Scoring Model'!R34*Dashboard!$E$26+'Scoring Model'!S34*Dashboard!$E$27+'Scoring Model'!T34*Dashboard!$E$28+'Scoring Model'!U34*Dashboard!$E$29+'Scoring Model'!V34*Dashboard!$E$30+'Scoring Model'!W34*Dashboard!$E$31+'Scoring Model'!X34*Dashboard!$E$32+'Scoring Model'!Y34*Dashboard!$E$33+'Scoring Model'!Z34*Dashboard!$E$34+'Scoring Model'!AA34*Dashboard!$E$35+'Scoring Model'!AB34*Dashboard!$E$36)/Dashboard!$E$37,0) -> 20.423077 | H14: =IF(AND(G14>=Dashboard!$E$15,D14<=Dashboard!$E$14),1,0) -> 0 | I14: =Dashboard!$E$19+D14*Dashboard!$E$20 -> 0.18713342 | J14: ='Investor Personas'!$C$11*I14+(1-'Investor Personas'!$C$11)*F14+(G14-50)/50*Dashboard!$E$21 -> 0.090070587 | K14: =IF(AND(H14=1,O14>0),Dashboard!$E$10*INDEX($D$22:$D$24,MATCH(B14,$A$22:$A$24,0))*G14/O14,0) -> 0 | L14: =IF(E14>0,ROUNDDOWN(K14*Dashboard!$E$7/E14,0),0) -> 0 | M14: =L14*E14 -> 0 | N14: =M14*(1+J14)^Dashboard!$E$9 -> 0 | O14: =SUMIFS($G$3:$G$16,$B$3:$B$16,B14,$H$3:$H$16,1) -> 106.46154
... A16: ='Scoring Model'!A36 -> EIHOTEL | B16: ='Scoring Model'!B36 -> Small Cap | C16: ='Master Fund Sheet'!E15 -> Hotels & Hospitality | D16: ='Risk Metrics'!G15 -> 1.1041444 | E16: ='Master Fund Sheet'!I15 -> 291.95 | F16: ='Scoring Model'!AN36 -> 0.13112838 | G16: =IF(Dashboard!$E$37>0,('Scoring Model'!P36*Dashboard!$E$24+'Scoring Model'!Q36*Dashboard!$E$25+'Scoring Model'!R36*Dashboard!$E$26+'Scoring Model'!S36*Dashboard!$E$27+'Scoring Model'!T36*Dashboard!$E$28+'Scoring Model'!U36*Dashboard!$E$29+'Scoring Model'!V36*Dashboard!$E$30+'Scoring Model'!W36*Dashboard!$E$31+'Scoring Model'!X36*Dashboard!$E$32+'Scoring Model'!Y36*Dashboard!$E$33+'Scoring Model'!Z36*Dashboard!$E$34+'Scoring Model'!AA36*Dashboard!$E$35+'Scoring Model'!AB36*Dashboard!$E$36)/Dashboard!$E$37,0) -> 55.153846 | H16: =IF(AND(G16>=Dashboard!$E$15,D16<=Dashboard!$E$14),1,0) -> 1 | I16: =Dashboard!$E$19+D16*Dashboard!$E$20 -> 0.15079011 | J16: ='Investor Personas'!$C$11*I16+(1-'Investor Personas'!$C$11)*F16+(G16-50)/50*Dashboard!$E$21 -> 0.14405155 | K16: =IF(AND(H16=1,O16>0),Dashboard!$E$10*INDEX($D$22:$D$24,MATCH(B16,$A$22:$A$24,0))*G16/O16,0) -> 0.1230401 | L16: =IF(E16>0,ROUNDDOWN(K16*Dashboard!$E$7/E16,0),0) -> 4214 | M16: =L16*E16 -> 1230277.3 | N16: =M16*(1+J16)^Dashboard!$E$9 -> 1842212.8 | O16: =SUMIFS($G$3:$G$16,$B$3:$B$16,B16,$H$3:$H$16,1) -> 106.46154
A17: ='Master Fund Sheet'!C18 -> GSEC-3Y | B17: Debt | C17: ='Master Fund Sheet'!G18 -> Sovereign (SOV) | D17: 0 | E17: ='Master Fund Sheet'!H18 -> 100 | H17: =IF(K17>0,1,0) -> 0 | J17: ='Master Fund Sheet'!M18 -> 0.0707 | K17: =IF(SUM(Dashboard!$E$16:$E$18)>0,(1-Dashboard!$E$10)*Dashboard!$E$16/SUM(Dashboard!$E$16:$E$18),0) -> 0 | L17: =IF(E17>0,ROUNDDOWN(K17*Dashboard!$E$7/E17,0),0) -> 0 | M17: =L17*E17 -> 0 | N17: =M17*(1+J17)^Dashboard!$E$9 -> 0
A18: ='Master Fund Sheet'!C19 -> RIL-NCD-2036 | B18: Debt | C18: ='Master Fund Sheet'!G19 -> CRISIL AAA / CARE AAA | D18: 0 | E18: ='Master Fund Sheet'!H19 -> 100000 | H18: =IF(K18>0,1,0) -> 0 | J18: ='Master Fund Sheet'!M19 -> 0.07875 | K18: =IF(SUM(Dashboard!$E$16:$E$18)>0,(1-Dashboard!$E$10)*Dashboard!$E$17/SUM(Dashboard!$E$16:$E$18),0) -> 0 | L18: =IF(E18>0,ROUNDDOWN(K18*Dashboard!$E$7/E18,0),0) -> 0 | M18: =L18*E18 -> 0 | N18: =M18*(1+J18)^Dashboard!$E$9 -> 0
A19: ='Master Fund Sheet'!C20 -> SMC-NCD-2029 | B19: Debt | C19: ='Master Fund Sheet'!G20 -> ICRA A (Stable) | D19: 0 | E19: ='Master Fund Sheet'!H20 -> 1000 | H19: =IF(K19>0,1,0) -> 1 | J19: ='Master Fund Sheet'!M20 -> 0.0945 | K19: =IF(SUM(Dashboard!$E$16:$E$18)>0,(1-Dashboard!$E$10)*Dashboard!$E$18/SUM(Dashboard!$E$16:$E$18),0) -> 0.05 | L19: =IF(E19>0,ROUNDDOWN(K19*Dashboard!$E$7/E19,0),0) -> 500 | M19: =L19*E19 -> 500000 | N19: =M19*(1+J19)^Dashboard!$E$9 -> 655567.33
A21: Segment | B21: Policy share | C21: Has eligible stock | D21: Effective share | E21: Actual weight
A22: Large Cap | B22: =Dashboard!$E$11 -> 0.4 | C22: =IF(COUNTIFS($B$3:$B$16,A22,$H$3:$H$16,1)>0,1,0) -> 1 | D22: =IF(SUMPRODUCT($B$22:$B$24,$C$22:$C$24)>0,B22*C22/SUMPRODUCT($B$22:$B$24,$C$22:$C$24),0) -> 0.4 | E22: =SUMIF($B$3:$B$16,A22,$M$3:$M$16)/Dashboard!$E$7 -> 0.3785887
A23: Mid Cap | B23: =Dashboard!$E$12 -> 0.35 | C23: =IF(COUNTIFS($B$3:$B$16,A23,$H$3:$H$16,1)>0,1,0) -> 1 | D23: =IF(SUMPRODUCT($B$22:$B$24,$C$22:$C$24)>0,B23*C23/SUMPRODUCT($B$22:$B$24,$C$22:$C$24),0) -> 0.35 | E23: =SUMIF($B$3:$B$16,A23,$M$3:$M$16)/Dashboard!$E$7 -> 0.33227356
A24: Small Cap | B24: =Dashboard!$E$13 -> 0.25 | C24: =IF(COUNTIFS($B$3:$B$16,A24,$H$3:$H$16,1)>0,1,0) -> 1 | D24: =IF(SUMPRODUCT($B$22:$B$24,$C$22:$C$24)>0,B24*C24/SUMPRODUCT($B$22:$B$24,$C$22:$C$24),0) -> 0.25 | E24: =SUMIF($B$3:$B$16,A24,$M$3:$M$16)/Dashboard!$E$7 -> 0.23745663
A25: Debt | E25: =SUM(M17:M19)/Dashboard!$E$7 -> 0.05
A26: Cash | E26: =(Dashboard!$E$7-SUM(M3:M19))/Dashboard!$E$7 -> 0.001681106
A28: Invested | B28: =SUM(M3:M19) -> 9983188.9 | D28: Largest position | E28: =MAX(K3:K19) -> 0.14383291
A29: Cash residual | B29: =Dashboard!$E$7-B28 -> 16811.06 | D29: Largest position name | E29: =INDEX(A3:A19,MATCH(E28,K3:K19,0)) -> KEI
A30: Projected value | B30: =SUM(N3:N19)+B29*(1+'Master Fund Sheet'!$I$18)^Dashboard!$E$9 -> 14451037 | D30: Backtest CAGR (5Y) | E30: =(D112/100)^(12/60)-1 -> 0.10828102
A31: Expected CAGR | B31: =(B30/Dashboard!$E$7)^(1/Dashboard!$E$9)-1 -> 0.13057575 | D31: Backtest max drawdown | E31: =MIN(F53:F112) -> -0.21017469
A32: Required CAGR | B32: =(Dashboard!$E$8/Dashboard!$E$7)^(1/Dashboard!$E$9)-1 -> 0.29066288 | D32: NIFTY CAGR (5Y) | E32: =(E112/100)^(12/60)-1 -> 0.051255274
A33: Surplus / (shortfall) | B33: =B30-Dashboard!$E$8 -> -7048963.3 | D33: Weight check | E33: =SUM(K3:K19) -> 1
A34: Portfolio beta | B34: =SUMPRODUCT(M3:M19,D3:D19)/Dashboard!$E$7 -> 0.9695613
A35: Volatility (5Y history) | B35: =STDEV(B53:B112)*SQRT(12) -> 0.16169608
A36: Sharpe (expected) | B36: =IF(B35>0,(B31-Dashboard!$E$19)/B35,0) -> 0.35298169
A37: Probability of target | B37: =IF(B35>0,1-NORMSDIST((LN(Dashboard!$E$8/Dashboard!$E$7)-LN(1+B31)*Dashboard!$E$9)/(B35*SQRT(Dashboard!$E$9))),0) -> 0.078015433
A38: Stocks held | B38: =COUNTIF(K3:K16,">0") -> 12
A39: Preset policy table (segment split of equity, debt mix as share of debt sleeve)
A40: Parameter | B40: Vikram | C40: Ananya | D40: Rohan | E40: Meera
A41: Large-cap share | B41: 0.4 | C41: 0.5 | D41: 0.65 | E41: 0.8
A42: Mid-cap share | B42: 0.35 | C42: 0.3 | D42: 0.25 | E42: 0.15
A43: Small-cap share | B43: 0.25 | C43: 0.2 | D43: 0.1 | E43: 0.05
A44: 3Y G-Sec share of debt | B44: 0 | C44: 0.34 | D44: 0.43 | E44: 0.5
A45: RIL AAA share of debt | B45: 0 | C45: 0.33 | D45: 0.34 | E45: 0.33
A46: SMC A share of debt | B46: 1 | C46: 0.33 | D46: 0.23 | E46: 0.17
A47: Backtest weights (horizontal)
B48: =A3 -> RELIANCE | C48: =A4 -> HDFCBANK | D48: =A5 -> INFY | E48: =A6 -> ITC | F48: =A7 -> SUNPHARMA | G48: =A8 -> MARUTI | H48: =A9 -> TATASTEEL | I48: =A10 -> DABUR | J48: =A11 -> ASTRAL | K48: =A12 -> KEI | L48: =A13 -> BATAINDIA | M48: =A14 -> ZEEL | N48: =A15 -> JUSTDIAL | O48: =A16 -> EIHOTEL | P48: Debt wt | Q48: Debt yld
B49: =K3 -> 0.049561928 | C49: =K4 -> 0.054499204 | D49: =K5 -> 0.061517324 | E49: =K6 -> 0.042051971 | F49: =K7 -> 0.060514735 | G49: =K8 -> 0.059228395 | H49: =K9 -> 0.052626444 | I49: =K10 -> 0.09326318 | J49: =K11 -> 0.095403912 | K49: =K12 -> 0.14383291 | L49: =K13 -> 0 | M49: =K14 -> 0 | N49: =K15 -> 0.1144599 | O49: =K16 -> 0.1230401 | P49: =SUM(K17:K19) -> 0.05 | Q49: =IF(P49>0,SUMPRODUCT(K17:K19,J17:J19)/P49,0) -> 0.0945
A51: Month | B51: Portfolio return | C51: NIFTY return | D51: Portfolio ₹100 | E51: NIFTY ₹100 | F51: Drawdown
A52: Start | D52: 100 | E52: 100
A53: =Monthly_Returns!A2 -> 44500 | B53: =SUMPRODUCT($B$49:$O$49,Monthly_Returns!B2:O2)+$P$49*$Q$49/12 -> -0.020238039 | C53: =Monthly_Returns!P2 -> 0.0030366412 | D53: =D52*(1+B53) -> 97.976196 | E53: =E52*(1+C53) -> 100.30366 | F53: =D53/MAX(D$52:D53)-1 -> -0.020238039
A54: =Monthly_Returns!A3 -> 44530 | B54: =SUMPRODUCT($B$49:$O$49,Monthly_Returns!B3:O3)+$P$49*$Q$49/12 -> -0.024435114 | C54: =Monthly_Returns!P3 -> -0.038957879 | D54: =D53*(1+B54) -> 95.582137 | E54: =E53*(1+C54) -> 96.396046 | F54: =D54/MAX(D$52:D54)-1 -> -0.044178634
A55: =Monthly_Returns!A4 -> 44561 | B55: =SUMPRODUCT($B$49:$O$49,Monthly_Returns!B4:O4)+$P$49*$Q$49/12 -> 0.059534405 | C55: =Monthly_Returns!P4 -> 0.021836285 | D55: =D54*(1+B55) -> 101.27256 | E55: =E54*(1+C55) -> 98.500978 | F55: =D55/MAX(D$52:D55)-1 -> 0
A56: =Monthly_Returns!A5 -> 44592 | B56: =SUMPRODUCT($B$49:$O$49,Monthly_Returns!B5:O5)+$P$49*$Q$49/12 -> 0.0087598006 | C56: =Monthly_Returns!P5 -> -0.0008182528 | D56: =D55*(1+B56) -> 102.15969 | E56: =E55*(1+C56) -> 98.420379 | F56: =D56/MAX(D$52:D56)-1 -> 0
A57: =Monthly_Returns!A6 -> 44620 | B57: =SUMPRODUCT($B$49:$O$49,Monthly_Returns!B6:O6)+$P$49*$Q$49/12 -> -0.043393744 | C57: =Monthly_Returns!P6 -> -0.031485278 | D57: =D56*(1+B57) -> 97.726598 | E57: =E56*(1+C57) -> 95.321586 | F57: =D57/MAX(D$52:D57)-1 -> -0.043393744
A58: =Monthly_Returns!A7 -> 44651 | B58: =SUMPRODUCT($B$49:$O$49,Monthly_Returns!B7:O7)+$P$49*$Q$49/12 -> 0.082560484 | C58: =Monthly_Returns!P7 -> 0.039946052 | D58: =D57*(1+B58) -> 105.79495 | E58: =E57*(1+C58) -> 99.129307 | F58: =D58/MAX(D$52:D58)-1 -> 0
A59: =Monthly_Returns!A8 -> 44681 | B59: =SUMPRODUCT($B$49:$O$49,Monthly_Returns!B8:O8)+$P$49*$Q$49/12 -> 0.023284478 | C59: =Monthly_Returns!P8 -> -0.020738917 | D59: =D58*(1+B59) -> 108.25833 | E59: =E58*(1+C59) -> 97.073473 | F59: =D59/MAX(D$52:D59)-1 -> 0
A60: =Monthly_Returns!A9 -> 44712 | B60: =SUMPRODUCT($B$49:$O$49,Monthly_Returns!B9:O9)+$P$49*$Q$49/12 -> -0.0793599 | C60: =Monthly_Returns!P9 -> -0.030287881 | D60: =D59*(1+B60) -> 99.666963 | E60: =E59*(1+C60) -> 94.133323 | F60: =D60/MAX(D$52:D60)-1 -> -0.0793599
A61: =Monthly_Returns!A10 -> 44742 | B61: =SUMPRODUCT($B$49:$O$49,Monthly_Returns!B10:O10)+$P$49*$Q$49/12 -> -0.052572109 | C61: =Monthly_Returns!P10 -> -0.048496944 | D61: =D60*(1+B61) -> 94.427261 | E61: =E60*(1+C61) -> 89.568144 | F61: =D61/MAX(D$52:D61)-1 -> -0.12775989
A62: =Monthly_Returns!A11 -> 44773 | B62: =SUMPRODUCT($B$49:$O$49,Monthly_Returns!B11:O11)+$P$49*$Q$49/12 -> 0.099564171 | C62: =Monthly_Returns!P11 -> 0.087324345 | D62: =D61*(1+B62) -> 103.82883 | E62: =E61*(1+C62) -> 97.389624 | F62: =D62/MAX(D$52:D62)-1 -> -0.040916029
A63: =Monthly_Returns!A12 -> 44804 | B63: =SUMPRODUCT($B$49:$O$49,Monthly_Returns!B12:O12)+$P$49*$Q$49/12 -> 0.056514808 | C63: =Monthly_Returns!P12 -> 0.035029796 | D63: =D62*(1+B63) -> 109.6967 | E63: =E62*(1+C63) -> 100.80116 | F63: =D63/MAX(D$52:D63)-1 -> 0
A64: =Monthly_Returns!A13 -> 44834 | B64: =SUMPRODUCT($B$49:$O$49,Monthly_Returns!B13:O13)+$P$49*$Q$49/12 -> 0.0073217787 | C64: =Monthly_Returns!P13 -> -0.037442354 | D64: =D63*(1+B64) -> 110.49987 | E64: =E63*(1+C64) -> 97.02693 | F64: =D64/MAX(D$52:D64)-1 -> 0
... A112: =Monthly_Returns!A61 -> 46295 | B112: =SUMPRODUCT($B$49:$O$49,Monthly_Returns!B61:O61)+$P$49*$Q$49/12 -> -0.062404392 | C112: =Monthly_Returns!P61 -> -0.060628146 | D112: =D111*(1+B112) -> 167.20508 | E112: =E111*(1+C112) -> 128.39288 | F112: =D112/MAX(D$52:D112)-1 -> -0.17600215
A115: Year | B115: Expected path | C115: Target path | D115: Downside (-1σ) | E115: Upside (+1σ)
A116: Year 0 | B116: =Dashboard!$E$7*(1+$B$31)^(0*Dashboard!$E$9/3) -> 10000000 | C116: =Dashboard!$E$7*(1+$B$32)^(0*Dashboard!$E$9/3) -> 10000000 | D116: =B116*EXP(-$B$35*SQRT(0*Dashboard!$E$9/3)) -> 10000000 | E116: =B116*EXP($B$35*SQRT(0*Dashboard!$E$9/3)) -> 10000000
A117: Year 1 | B117: =Dashboard!$E$7*(1+$B$31)^(1*Dashboard!$E$9/3) -> 11305758 | C117: =Dashboard!$E$7*(1+$B$32)^(1*Dashboard!$E$9/3) -> 12906629 | D117: =B117*EXP(-$B$35*SQRT(1*Dashboard!$E$9/3)) -> 9617804.7 | E117: =B117*EXP($B$35*SQRT(1*Dashboard!$E$9/3)) -> 13289951
A118: Year 2 | B118: =Dashboard!$E$7*(1+$B$31)^(2*Dashboard!$E$9/3) -> 12782015 | C118: =Dashboard!$E$7*(1+$B$32)^(2*Dashboard!$E$9/3) -> 16658107 | D118: =B118*EXP(-$B$35*SQRT(2*Dashboard!$E$9/3)) -> 10169228 | E118: =B118*EXP($B$35*SQRT(2*Dashboard!$E$9/3)) -> 16066107
A119: Year 3 | B119: =Dashboard!$E$7*(1+$B$31)^(3*Dashboard!$E$9/3) -> 14451037 | C119: =Dashboard!$E$7*(1+$B$32)^(3*Dashboard!$E$9/3) -> 21500000 | D119: =B119*EXP(-$B$35*SQRT(3*Dashboard!$E$9/3)) -> 10921140 | E119: =B119*EXP($B$35*SQRT(3*Dashboard!$E$9/3)) -> 19121856
